Workbook
Name _______CAP10: {"LC",#N/A,FALSE,"FC-15 Cap Expend"}
Name _______new3: {"FY98Q1 nvs",#N/A,FALSE,"FY98 - Q1";"FY98Q2 nvs",#N/A,FALSE,"FY98 - Q2";"FY98Q3 nvs",#N/A,FALSE,"FY98 - Q3";"FY98Q4 nvs",#N/A,FALSE,"FY98 - Q4"}
Name _______new4: {"INPUT",#N/A,FALSE,"REVENUE AND GM ";"CONTROL",#N/A,FALSE,"REVENUE AND GM ";"SWITCH",#N/A,FALSE,"REVENUE AND GM ";"OUTPUT",#N/A,FALSE,"REVENUE AND GM ";"TOTAL",#N/A,FALSE,"REVENUE AND GM "}
Name _______new5: {"FY97Total",#N/A,FALSE,"FY97 - Total";"FY98Total",#N/A,FALSE,"FY98 - Total"}
Name _______new6: {"FY97Q1",#N/A,FALSE,"FY97 - Q1";"FY97Q2",#N/A,FALSE,"FY97 - Q2";"FY97Q3",#N/A,FALSE,"FY97 - Q3";"FY97Q4",#N/A,FALSE,"FY97 - Q4"}
Name ______CAP10: {"LC",#N/A,FALSE,"FC-15 Cap Expend"}
Name ______DP6434: {"TOTALDPAK",#N/A,FALSE,"DPAK PRODUCTION";"HADPAK",#N/A,FALSE,"DPAK PRODUCTION";"PSIDPAK",#N/A,FALSE,"DPAK PRODUCTION"}
Name ______new3: {"FY98Q1 nvs",#N/A,FALSE,"FY98 - Q1";"FY98Q2 nvs",#N/A,FALSE,"FY98 - Q2";"FY98Q3 nvs",#N/A,FALSE,"FY98 - Q3";"FY98Q4 nvs",#N/A,FALSE,"FY98 - Q4"}
Name ______new4: {"INPUT",#N/A,FALSE,"REVENUE AND GM ";"CONTROL",#N/A,FALSE,"REVENUE AND GM ";"SWITCH",#N/A,FALSE,"REVENUE AND GM ";"OUTPUT",#N/A,FALSE,"REVENUE AND GM ";"TOTAL",#N/A,FALSE,"REVENUE AND GM "}
Name ______new5: {"FY97Total",#N/A,FALSE,"FY97 - Total";"FY98Total",#N/A,FALSE,"FY98 - Total"}
Name ______new6: {"FY97Q1",#N/A,FALSE,"FY97 - Q1";"FY97Q2",#N/A,FALSE,"FY97 - Q2";"FY97Q3",#N/A,FALSE,"FY97 - Q3";"FY97Q4",#N/A,FALSE,"FY97 - Q4"}
Name ______TEM6434: {"ALLOCATION1",#N/A,FALSE,"EXPENSE ALLOCATIONS";"ALLOCATION2",#N/A,FALSE,"EXPENSE ALLOCATIONS";"ALLOCATION3",#N/A,FALSE,"EXPENSE ALLOCATIONS";"ALLOCATION4",#N/A,FALSE,"EXPENSE ALLOCATIONS"}
Name _____a2: {#N/A,#N/A,FALSE,"Sheet1"}
Name _____a3: {#N/A,#N/A,FALSE,"Sheet1"}
Name _____ALL6434: {"ALLOCATION1",#N/A,FALSE,"EXPENSE ALLOCATIONS";"ALLOCATION2",#N/A,FALSE,"EXPENSE ALLOCATIONS";"ALLOCATION3",#N/A,FALSE,"EXPENSE ALLOCATIONS";"ALLOCATION4",#N/A,FALSE,"EXPENSE ALLOCATIONS"}
Name _____CAP10: {"LC",#N/A,FALSE,"FC-15 Cap Expend"}
Name _____DP6434: {"TOTALDPAK",#N/A,FALSE,"DPAK PRODUCTION";"HADPAK",#N/A,FALSE,"DPAK PRODUCTION";"PSIDPAK",#N/A,FALSE,"DPAK PRODUCTION"}
Name _____new2: {"FY97Q1 nvs",#N/A,FALSE,"FY97 - Q1";"FY97Q2 nvs",#N/A,FALSE,"FY97 - Q2";"FY97Q3 nvs",#N/A,FALSE,"FY97 - Q3";"FY97Q4 nvs",#N/A,FALSE,"FY97 - Q4"}
Name _____new3: {"FY98Q1 nvs",#N/A,FALSE,"FY98 - Q1";"FY98Q2 nvs",#N/A,FALSE,"FY98 - Q2";"FY98Q3 nvs",#N/A,FALSE,"FY98 - Q3";"FY98Q4 nvs",#N/A,FALSE,"FY98 - Q4"}
Name _____new4: {"INPUT",#N/A,FALSE,"REVENUE AND GM ";"CONTROL",#N/A,FALSE,"REVENUE AND GM ";"SWITCH",#N/A,FALSE,"REVENUE AND GM ";"OUTPUT",#N/A,FALSE,"REVENUE AND GM ";"TOTAL",#N/A,FALSE,"REVENUE AND GM "}
Name _____new5: {"FY97Total",#N/A,FALSE,"FY97 - Total";"FY98Total",#N/A,FALSE,"FY98 - Total"}
Name _____new6: {"FY97Q1",#N/A,FALSE,"FY97 - Q1";"FY97Q2",#N/A,FALSE,"FY97 - Q2";"FY97Q3",#N/A,FALSE,"FY97 - Q3";"FY97Q4",#N/A,FALSE,"FY97 - Q4"}
Name _____TEM6434: {"ALLOCATION1",#N/A,FALSE,"EXPENSE ALLOCATIONS";"ALLOCATION2",#N/A,FALSE,"EXPENSE ALLOCATIONS";"ALLOCATION3",#N/A,FALSE,"EXPENSE ALLOCATIONS";"ALLOCATION4",#N/A,FALSE,"EXPENSE ALLOCATIONS"}
Name ____a2: {#N/A,#N/A,FALSE,"Sheet1"}
Name ____a3: {#N/A,#N/A,FALSE,"Sheet1"}
Name ____ALL6434: {"ALLOCATION1",#N/A,FALSE,"EXPENSE ALLOCATIONS";"ALLOCATION2",#N/A,FALSE,"EXPENSE ALLOCATIONS";"ALLOCATION3",#N/A,FALSE,"EXPENSE ALLOCATIONS";"ALLOCATION4",#N/A,FALSE,"EXPENSE ALLOCATIONS"}
Name ____CAP10: {"LC",#N/A,FALSE,"FC-15 Cap Expend"}
Name ____DP6434: {"TOTALDPAK",#N/A,FALSE,"DPAK PRODUCTION";"HADPAK",#N/A,FALSE,"DPAK PRODUCTION";"PSIDPAK",#N/A,FALSE,"DPAK PRODUCTION"}
Name ____new2: {"FY97Q1 nvs",#N/A,FALSE,"FY97 - Q1";"FY97Q2 nvs",#N/A,FALSE,"FY97 - Q2";"FY97Q3 nvs",#N/A,FALSE,"FY97 - Q3";"FY97Q4 nvs",#N/A,FALSE,"FY97 - Q4"}
Name ____new3: {"FY98Q1 nvs",#N/A,FALSE,"FY98 - Q1";"FY98Q2 nvs",#N/A,FALSE,"FY98 - Q2";"FY98Q3 nvs",#N/A,FALSE,"FY98 - Q3";"FY98Q4 nvs",#N/A,FALSE,"FY98 - Q4"}
Name ____new4: {"INPUT",#N/A,FALSE,"REVENUE AND GM ";"CONTROL",#N/A,FALSE,"REVENUE AND GM ";"SWITCH",#N/A,FALSE,"REVENUE AND GM ";"OUTPUT",#N/A,FALSE,"REVENUE AND GM ";"TOTAL",#N/A,FALSE,"REVENUE AND GM "}
Name ____new5: {"FY97Total",#N/A,FALSE,"FY97 - Total";"FY98Total",#N/A,FALSE,"FY98 - Total"}
Name ____new6: {"FY97Q1",#N/A,FALSE,"FY97 - Q1";"FY97Q2",#N/A,FALSE,"FY97 - Q2";"FY97Q3",#N/A,FALSE,"FY97 - Q3";"FY97Q4",#N/A,FALSE,"FY97 - Q4"}
Name ____TEM6434: {"ALLOCATION1",#N/A,FALSE,"EXPENSE ALLOCATIONS";"ALLOCATION2",#N/A,FALSE,"EXPENSE ALLOCATIONS";"ALLOCATION3",#N/A,FALSE,"EXPENSE ALLOCATIONS";"ALLOCATION4",#N/A,FALSE,"EXPENSE ALLOCATIONS"}
Name ___a2: {#N/A,#N/A,FALSE,"Sheet1"}
Name ___a3: {#N/A,#N/A,FALSE,"Sheet1"}
Name ___ALL6434: {"ALLOCATION1",#N/A,FALSE,"EXPENSE ALLOCATIONS";"ALLOCATION2",#N/A,FALSE,"EXPENSE ALLOCATIONS";"ALLOCATION3",#N/A,FALSE,"EXPENSE ALLOCATIONS";"ALLOCATION4",#N/A,FALSE,"EXPENSE ALLOCATIONS"}
Name ___CAP10: {"LC",#N/A,FALSE,"FC-15 Cap Expend"}
Name ___DP6434: {"TOTALDPAK",#N/A,FALSE,"DPAK PRODUCTION";"HADPAK",#N/A,FALSE,"DPAK PRODUCTION";"PSIDPAK",#N/A,FALSE,"DPAK PRODUCTION"}
Name ___new2: {"FY97Q1 nvs",#N/A,FALSE,"FY97 - Q1";"FY97Q2 nvs",#N/A,FALSE,"FY97 - Q2";"FY97Q3 nvs",#N/A,FALSE,"FY97 - Q3";"FY97Q4 nvs",#N/A,FALSE,"FY97 - Q4"}
Name ___new3: {"FY98Q1 nvs",#N/A,FALSE,"FY98 - Q1";"FY98Q2 nvs",#N/A,FALSE,"FY98 - Q2";"FY98Q3 nvs",#N/A,FALSE,"FY98 - Q3";"FY98Q4 nvs",#N/A,FALSE,"FY98 - Q4"}
Name ___new4: {"INPUT",#N/A,FALSE,"REVENUE AND GM ";"CONTROL",#N/A,FALSE,"REVENUE AND GM ";"SWITCH",#N/A,FALSE,"REVENUE AND GM ";"OUTPUT",#N/A,FALSE,"REVENUE AND GM ";"TOTAL",#N/A,FALSE,"REVENUE AND GM "}
Name ___new5: {"FY97Total",#N/A,FALSE,"FY97 - Total";"FY98Total",#N/A,FALSE,"FY98 - Total"}
Name ___new6: {"FY97Q1",#N/A,FALSE,"FY97 - Q1";"FY97Q2",#N/A,FALSE,"FY97 - Q2";"FY97Q3",#N/A,FALSE,"FY97 - Q3";"FY97Q4",#N/A,FALSE,"FY97 - Q4"}
Name ___TEM6434: {"ALLOCATION1",#N/A,FALSE,"EXPENSE ALLOCATIONS";"ALLOCATION2",#N/A,FALSE,"EXPENSE ALLOCATIONS";"ALLOCATION3",#N/A,FALSE,"EXPENSE ALLOCATIONS";"ALLOCATION4",#N/A,FALSE,"EXPENSE ALLOCATIONS"}
Name __123Graph_A: #REF!
Name __123Graph_ACURRENT: #REF!
Name __123Graph_APROCEEDS: #REF!
Name __123Graph_ASALESTREND: #REF!
Name __123Graph_B: #REF!
Name __123Graph_BCURRENT: #REF!
Name __123Graph_BPROCEEDS: #REF!
Name __123Graph_C: #REF!
Name __123Graph_CPROCEEDS: #REF!
Name __123Graph_D: #REF!
Name __123Graph_E: #REF!
Name __123Graph_F: #REF!
Name __123Graph_LBL_ASALESTREND: #REF!
Name __123Graph_X: #REF!
Name __123Graph_XCURRENT: #REF!

Sheet DEFINITIONS
B2: DEFINITION OF EACH LINE ITEM
A3: x | B3: OPERATING CASH INFLOWS
B4: Operating Cash Receipts
B5: Customer Cash Receipts from A/R | C5: Pulled from AR Aging report
B6: Customer Forecasted Receipts from Backlog | C6: Receipts for products/services that are in backlog and sale is not complete; pulled from ERP/MRP/Other infrastructure
B7: Customer Forecasted Receipts from Sales Forecast | C7: Forecasted receipts from products / services in pipeline; pulled from Salesforce and/or sales team reports built off Salesforce
B8: Other, non-customer related inflows | C8: Non-customer related inflows; this could include insurance payments, legal settlements, asset disposal, etc.
B9: TOTAL INCOMING CASH
A11: x | B11: OPERATING CASH DISBURSEMENTS
B12: Must Pays
B13: Wages and benefits | C13: Weekly payroll (Salary + all benefits + bonus accruals + etc.); pulled from payroll systems
B14: Rent | C14: Rental invoice (vs. accrued rent)
B15: Insurance | C15: Insurance Invoice
B16: Sales Tax Expense | C16: Sales tax expense - payment cadence and date varies per nexus
B17: Credit Card Expense | C17: Credit card expense - payment is on autopayment
B18: Other | C18: Other, non-material weekly, monthly, or quarterly 'must pays'
B19: Total Must Pay
B20: Accounts Payable
B21: Payables by week | C21: Pulled from AP Aging report
B22: Recurring Non Inventory Payables not in Aging report | C22: Payables that recur that are not related to inventory and do not show up in AP aging report
B23: Estimated Inventory AP from Open Purchase Orders | C23: Forecast of cash outlays for AP on open purchase orders
B24: Estimated Inventory AP from MRP estimated purchases | C24: Forecast of cash outlays for AP on orders in MRP and/or forecasted for following 13 weeks
B25: Total Accounts Payable
B26: TOTAL OPERATING CASH OUTFLOWS
A28: x | B28: OPERATING CASH FLOW (excl. financing activities) | C28: Forecasted cashflow from operations - does not include financing activities
A30: x | B30: FUNDING REQUEST
B31: Tide Rock Capital Funding (LT Notes Payable) | C31: LT funding request for CapEx
B32: Tide Rock Cashflow Funding (ST Notes Payable) | C32: ST funding request for Working Capital
B33: TOTAL FUNDING REQUEST
A35: x | B35: NON OPERATING CASH DISBURSEMENTS
B36: Tide Rock Notes Repayment | C36: Identify repayment plan and months for payment
B37: Tide Rock Interest Payments | C37: Tide Rock interest payments on outstanding line of credit
B38: Tide Rock Distributions (including MPs) | C38: Tide Rock distribution payments
A40: x | B40: NET CASH FLOW | C40: Net cashflow when including financing activities
B42: Beginning Bank Balance | C42: Cash balance across all operating accounts
B43: Outstanding checks | C43: Outstanding checks that have been sent but not cashed by time of forecast
A45: x | B45: ENDING BOOK BALANCE | C45: Ending bank balance across all operating accounts

Sheet CURRENT FORECAST START DATE
B4: Forecast Start Date | C4: 45971
C5: This should be the Monday of the first week you are forecasting (i.e., the Monday you send this to your accounting contact)

Sheet Weekly Spend
O3: =IF(O8='CURRENT FORECAST START DATE'!$C$4,"CURRENT WEEK","") | P3: =IF(P8='CURRENT FORECAST START DATE'!$C$4,"CURRENT WEEK","") | Q3: =IF(Q8='CURRENT FORECAST START DATE'!$C$4,"CURRENT WEEK","") | R3: =IF(R8='CURRENT FORECAST START DATE'!$C$4,"CURRENT WEEK","") | S3: =IF(S8='CURRENT FORECAST START DATE'!$C$4,"CURRENT WEEK","") | T3: =IF(T8='CURRENT FORECAST START DATE'!$C$4,"CURRENT WEEK","") | U3: =IF(U8='CURRENT FORECAST START DATE'!$C$4,"CURRENT WEEK","") | V3: =IF(V8='CURRENT FORECAST START DATE'!$C$4,"CURRENT WEEK","") | ... CV3: =IF(CV8='CURRENT FORECAST START DATE'!$C$4,"CURRENT WEEK","")
H4: Labor | J4: Labor | L4: =H4 -> Labor | M4: =I4 -> 0 | O4: =J4 -> Labor | P4: =K4 -> 0 | Q4: =L4 -> Labor | R4: =M4 -> 0 | S4: =O4 -> Labor | T4: =P4 -> 0 | U4: =Q4 -> Labor | V4: =R4 -> 0 | W4: =S4 -> Labor | X4: =T4 -> 0 | Y4: =U4 -> Labor | Z4: =V4 -> 0 | ... CV4: =CR4 -> 0
G5: =WEEKNUM(G7) -> 14 | H5: =WEEKNUM(H7) -> 14 | I5: =WEEKNUM(I7) -> 18 | J5: =WEEKNUM(J7)&YEAR(J7) -> 182025 | K5: =WEEKNUM(K7)&YEAR(K7) -> 182025 | L5: =WEEKNUM(L7)&YEAR(L7) -> 182025 | M5: =WEEKNUM(M7)&YEAR(M7) -> 222025 | O5: =WEEKNUM(O7)&YEAR(O7) -> 222025 | P5: =WEEKNUM(P7)&YEAR(P7) -> 222025 | Q5: =WEEKNUM(Q7)&YEAR(Q7) -> 222025 | R5: =WEEKNUM(R7)&YEAR(R7) -> 272025 | S5: =WEEKNUM(S7)&YEAR(S7) -> 272025 | T5: =WEEKNUM(T7)&YEAR(T7) -> 272025 | U5: =WEEKNUM(U7)&YEAR(U7) -> 272025 | V5: =WEEKNUM(V7)&YEAR(V7) -> 272025 | ... CV5: =WEEKNUM(CV7)&YEAR(CV7) -> 532026
G6: =WEEKNUM(G8) -> 13 | H6: =WEEKNUM(H8) -> 14 | I6: =WEEKNUM(I8) -> 15 | J6: =WEEKNUM(J8)&YEAR(J8) -> 162025 | K6: =WEEKNUM(K8)&YEAR(K8) -> 172025 | L6: =WEEKNUM(L8)&YEAR(L8) -> 182025 | M6: =WEEKNUM(M8)&YEAR(M8) -> 192025 | O6: =WEEKNUM(O8)&YEAR(O8) -> 202025 | P6: =WEEKNUM(P8)&YEAR(P8) -> 212025 | Q6: =WEEKNUM(Q8)&YEAR(Q8) -> 222025 | R6: =WEEKNUM(R8)&YEAR(R8) -> 232025 | S6: =WEEKNUM(S8)&YEAR(S8) -> 242025 | T6: =WEEKNUM(T8)&YEAR(T8) -> 252025 | U6: =WEEKNUM(U8)&YEAR(U8) -> 262025 | V6: =WEEKNUM(V8)&YEAR(V8) -> 272025 | ... CV6: =WEEKNUM(CV8)&YEAR(CV8) -> 532026
F7: Month End | G7: =EOMONTH(G8,0) -> 45747 | H7: =EOMONTH(H8,0) -> 45747 | I7: =EOMONTH(I8,0) -> 45777 | J7: =EOMONTH(J8,0) -> 45777 | K7: =EOMONTH(K8,0) -> 45777 | L7: =EOMONTH(L8,0) -> 45777 | M7: =EOMONTH(M8,0) -> 45808 | N7: 2025 YTG | O7: =EOMONTH(O8,0) -> 45808 | P7: =EOMONTH(P8,0) -> 45808 | Q7: =EOMONTH(Q8,0) -> 45808 | R7: =EOMONTH(R8,0) -> 45838 | S7: =EOMONTH(S8,0) -> 45838 | T7: =EOMONTH(T8,0) -> 45838 | U7: =EOMONTH(U8,0) -> 45838 | V7: =EOMONTH(V8,0) -> 45838 | ... CV7: =EOMONTH(CV8,0) -> 46387
F8: Week Start | G8: 45740 | H8: =+G8+7 -> 45747 | I8: =+H8+7 -> 45754 | J8: =+I8+7 -> 45761 | K8: =+J8+7 -> 45768 | L8: =+K8+7 -> 45775 | M8: =+L8+7 -> 45782 | O8: =+M8+7 -> 45789 | P8: =+O8+7 -> 45796 | Q8: =+P8+7 -> 45803 | R8: =+Q8+7 -> 45810 | S8: =+R8+7 -> 45817 | T8: =+S8+7 -> 45824 | U8: =+T8+7 -> 45831 | V8: =+U8+7 -> 45838 | W8: =+V8+7 -> 45845 | ... CV8: =+CU8+7 -> 46384
A9: Source | B9: Order | C9: ID | D9: Vendor | E9: Type | F9: Category | G9: =G23 -> 0 | H9: =H23 -> 0 | I9: =I23 -> 0 | J9: =J23 -> 0 | K9: =K23 -> 0 | L9: =L23 -> 0 | M9: =M23 -> 5000 | O9: =O23 -> 0 | P9: =P23 -> 0 | Q9: =Q23 -> 0 | R9: =R23 -> 0 | S9: =S23 -> 0 | T9: =T23 -> 0 | U9: =U23 -> 100 | V9: =V23 -> 0 | ... AI9: =AI23 -> 0 | AJ9: hju | AK9: =AK23 -> 0 | AL9: =AL23 -> 15000 | AM9: =AM23 -> 0 | AN9: =AN23 -> 0 | AO9: =AO23 -> 10378 | AP9: =AP23 -> 0 | AQ9: =AQ23 -> 0 | AR9: =AR23 -> 0 | ... CV9: =CV23 -> 0
A10: ST Cash File (Manual) | B10: =_xlfn.SINGLE(_xlfn.XLOOKUP(F10, $F$87:$F$95, $E$87:$E$95)) -> 6 | C10: K31 | D10: Askey | E10: Q20 | F10: Inventory | H10: 530470 | N10: =SUMIF($O$8:$AV$8,">="&'CURRENT FORECAST START DATE'!$C$4,'Weekly Spend'!O10:AV10) -> 0 | O10: 561009 | P10: 0 | Q10: 0 | R10: 0 | S10: 0 | T10: 0 | U10: 0 | V10: 0 | W10: 0 | X10: 0 | Y10: 294525 | AA10: 0 | AB10: 0 | AC10: 0 | AD10: 0 | AE10: 0 | AF10: 0 | AG10: 0 | AH10: 0 | AI10: 0 | AJ10: 0 | AK10: 0 | AL10: 0 | AM10: 0 | AN10: 0 | AO10: 0 | AP10: 0 | AQ10: 0 | AR10: 0 | AS10: 0 | AT10: 0 | AU10: 0 | AV10: 0 | AW10: 0 | AX10: 0 | AY10: 0 | AZ10: 0 | BA10: 0 | BB10: 0 | BC10: 0 | BD10: 0 | BE10: 0 | BF10: 0 | BG10: 0 | BH10: 0 | BI10: 0 | BJ10: 0 | BK10: 0 | BL10: 0 | BM10: 0 | BN10: 0 | BO10: 0 | BP10: 0 | BQ10: 0 | BR10: 0 | BS10: 0 | BT10: 0 | BU10: 0 | BV10: 0 | BW10: 0 | BX10: 0 | BY10: 0 | BZ10: 0 | CA10: 0 | CB10: 0 | CC10: 0 | CD10: 0 | CE10: 0 | CF10: 0 | CG10: 0 | CH10: 0 | CI10: 0 | CJ10: 0 | CK10: 0 | CL10: 0 | CM10: 0 | CN10: 0 | CO10: 0 | CP10: 0 | CQ10: 0 | CR10: 0 | CS10: 0 | CT10: 0 | CU10: 0 | CV10: 0
D11: Askey | E11: Q20RoW | F11: Inventory | N11: =SUMIF($O$8:$AV$8,">="&'CURRENT FORECAST START DATE'!$C$4,'Weekly Spend'!O11:AV11) -> 0 | O11: 0 | P11: 0 | Q11: 0 | R11: 0 | S11: 0 | T11: 0 | U11: 0 | V11: 0 | W11: 0 | X11: 0 | Y11: 0 | Z11: 0 | AA11: 0 | AB11: 0 | AC11: 0 | AD11: 0 | AE11: 0 | AF11: 0 | AG11: 0 | AH11: 0 | AI11: 0 | AJ11: 0 | AK11: 0 | AL11: 0 | AM11: 0 | AN11: 0 | AO11: 0 | AP11: 0 | AQ11: 0 | AR11: 0 | AS11: 0 | AT11: 0 | AU11: 0 | AV11: 0 | AW11: 0 | AX11: 0 | AY11: 0 | AZ11: 0 | BA11: 0 | BB11: 0 | BC11: 0 | BD11: 0 | BE11: 0 | BF11: 0 | BG11: 0 | BH11: 0 | BI11: 0 | BJ11: 0 | BK11: 0 | BL11: 0 | BM11: 0 | BN11: 0 | BO11: 0 | BP11: 0 | BQ11: 0 | BR11: 0 | BS11: 0 | BT11: 0 | BU11: 0 | BV11: 0 | BW11: 0 | BX11: 0 | BY11: 0 | BZ11: 0 | CA11: 0 | CB11: 0 | CC11: 0 | CD11: 0 | CE11: 0 | CF11: 0 | CG11: 0 | CH11: 0 | CI11: 0 | CJ11: 0 | CK11: 0 | CL11: 0 | CM11: 0 | CN11: 0 | CO11: 0 | CP11: 0 | CQ11: 0 | CR11: 0 | CS11: 0 | CT11: 0 | CU11: 0 | CV11: 0
A12: ST Cash File (Manual) | B12: =_xlfn.SINGLE(_xlfn.XLOOKUP(F12, $F$87:$F$95, $E$87:$E$95)) -> 6 | C12: K30 | D12: T&W | E12: PO3 | F12: Inventory | J12: 365500 | M12: 0 | N12: =SUMIF($O$8:$AV$8,">="&'CURRENT FORECAST START DATE'!$C$4,'Weekly Spend'!O12:AV12) -> 29050 | O12: 0 | P12: 0 | Q12: 0 | R12: 0 | S12: =446000+35000 -> 481000 | T12: 0 | U12: 0 | V12: 0 | W12: 0 | X12: 0 | Y12: 0 | Z12: 0 | AA12: 0 | AB12: 0 | AC12: 0 | AD12: 0 | AE12: 0 | AF12: 0 | AG12: 0 | AH12: 0 | AI12: 0 | AJ12: 0 | AK12: 0 | AL12: 0 | AM12: 0 | AN12: 0 | AO12: 29050 | AP12: 0 | AQ12: 0 | AR12: 0 | AS12: 0 | AT12: 0 | AU12: 0 | AV12: 0 | AW12: 0 | AY12: 0 | AZ12: 35000 | BA12: 0 | BB12: 0 | BC12: 0 | BD12: 0 | BE12: 0 | BF12: 0 | BG12: 0 | BH12: 0 | BI12: 0 | BJ12: 0 | BK12: 0 | BL12: 0 | BM12: 0 | BN12: 0 | BO12: 0 | BP12: 0 | BQ12: 0 | BR12: 0 | BS12: 0 | BT12: 0 | BU12: 0 | BV12: 0 | BW12: 0 | BX12: 0 | BY12: 0 | BZ12: 0 | CA12: 0 | CB12: 0 | CC12: 0 | CD12: 0 | CE12: 0 | CF12: 0 | CG12: 0 | CH12: 0 | CI12: 0 | CJ12: 0 | CK12: 0 | CL12: 0 | CM12: 0 | CN12: 0 | CO12: 0 | CP12: 0 | CQ12: 0 | CR12: 0 | CS12: 0 | CT12: 0 | CU12: 0 | CV12: 0
A13: ST Cash File (Manual) | B13: =_xlfn.SINGLE(_xlfn.XLOOKUP(F13, $F$87:$F$95, $E$87:$E$95)) -> 6 | C13: K35 | D13: Compal (CBN) | E13: B15 Inventory | F13: Inventory | N13: =SUMIF($O$8:$AV$8,">="&'CURRENT FORECAST START DATE'!$C$4,'Weekly Spend'!O13:AV13) -> 17000 | O13: 0 | P13: 0 | Q13: 0 | R13: 0 | S13: 0 | T13: 0 | U13: 0 | V13: 0 | W13: 0 | X13: 189950 | Y13: 0 | Z13: 0 | AA13: 0 | AB13: 0 | AC13: =56500+313466 -> 369966 | AE13: 0 | AH13: 0 | AI13: 14000 | AJ13: 0 | AK13: 0 | AL13: 0 | AN13: 14000 | AO13: 0 | AP13: 0 | AQ13: =200*85 -> 17000 | AR13: 0 | AS13: 0 | AT13: 0 | AU13: 0 | AW13: 221429 | AX13: =844300-274450 -> 569850 | AY13: 0 | BB13: 0 | BC13: 0 | BD13: =AV13 -> 0 | BE13: =AW13 -> 221429 | BF13: 0 | BG13: 0 | BH13: 0 | BK13: 0 | BL13: 0 | BM13: =BD13 -> 0 | BN13: =BE13 -> 221429 | BO13: 0 | BP13: 0 | BQ13: 0 | BR13: =BJ13 -> 0 | BS13: 0 | BU13: 0 | BV13: 288498 | BW13: 0 | BX13: 0 | BY13: 0 | BZ13: 0 | CA13: 0 | CB13: 0 | CC13: 0 | CD13: 0 | CE13: 0 | CF13: 0 | CG13: 0 | CH13: 0 | CI13: 0 | CJ13: 0 | CK13: 0 | CL13: 0 | CM13: 0 | CN13: 0 | CO13: 0 | CP13: 0 | CQ13: 0 | CR13: 0 | CS13: 0 | CT13: 0 | CU13: 0 | CV13: 0
A14: Atel | D14: Atel | E14: P15 | F14: Inventory | N14: =SUMIF($O$8:$AV$8,">="&'CURRENT FORECAST START DATE'!$C$4,'Weekly Spend'!O14:AV14) -> 38100 | O14: 0 | P14: 0 | Q14: 0 | R14: 0 | S14: 0 | T14: 0 | U14: 0 | V14: 0 | W14: 0 | X14: 0 | Y14: 0 | Z14: 0 | AA14: 0 | AB14: 0 | AC14: 0 | AD14: 0 | AE14: 0 | AF14: 0 | AG14: 0 | AH14: 0 | AI14: 0 | AJ14: 0 | AK14: 0 | AL14: 0 | AM14: 0 | AN14: 0 | AP14: 0 | AQ14: 0 | AR14: 38100 | AS14: 0 | AT14: 0 | AU14: 0 | AV14: 0 | AW14: 0 | AX14: 0 | AZ14: 0 | BA14: 0 | BB14: 0 | BC14: 0 | BD14: 215900 | BE14: 0 | BF14: 0 | BG14: 0 | BH14: 0 | BI14: 0 | BJ14: 0 | BK14: 0 | BL14: 0 | BM14: 0 | BN14: 0 | BO14: 0 | BP14: 0 | BQ14: 0 | BR14: 0 | BS14: 0 | BT14: 0 | BU14: 0 | BV14: 0 | BW14: 0 | BX14: 0 | BY14: 0 | BZ14: 0 | CA14: 0 | CB14: 0 | CC14: 0 | CD14: 0 | CE14: 0 | CF14: 0 | CG14: 0 | CH14: 0 | CI14: 0 | CJ14: 0 | CK14: 0 | CL14: 0 | CM14: 0 | CN14: 0 | CO14: 0 | CP14: 0 | CQ14: 0 | CR14: 0 | CS14: 0 | CT14: 0 | CU14: 0 | CV14: 0
D15: CBN | E15: Q12 | F15: Inventory | N15: =SUMIF($O$8:$AV$8,">="&'CURRENT FORECAST START DATE'!$C$4,'Weekly Spend'!O15:AV15) -> 132000 | O15: 0 | P15: 0 | Q15: 0 | R15: 0 | S15: 0 | T15: 0 | U15: 0 | V15: 0 | W15: 0 | X15: 0 | Y15: 0 | Z15: 0 | AA15: 0 | AB15: 0 | AC15: 0 | AD15: 0 | AE15: 0 | AF15: 0 | AG15: 0 | AH15: 0 | AJ15: 0 | AK15: 0 | AL15: 0 | AN15: 0 | AO15: 0 | AP15: 0 | AR15: 0 | AS15: 0 | AT15: =25% * (26.4*20000) -> 132000 | AU15: 0 | AW15: 0 | AX15: 0 | AY15: 0 | AZ15: 0 | BA15: 0 | BB15: 0 | BC15: 0 | BD15: 0 | BE15: 0 | BF15: 0 | BG15: 0 | BH15: 0 | BI15: 0 | BJ15: 0 | BK15: 0 | BL15: 0 | BM15: 0 | BN15: =75% * (26.4*20000) -> 396000 | BO15: 0 | BP15: 0 | BQ15: 0 | BR15: 0 | BS15: 0 | BT15: 0 | BU15: 0 | BV15: 0 | BW15: 0 | BX15: 0 | BY15: 0 | BZ15: 0 | CA15: 0 | CB15: 0 | CC15: 0 | CD15: 0 | CE15: 0 | CF15: 0 | CG15: 0 | CH15: 0 | CI15: 0 | CJ15: 0 | CK15: 0 | CL15: 0 | CM15: 0 | CN15: 0 | CO15: 0 | CP15: 0 | CQ15: 0 | CR15: 0 | CS15: 0 | CT15: 0 | CU15: 0 | CV15: 0
D16: Salom America | E16: Discount Inventory | F16: Inventory | N16: =SUMIF($O$8:$AV$8,">="&'CURRENT FORECAST START DATE'!$C$4,'Weekly Spend'!O16:AV16) -> 0 | O16: 0 | P16: 0 | Q16: 0 | R16: 0 | S16: 0 | T16: 0 | U16: 450 | V16: 0 | W16: 0 | X16: 0 | Y16: 0 | Z16: 0 | AA16: 0 | AB16: 0 | AC16: 0 | AD16: 0 | AE16: 0 | AF16: 0 | AG16: 0 | AH16: 0 | AI16: 0 | AJ16: 0 | AK16: 0 | AL16: 0 | AM16: 0 | AN16: 0 | AO16: 0 | AP16: 0 | AQ16: 0 | AR16: 0 | AS16: 0 | AT16: 0 | AU16: 0 | AV16: 0 | AW16: 0 | AX16: 0 | AY16: 0 | AZ16: 0 | BA16: 0 | BB16: 0 | BC16: 0 | BD16: 0 | BE16: 0 | BF16: 0 | BG16: 0 | BH16: 0 | BI16: 0 | BJ16: 0 | BK16: 0 | BL16: 0 | BM16: 0 | BN16: 0 | BO16: 0 | BP16: 0 | BQ16: 0 | BR16: 0 | BS16: 0 | BT16: 0 | BU16: 0 | BV16: 0 | BW16: 0 | BX16: 0 | BY16: 0 | BZ16: 0 | CA16: 0 | CB16: 0 | CC16: 0 | CD16: 0 | CE16: 0 | CF16: 0 | CG16: 0 | CH16: 0 | CI16: 0 | CJ16: 0 | CK16: 0 | CL16: 0 | CM16: 0 | CN16: 0 | CO16: 0 | CP16: 0 | CQ16: 0 | CR16: 0 | CS16: 0 | CT16: 0 | CU16: 0 | CV16: 0
A17: ST Cash File (Manual) | D17: Flexport | E17: Shipping | F17: Inventory | J17: 39476.51 | L17: 5000 | N17: =SUMIF($O$8:$AV$8,">="&'CURRENT FORECAST START DATE'!$C$4,'Weekly Spend'!O17:AV17) -> 0 | O17: 0 | P17: 0 | Q17: 0 | R17: 0 | S17: 0 | T17: 0 | U17: 3463 | V17: 0 | W17: =4000+34000 -> 38000 | X17: 0 | Y17: 0 | Z17: 0 | AA17: 0 | AB17: 0 | AC17: 0 | AD17: 0 | AE17: 0 | AF17: 0 | AG17: 0 | AH17: 0 | AI17: 0 | AJ17: 0 | AK17: 0 | AL17: 0 | AM17: 0 | AN17: 0 | AO17: 0 | AP17: 0 | AQ17: 0 | AR17: 0 | AS17: 0 | AT17: 0 | AU17: 0 | AV17: 0 | AW17: 0 | AX17: 0 | AY17: 0 | AZ17: 0 | BA17: 0 | BB17: 0 | BC17: 0 | BD17: 0 | BE17: 0 | BF17: 0 | BG17: 0 | BH17: 0 | BI17: 0 | BJ17: 0 | BK17: 0 | BL17: 0 | BM17: 0 | BN17: 0 | BO17: 0 | BP17: 0 | BQ17: 0 | BR17: 0 | BS17: 0 | BT17: 0 | BU17: 0 | BV17: 0 | BW17: 0 | BX17: 0 | BY17: 0 | BZ17: 0 | CA17: 0 | CB17: 0 | CC17: 0 | CD17: 0 | CE17: 0 | CF17: 0 | CG17: 0 | CH17: 0 | CI17: 0 | CJ17: 0 | CK17: 0 | CL17: 0 | CM17: 0 | CN17: 0 | CO17: 0 | CP17: 0 | CQ17: 0 | CR17: 0 | CS17: 0 | CT17: 0 | CU17: 0 | CV17: 0
D18: Returns (Individual/Shopify) | E18: Returns | F18: Inventory | N18: =SUMIF($O$8:$AV$8,">="&'CURRENT FORECAST START DATE'!$C$4,'Weekly Spend'!O18:AV18) -> 0 | O18: 0 | P18: 0 | Q18: 0 | R18: 0 | S18: 0 | T18: 0 | U18: =238.98+385.68 -> 624.66 | V18: 141.53 | W18: 0 | X18: 0 | Y18: 0 | Z18: 0 | AA18: 0 | AB18: 0 | AC18: 0 | AD18: 0 | AE18: 0 | AF18: 0 | AG18: 0 | AH18: 0 | AI18: 0 | AJ18: 0 | AK18: 0 | AL18: 0 | AM18: 0 | AN18: 0 | AO18: 0 | AP18: 0 | AQ18: 0 | AR18: 0 | AS18: 0 | AT18: 0 | AU18: 0 | AV18: 0 | AW18: 0 | AX18: 0 | AY18: 0 | AZ18: 0 | BA18: 0 | BB18: 0 | BC18: 0 | BD18: 0 | BE18: 0 | BF18: 0 | BG18: 0 | BH18: 0 | BI18: 0 | BJ18: 0 | BK18: 0 | BL18: 0 | BM18: 0 | BN18: 0 | BO18: 0 | BP18: 0 | BQ18: 0 | BR18: 0 | BS18: 0 | BT18: 0 | BU18: 0 | BV18: 0 | BW18: 0 | BX18: 0 | BY18: 0 | BZ18: 0 | CA18: 0 | CB18: 0 | CC18: 0 | CD18: 0 | CE18: 0 | CF18: 0 | CG18: 0 | CH18: 0 | CI18: 0 | CJ18: 0 | CK18: 0 | CL18: 0 | CM18: 0 | CN18: 0 | CO18: 0 | CP18: 0 | CQ18: 0 | CR18: 0 | CS18: 0 | CT18: 0 | CU18: 0 | CV18: 0
A19: ST Cash File (Manual) | B19: =_xlfn.SINGLE(_xlfn.XLOOKUP(F19, $F$87:$F$95, $E$87:$E$95)) -> 6 | C19: K37 | D19: MTN PD | E19: Q15 | F19: Inventory | G19: 71119 | N19: =SUMIF($O$8:$AV$8,">="&'CURRENT FORECAST START DATE'!$C$4,'Weekly Spend'!O19:AV19) -> 45000 | O19: 96000 | P19: 0 | Q19: 0 | R19: 0 | S19: 0 | T19: 0 | U19: 0 | V19: 0 | W19: 0 | X19: 50000 | Z19: 0 | AA19: 0 | AB19: 0 | AC19: 0 | AD19: 0 | AE19: 0 | AF19: 0 | AG19: 0 | AH19: 23100 | AI19: =241500-23100 -> 218400 | AJ19: 0 | AK19: 0 | AL19: 5000 | AM19: 0 | AN19: 0 | AO19: 20000 | AP19: 0 | AQ19: 0 | AR19: 0 | AS19: 0 | AT19: 0 | AU19: 0 | AV19: 25000 | AW19: 0 | AX19: 0 | AY19: 0 | AZ19: 0 | BA19: 0 | BB19: 0 | BC19: 0 | BD19: 0 | BE19: 0 | BF19: 400000 | BG19: 0 | BH19: 0 | BI19: 0 | BJ19: 0 | BK19: 0 | BL19: 0 | BM19: 0 | BN19: 0 | BO19: 0 | BP19: 0 | BQ19: 0 | BR19: 0 | BS19: 0 | BT19: 0 | BU19: 0 | BV19: 0 | BW19: 0 | BX19: 0 | BY19: 0 | BZ19: 0 | CA19: 0 | CB19: 0 | CC19: 0 | CD19: 0 | CE19: 0 | CF19: 0 | CG19: 0 | CH19: 0 | CI19: 0 | CJ19: 0 | CK19: 0 | CL19: 0 | CM19: 0 | CN19: 0 | CO19: 0 | CP19: 0 | CQ19: 0 | CR19: 0 | CS19: 0 | CT19: 0 | CU19: 0 | CV19: 0
D20: CBN | E20: Q12 ROW | F20: Inventory | N20: =SUMIF($O$8:$AV$8,">="&'CURRENT FORECAST START DATE'!$C$4,'Weekly Spend'!O20:AV20) -> 405000 | O20: 0 | P20: 0 | Q20: 0 | R20: 0 | S20: 0 | T20: 0 | U20: 0 | V20: 0 | W20: 0 | X20: 0 | Y20: 0 | Z20: 0 | AA20: 0 | AB20: 0 | AC20: 0 | AD20: 0 | AE20: 0 | AF20: 0 | AG20: 0 | AH20: 0 | AI20: 0 | AJ20: 0 | AK20: 0 | AL20: 0 | AM20: 0 | AN20: 0 | AO20: 0 | AP20: 0 | AQ20: 0 | AR20: 0 | AS20: 0 | AT20: 0 | AU20: 0 | AV20: =25% * (27 * 60000) -> 405000 | AW20: 0 | AX20: 0 | AY20: 0 | BA20: 0 | BB20: 0 | BC20: 0 | BD20: 0 | BE20: 0 | BF20: 0 | BG20: 0 | BH20: 0 | BI20: 0 | BJ20: 0 | BK20: 0 | BL20: 0 | BM20: 0 | BN20: 0 | BO20: 0 | BP20: 0 | BQ20: 0 | BS20: 0 | BT20: 0 | BU20: 0 | BV20: 0 | BW20: 0 | BX20: 0 | BY20: 0 | BZ20: 0 | CA20: 0 | CB20: 0 | CC20: 0 | CD20: 0 | CE20: 0 | CF20: 0 | CG20: 0 | CH20: 0 | CI20: 0 | CJ20: 0 | CK20: 0 | CL20: 0 | CM20: 0 | CN20: 0 | CO20: 0 | CP20: 0 | CQ20: 0 | CR20: 0 | CS20: 0 | CT20: 0 | CU20: 0 | CV20: 0
D21: MTN | E21: Q15 RoW | F21: Inventory | N21: =SUMIF($O$8:$AV$8,">="&'CURRENT FORECAST START DATE'!$C$4,'Weekly Spend'!O21:AV21) -> 174000 | O21: 0 | P21: 0 | Q21: 0 | R21: 0 | S21: 0 | T21: 0 | U21: 0 | V21: 0 | W21: 0 | X21: 0 | AA21: 104700 | AB21: 0 | AC21: 0 | AD21: 0 | AE21: 0 | AF21: 0 | AG21: 0 | AH21: 0 | AI21: 244300 | AJ21: 0 | AK21: 0 | AL21: 0 | AM21: 0 | AN21: 0 | AO21: 0 | AP21: 0 | AQ21: 0 | AR21: =5000*34.8 -> 174000 | AS21: 0 | AT21: 0 | AU21: 0 | AV21: 0 | AW21: 0 | AX21: 0 | AY21: 0 | AZ21: 0 | BA21: 0 | BB21: 0 | BC21: 0 | BD21: 0 | BE21: 0 | BF21: 0 | BG21: 0 | BH21: 0 | BI21: 0 | BJ21: 0 | BK21: 0 | BL21: 0 | BM21: 0 | BN21: 0 | BO21: 0 | BP21: 0 | BQ21: 0 | BR21: 0 | BS21: 0 | BT21: 0 | BU21: 0 | BV21: 0 | BW21: 0 | BX21: 0 | BY21: 0 | BZ21: 0 | CA21: 0 | CB21: 0 | CC21: 0 | CD21: 0 | CE21: 0 | CF21: 0 | CG21: 0 | CH21: 0 | CI21: 0 | CJ21: 0 | CK21: 0 | CL21: 0 | CM21: 0 | CN21: 0 | CO21: 0 | CP21: 0 | CQ21: 0 | CR21: 0 | CS21: 0 | CT21: 0 | CU21: 0 | CV21: 0
A22: Manual Estimate | B22: =_xlfn.SINGLE(_xlfn.XLOOKUP(F22, $F$87:$F$95, $E$87:$E$95)) -> 6 | C22: K47 | D22: CBP | E22: Tariffs | F22: Inventory | M22: 21000 | N22: =SUMIF($O$8:$AV$8,">="&'CURRENT FORECAST START DATE'!$C$4,'Weekly Spend'!O22:AV22) -> 2000 | O22: 0 | P22: 0 | Q22: 0 | R22: 0 | S22: 0 | T22: 0 | U22: 0 | V22: 0 | W22: 0 | X22: 0 | Y22: 0 | Z22: 0 | AA22: =1076.11+48.88 -> 1124.99 | AB22: 0 | AC22: 0 | AD22: 0 | AF22: 2000 | AK22: 2000 | AL22: 0 | AM22: 0 | AN22: 0 | AO22: 0 | AP22: 0 | AQ22: =200*10 -> 2000 | AR22: 0 | AT22: 0 | AV22: 0 | AW22: 0 | AX22: 31194 | AY22: 14400 | AZ22: 0 | BA22: 0 | BB22: 0 | BC22: 0 | BD22: 0 | BE22: 0 | BF22: 60200 | BG22: 0 | BH22: 0 | BI22: 33600 | BJ22: 72786 | BK22: 0 | BL22: 0 | BM22: 0 | BN22: 0 | BO22: 0 | BP22: 0 | BQ22: 0 | BR22: 0 | BS22: 0 | BT22: 0 | BU22: 0 | BV22: 0 | BW22: 0 | BX22: 0 | BY22: 0 | BZ22: 0 | CA22: 0 | CB22: 0 | CC22: 0 | CD22: 0 | CE22: 0 | CF22: 0 | CG22: 0 | CH22: 0 | CI22: 0 | CJ22: 0 | CK22: 0 | CL22: 0 | CM22: 0 | CN22: 0 | CO22: 0 | CP22: 0 | CQ22: 0 | CR22: 0 | CS22: 0 | CT22: 0 | CU22: 0 | CV22: 0
A23: ST Cash File (Manual) | B23: =_xlfn.SINGLE(_xlfn.XLOOKUP(F23, $F$87:$F$95, $E$87:$E$95)) -> 6 | C23: K48 | D23: OL-USA | E23: Shipping | F23: Inventory | M23: 5000 | N23: =SUMIF($O$8:$AV$8,">="&'CURRENT FORECAST START DATE'!$C$4,'Weekly Spend'!O23:AV23) -> 29578 | O23: 0 | P23: 0 | Q23: 0 | R23: 0 | S23: 0 | T23: 0 | U23: 100 | V23: 0 | W23: 0 | X23: 0 | Y23: 19000 | AB23: 21000 | AC23: 0 | AD23: 0 | AE23: =2464+10000+9600 -> 22064 | AF23: 0 | AG23: 15000 | AH23: 0 | AJ23: 8000 | AL23: 15000 | AM23: 0 | AN23: 0 | AO23: 10378 | AP23: 0 | AR23: 0 | AS23: 0 | AT23: 0 | AU23: =4800*4 -> 19200 | AV23: 0 | AW23: 0 | AX23: 0 | AY23: 0 | AZ23: 15000 | BA23: 0 | BB23: 0 | BC23: 0 | BD23: 0 | BE23: 0 | BF23: 0 | BG23: 0 | BH23: 0 | BI23: 0 | BJ23: 30000 | BK23: 0 | BL23: 0 | BM23: 0 | BN23: 0 | BO23: 0 | BP23: 0 | BQ23: 0 | BR23: 0 | BS23: 0 | BT23: 0 | BU23: 0 | BV23: 0 | BW23: 0 | BX23: 0 | BY23: 0 | BZ23: 0 | CA23: 0 | CB23: 0 | CC23: 0 | CD23: 0 | CE23: 0 | CF23: 0 | CG23: 0 | CH23: 0 | CI23: 0 | CJ23: 0 | CK23: 0 | CL23: 0 | CM23: 0 | CN23: 0 | CO23: 0 | CP23: 0 | CQ23: 0 | CR23: 0 | CS23: 0 | CT23: 0 | CU23: 0 | CV23: 0
D24: Gryphon | E24: Contract | F24: Inventory | N24: =SUMIF($O$8:$AV$8,">="&'CURRENT FORECAST START DATE'!$C$4,'Weekly Spend'!O24:AV24) -> 0 | O24: 0 | P24: 0 | Q24: 0 | R24: 0 | S24: 0 | T24: 0 | U24: 0 | V24: 0 | W24: 0 | X24: =2059.5+4907 -> 6966.5 | Y24: 0 | Z24: 0 | AA24: 4555 | AB24: 0 | AC24: 0 | AD24: 0 | AE24: 0 | AF24: 0 | AG24: 0 | AH24: 0 | AI24: 0 | AJ24: 0 | AK24: 0 | AL24: 0 | AM24: 0 | AN24: 0 | AO24: 0 | AP24: 0 | AQ24: 0 | AR24: 0 | AS24: 0 | AT24: 0 | AU24: 0 | AV24: 0 | AW24: 0 | AX24: 0 | AY24: 0 | AZ24: 0 | BA24: 0 | BB24: 0 | BC24: 0 | BD24: 0 | BE24: 0 | BF24: 0 | BG24: 0 | BH24: 0 | BI24: 0 | BJ24: 0 | BK24: 0 | BL24: 0 | BM24: 0 | BN24: 0 | BO24: 0 | BP24: 0 | BQ24: 0 | BR24: 0 | BS24: 0 | BT24: 0 | BU24: 0 | BV24: 0 | BW24: 0 | BX24: 0 | BY24: 0 | BZ24: 0 | CA24: 0 | CB24: 0 | CC24: 0 | CD24: 0 | CE24: 0 | CF24: 0 | CG24: 0 | CH24: 0 | CI24: 0 | CJ24: 0 | CK24: 0 | CL24: 0 | CM24: 0 | CN24: 0 | CO24: 0 | CP24: 0 | CQ24: 0 | CR24: 0 | CS24: 0 | CT24: 0 | CU24: 0 | CV24: 0
D25: Askey | E25: Q20 | F25: NRE | N25: =SUMIF($O$8:$AV$8,">="&'CURRENT FORECAST START DATE'!$C$4,'Weekly Spend'!O25:AV25) -> 0 | O25: 0 | P25: 0 | Q25: 0 | R25: 0 | S25: 0 | T25: 0 | U25: 0 | V25: 0 | W25: 0 | X25: 0 | Y25: 0 | Z25: 0 | AA25: 0 | AB25: 0 | AC25: 0 | AD25: 0 | AE25: 0 | AF25: 0 | AG25: 0 | AH25: 0 | AI25: 0 | AJ25: 0 | AK25: 0 | AL25: 0 | AM25: 0 | AN25: 0 | AO25: 0 | AP25: 0 | AQ25: 0 | AR25: 0 | AS25: 0 | AT25: 0 | AU25: 0 | AV25: 0 | AW25: 0 | AX25: 0 | AY25: 0 | AZ25: 0 | BA25: 0 | BB25: 0 | BC25: 0 | BD25: 0 | BE25: 0 | BF25: 0 | BG25: 0 | BH25: 0 | BI25: 0 | BJ25: 0 | BK25: 0 | BL25: 0 | BM25: 0 | BN25: 0 | BO25: 0 | BP25: 0 | BQ25: 0 | BR25: 0 | BS25: 0 | BT25: 0 | BU25: 0 | BV25: 0 | BW25: 0 | BX25: 0 | BY25: 0 | BZ25: 0 | CA25: 0 | CB25: 0 | CC25: 0 | CD25: 0 | CE25: 0 | CF25: 0 | CG25: 0 | CH25: 0 | CI25: 0 | CJ25: 0 | CK25: 0 | CL25: 0 | CM25: 0 | CN25: 0 | CO25: 0 | CP25: 0 | CQ25: 0 | CR25: 0 | CS25: 0 | CT25: 0 | CU25: 0 | CV25: 0
D26: Atel | E26: P15 NRE | F26: NRE | N26: =SUMIF($O$8:$AV$8,">="&'CURRENT FORECAST START DATE'!$C$4,'Weekly Spend'!O26:AV26) -> 94250 | O26: 0 | P26: 0 | Q26: 0 | R26: 0 | S26: 0 | T26: 0 | U26: 0 | V26: 0 | W26: 0 | X26: 118750 | Y26: 0 | Z26: 0 | AA26: 0 | AC26: 37500 | AD26: 0 | AE26: 0 | AF26: 0 | AG26: 0 | AH26: 0 | AI26: 0 | AK26: 0 | AL26: 0 | AM26: 0 | AN26: 0 | AQ26: 0 | AR26: 0 | AS26: =37500+25000+13000 -> 75500 | AT26: 18750 | AU26: 0 | AV26: 0 | AW26: 0 | AX26: 38000 | AY26: 0 | AZ26: 0 | BA26: 0 | BB26: 0 | BC26: 0 | BD26: 0 | BE26: 0 | BF26: 0 | BG26: 0 | BH26: 0 | BI26: 0 | BJ26: 0 | BK26: 0 | BL26: 0 | BM26: 0 | BN26: 0 | BO26: 0 | BP26: 0 | BQ26: 0 | BR26: 0 | BS26: 0 | BT26: 0 | BU26: 0 | BV26: 0 | BW26: 0 | BX26: 0 | BY26: 0 | BZ26: 0 | CA26: 0 | CB26: 0 | CC26: 0 | CD26: 0 | CE26: 0 | CF26: 0 | CG26: 0 | CH26: 0 | CI26: 0 | CJ26: 0 | CK26: 0 | CL26: 0 | CM26: 0 | CN26: 0 | CO26: 0 | CP26: 0 | CQ26: 0 | CR26: 0 | CS26: 0 | CT26: 0 | CU26: 0 | CV26: 0
D27: Atel | E27: P15RoW | F27: NRE | N27: =SUMIF($O$8:$AV$8,">="&'CURRENT FORECAST START DATE'!$C$4,'Weekly Spend'!O27:AV27) -> 0 | O27: 0 | P27: 0 | Q27: 0 | R27: 0 | S27: 0 | T27: 0 | U27: 0 | V27: 0 | W27: 0 | X27: 0 | Y27: 0 | Z27: 0 | AA27: 0 | AB27: 0 | AC27: 0 | AD27: 0 | AE27: 0 | AF27: 0 | AG27: 0 | AH27: 0 | AI27: 0 | AJ27: 0 | AK27: 0 | AL27: 0 | AM27: 0 | AN27: 0 | AO27: 0 | AP27: 0 | AQ27: 0 | AR27: 0 | AS27: 0 | AT27: 0 | AU27: 0 | AV27: 0 | AW27: 0 | AX27: 0 | AY27: 0 | AZ27: 0 | BA27: 0 | BB27: 0 | BC27: 0 | BD27: 0 | BE27: 0 | BF27: 0 | BG27: 0 | BH27: 0 | BI27: 0 | BJ27: 0 | BK27: 0 | BL27: 0 | BM27: 0 | BN27: 0 | BO27: 0 | BP27: 0 | BQ27: 0 | BR27: 0 | BS27: 0 | BT27: 0 | BU27: 0 | BV27: 0 | BW27: 0 | BX27: 0 | BY27: 0 | BZ27: 0 | CA27: 0 | CB27: 0 | CC27: 0 | CD27: 0 | CE27: 0 | CF27: 0 | CG27: 0 | CH27: 0 | CI27: 0 | CJ27: 0 | CK27: 0 | CL27: 0 | CM27: 0 | CN27: 0 | CO27: 0 | CP27: 0 | CQ27: 0 | CR27: 0 | CS27: 0 | CT27: 0 | CU27: 0 | CV27: 0
D28: CBN | E28: Q12 | F28: NRE | N28: =SUMIF($O$8:$AV$8,">="&'CURRENT FORECAST START DATE'!$C$4,'Weekly Spend'!O28:AV28) -> 155000 | O28: 0 | P28: 0 | Q28: 0 | R28: 0 | S28: 0 | T28: 0 | U28: 0 | V28: 0 | W28: 0 | X28: 0 | Y28: 0 | Z28: 0 | AB28: 0 | AC28: 0 | AD28: 0 | AF28: 0 | AG28: 0 | AH28: 0 | AI28: 0 | AJ28: 0 | AK28: 0 | AL28: 0 | AM28: 0 | AN28: 0 | AO28: 0 | AQ28: 155000 | AR28: 0 | AS28: 0 | AT28: 0 | AU28: 0 | AW28: 0 | AX28: 0 | AY28: 0 | AZ28: 0 | BA28: 0 | BB28: 0 | BC28: 50000 | BD28: 0 | BE28: 155000 | BF28: 0 | BG28: 0 | BH28: 45000 | BI28: 0 | BJ28: 0 | BK28: 0 | BL28: 0 | BM28: 0 | BN28: 0 | BO28: 0 | BP28: 0 | BQ28: 0 | BR28: 0 | BS28: 0 | BT28: 0 | BU28: 0 | BV28: 0 | BW28: 0 | BX28: 0 | BY28: 0 | BZ28: 0 | CA28: 0 | CB28: 0 | CC28: 0 | CD28: 0 | CE28: 0 | CF28: 0 | CG28: 0 | CH28: 0 | CI28: 0 | CJ28: 0 | CK28: 0 | CL28: 0 | CM28: 0 | CN28: 0 | CO28: 0 | CP28: 0 | CQ28: 0 | CR28: 0 | CS28: 0 | CT28: 0 | CU28: 0 | CV28: 0
D29: CBN | E29: Q12 ROW | F29: NRE | N29: =SUMIF($O$8:$AV$8,">="&'CURRENT FORECAST START DATE'!$C$4,'Weekly Spend'!O29:AV29) -> 0 | O29: 0 | P29: 0 | Q29: 0 | R29: 0 | S29: 0 | T29: 0 | U29: 0 | V29: 0 | W29: 0 | X29: 0 | Y29: 0 | Z29: 0 | AB29: 0 | AC29: 0 | AD29: 0 | AE29: 0 | AF29: 0 | AH29: 0 | AL29: 0 | AM29: 0 | AN29: 0 | AP29: 0 | AQ29: 0 | AR29: 0 | AS29: 0 | AT29: 0 | AU29: 0 | AV29: 0 | AW29: 0 | AX29: 0 | AY29: 0 | AZ29: 0 | BA29: 0 | BB29: 0 | BC29: 0 | BD29: 0 | BE29: 0 | BF29: 0 | BG29: 0 | BH29: 0 | BI29: 0 | BJ29: 0 | BK29: 0 | BL29: 0 | BM29: 0 | BN29: 0 | BO29: 0 | BP29: 0 | BQ29: 0 | BR29: 0 | BS29: 0 | BT29: 0 | BU29: 0 | BV29: 0 | BW29: 0 | BX29: 0 | BY29: 0 | BZ29: 0 | CA29: 0 | CB29: 0 | CC29: 0 | CD29: 0 | CE29: 0 | CF29: 0 | CG29: 0 | CH29: 0 | CI29: 0 | CJ29: 0 | CK29: 0 | CL29: 0 | CM29: 0 | CN29: 0 | CO29: 0 | CP29: 0 | CQ29: 0 | CR29: 0 | CS29: 0 | CT29: 0 | CU29: 0 | CV29: 0
D30: MTN MMA | E30: Q15 | F30: NRE | G30: 71119 | N30: =SUMIF($O$8:$AV$8,">="&'CURRENT FORECAST START DATE'!$C$4,'Weekly Spend'!O30:AU30) -> 0 | O30: 0 | P30: 0 | Q30: 0 | R30: 0 | S30: 0 | T30: 0 | U30: 0 | V30: 0 | W30: 0 | X30: 0 | Y30: 0 | Z30: 0 | AA30: 0 | AC30: 0 | AD30: 0 | AE30: 0 | AG30: 0 | AH30: =71119+6350 -> 77469 | AK30: 0 | AL30: 0 | AM30: 0 | AN30: 0 | AO30: 0 | AP30: 0 | AQ30: 0 | AR30: 0 | AS30: 0 | AT30: 0 | AU30: 0 | AV30: 0 | AW30: 0 | AX30: 0 | AY30: 0 | AZ30: 0 | BA30: 0 | BB30: 0 | BC30: 0 | BD30: 0 | BE30: 0 | BF30: 0 | BG30: 0 | BH30: 0 | BI30: 0 | BJ30: 0 | BK30: 0 | BL30: 0 | BM30: 0 | BN30: 0 | BO30: 0 | BP30: 0 | BQ30: 0 | BR30: 0 | BS30: 0 | BT30: 0 | BU30: 0 | BV30: 0 | BW30: 0 | BX30: 0 | BY30: 0 | BZ30: 0 | CA30: 0 | CB30: 0 | CC30: 0 | CD30: 0 | CE30: 0 | CF30: 0 | CG30: 0 | CH30: 0 | CI30: 0 | CJ30: 0 | CK30: 0 | CL30: 0 | CM30: 0 | CN30: 0 | CO30: 0 | CP30: 0 | CQ30: 0 | CR30: 0 | CS30: 0 | CT30: 0 | CU30: 0 | CV30: 0
D31: Compal | E31: B15 RoW | F31: NRE | N31: =SUMIF($O$8:$AV$8,">="&'CURRENT FORECAST START DATE'!$C$4,'Weekly Spend'!O31:AV31) -> 0 | O31: 0 | P31: 0 | Q31: 0 | R31: 0 | S31: 0 | T31: 0 | U31: 0 | V31: 0 | W31: 0 | Z31: 0 | AC31: 0 | AE31: 0 | AF31: 0 | AG31: 0 | AI31: 0 | AK31: 0 | AL31: 0 | AT31: 0 | AU31: 0 | AV31: 0 | AW31: 0 | AX31: 0 | AY31: 0 | AZ31: 0 | BA31: 0 | BB31: 0 | BC31: 0 | BD31: 0 | BE31: 0 | BF31: 0 | BG31: 0 | BH31: 0 | BI31: 0 | BJ31: 0 | BK31: 0 | BL31: 0 | BM31: 0 | BN31: 0 | BO31: 0 | BP31: 0 | BQ31: 0 | BR31: 0 | BS31: 0 | BT31: 0 | BU31: 0 | BV31: 0 | BW31: 0 | BX31: 0 | BY31: 0 | BZ31: 0 | CA31: 0 | CB31: 0 | CC31: 0 | CD31: 0 | CE31: 0 | CF31: 0 | CG31: 0 | CH31: 0 | CI31: 0 | CJ31: 0 | CK31: 0 | CL31: 0 | CM31: 0 | CN31: 0 | CO31: 0 | CP31: 0 | CQ31: 0 | CR31: 0 | CS31: 0 | CT31: 0 | CU31: 0 | CV31: 0
A32: ST Cash File (Manual) | B32: =_xlfn.SINGLE(_xlfn.XLOOKUP(F32, $F$87:$F$95, $E$87:$E$95)) -> 8 | C32: K33 | D32: Compal | E32: B15 | F32: NRE | I32: 151355 | L32: 33000 | N32: =SUMIF($O$8:$AV$8,">="&'CURRENT FORECAST START DATE'!$C$4,'Weekly Spend'!O32:AV32) -> 28500 | O32: 0 | P32: 0 | Q32: 0 | R32: 0 | S32: 0 | T32: 0 | U32: 0 | V32: 0 | W32: 0 | X32: 5292 | Y32: 0 | AA32: 0 | AB32: 0 | AC32: 0 | AD32: 5292 | AE32: 0 | AF32: 0 | AH32: 0 | AI32: 0 | AJ32: 0 | AM32: 0 | AN32: 0 | AO32: 0 | AP32: 0 | AQ32: 0 | AR32: 0 | AS32: 28500 | AT32: 0 | AU32: 0 | AV32: 0 | AW32: 0 | AX32: 0 | AY32: 0 | AZ32: 0 | BA32: 0 | BB32: 0 | BC32: 0 | BD32: 0 | BE32: 0 | BF32: 0 | BG32: 0 | BH32: 0 | BI32: 0 | BJ32: 0 | BK32: 0 | BL32: 0 | BM32: 0 | BN32: 0 | BO32: 0 | BP32: 0 | BQ32: 0 | BR32: 0 | BS32: 0 | BT32: 0 | BU32: 0 | BV32: 0 | BW32: 0 | BX32: 0 | BY32: 0 | BZ32: 0 | CA32: 0 | CB32: 0 | CC32: 0 | CD32: 0 | CE32: 0 | CF32: 0 | CG32: 0 | CH32: 0 | CI32: 0 | CJ32: 0 | CK32: 0 | CL32: 0 | CM32: 0 | CN32: 0 | CO32: 0 | CP32: 0 | CQ32: 0 | CR32: 0 | CS32: 0 | CT32: 0 | CU32: 0 | CV32: 0
D33: Atel | E33: Motosync+ | F33: NRE | N33: =SUMIF($O$8:$AV$8,">="&'CURRENT FORECAST START DATE'!$C$4,'Weekly Spend'!O33:AV33) -> 12500 | O33: 0 | P33: 0 | Q33: 0 | R33: 0 | S33: 0 | T33: 0 | U33: 0 | V33: 0 | W33: 0 | Z33: 0 | AB33: 0 | AF33: 0 | AG33: 0 | AH33: 0 | AI33: 0 | AJ33: 0 | AK33: 0 | AL33: 0 | AO33: 0 | AP33: 0 | AQ33: 0 | AR33: 0 | AS33: 0 | AT33: 0 | AU33: 12500 | AV33: 0 | AW33: 0 | AX33: 0 | AY33: 0 | AZ33: 0 | BA33: 0 | BB33: 0 | BC33: 0 | BD33: 0 | BE33: 0 | BF33: 0 | BG33: 0 | BH33: 0 | BI33: 0 | BJ33: 0 | BK33: 0 | BL33: 0 | BM33: 0 | BN33: 0 | BO33: 0 | BP33: 0 | BQ33: 0 | BR33: 0 | BS33: 0 | BT33: 0 | BU33: 0 | BV33: 0 | BW33: 0 | BX33: 0 | BY33: 0 | BZ33: 0 | CA33: 0 | CB33: 0 | CC33: 0 | CD33: 0 | CE33: 0 | CF33: 0 | CG33: 0 | CH33: 0 | CI33: 0 | CJ33: 0 | CK33: 0 | CL33: 0 | CM33: 0 | CN33: 0 | CO33: 0 | CP33: 0 | CQ33: 0 | CR33: 0 | CS33: 0 | CT33: 0 | CU33: 0 | CV33: 0
D34: MTN | E34: Q15 RoW | F34: NRE | N34: =SUMIF($O$8:$AV$8,">="&'CURRENT FORECAST START DATE'!$C$4,'Weekly Spend'!O34:AV34) -> 25196.66 | O34: 0 | P34: 0 | Q34: 0 | R34: 0 | S34: 0 | T34: 0 | U34: 0 | V34: 0 | W34: 0 | X34: 21053 | Z34: 0 | AA34: 0 | AB34: 0 | AC34: 0 | AD34: 0 | AE34: 0 | AF34: 0 | AG34: 0 | AH34: 0 | AI34: 21053 | AJ34: 0 | AK34: 0 | AM34: 0 | AN34: 0 | AO34: 0 | AP34: 0 | AQ34: 0 | AR34: 0 | AS34: 25196.66 | AT34: 0 | AU34: 0 | AV34: 0 | AW34: 0 | AX34: 0 | AY34: 0 | AZ34: 0 | BA34: 0 | BB34: 0 | BC34: 0 | BD34: 0 | BE34: 0 | BF34: 0 | BG34: 0 | BH34: 0 | BI34: 0 | BJ34: 0 | BK34: 0 | BL34: 0 | BM34: 0 | BN34: 0 | BO34: 0 | BP34: 0 | BQ34: 0 | BR34: 0 | BS34: 0 | BT34: 0 | BU34: 0 | BV34: 0 | BW34: 0 | BX34: 0 | BY34: 0 | BZ34: 0 | CA34: 0 | CB34: 0 | CC34: 0 | CD34: 0 | CE34: 0 | CF34: 0 | CG34: 0 | CH34: 0 | CI34: 0 | CJ34: 0 | CK34: 0 | CL34: 0 | CM34: 0 | CN34: 0 | CO34: 0 | CP34: 0 | CQ34: 0 | CR34: 0 | CS34: 0 | CT34: 0 | CU34: 0 | CV34: 0
D35: Gryphon | E35: P15 | F35: NRE | N35: =SUMIF($O$8:$AV$8,">="&'CURRENT FORECAST START DATE'!$C$4,'Weekly Spend'!O35:AV35) -> 58000 | AG35: 4846.15 | AJ35: 3000 | AN35: 3000 | AO35: 3000 | AP35: 0 | AQ35: 0 | AR35: 0 | AU35: 55000 | AW35: 50000 | AY35: 50000 | BG35: 0 | BH35: 0 | BI35: 0 | BJ35: 0 | BK35: 0 | BL35: 0 | BM35: 0 | BN35: 0 | BO35: 0 | BP35: 0 | BQ35: 0 | BR35: 35000 | BS35: 0 | BT35: 35000
D36: Gryphon | E36: Q15 | F36: NRE | N36: =SUMIF($O$8:$AV$8,">="&'CURRENT FORECAST START DATE'!$C$4,'Weekly Spend'!O36:AV36) -> 96307.69 | AJ36: 6000 | AN36: 12000 | AO36: 41307.69 | AP36: 0 | AQ36: 0 | AR36: 0 | AS36: 55000 | BG36: 0 | BH36: 0 | BI36: 0 | BJ36: 0 | BK36: 0 | BL36: 0 | BM36: 0 | BN36: 0 | BO36: 0 | BP36: 0 | BQ36: 0 | BR36: 0 | BS36: 0 | BT36: 0
D37: Gryphon | E37: Q12 | F37: NRE | N37: =SUMIF($O$8:$AV$8,">="&'CURRENT FORECAST START DATE'!$C$4,'Weekly Spend'!O37:AV37) -> 0 | AP37: 0 | AQ37: 0 | AR37: 0 | BN37: 35000
A38: SC File (Link) | B38: =_xlfn.SINGLE(_xlfn.XLOOKUP(F38, $F$87:$F$95, $E$87:$E$95)) -> 8 | C38: K4 | D38: Gryphon | E38: Contract/Weekly | F38: NRE | G38: {=INDEX('SC Cost File'!$A$2:$AB$31,MATCH($C38,'SC Cost File'!$A$2:$A$31,0),MATCH(G$7,'SC Cost File'!$A$2:$AB$2,0))/COUNTIF($G$7:$CV$7,G$7)} -> 15000 | H38: {=INDEX('SC Cost File'!$A$2:$AB$31,MATCH($C38,'SC Cost File'!$A$2:$A$31,0),MATCH(H$7,'SC Cost File'!$A$2:$AB$2,0))/COUNTIF($G$7:$CV$7,H$7)} -> 15000 | I38: {=INDEX('SC Cost File'!$A$2:$AB$31,MATCH($C38,'SC Cost File'!$A$2:$A$31,0),MATCH(I$7,'SC Cost File'!$A$2:$AB$2,0))/COUNTIF($G$7:$CV$7,I$7)} -> 7500 | J38: {=INDEX('SC Cost File'!$A$2:$AB$31,MATCH($C38,'SC Cost File'!$A$2:$A$31,0),MATCH(J$7,'SC Cost File'!$A$2:$AB$2,0))/COUNTIF($G$7:$CV$7,J$7)} -> 7500 | K38: {=INDEX('SC Cost File'!$A$2:$AB$31,MATCH($C38,'SC Cost File'!$A$2:$A$31,0),MATCH(K$7,'SC Cost File'!$A$2:$AB$2,0))/COUNTIF($G$7:$CV$7,K$7)} -> 7500 | L38: {=INDEX('SC Cost File'!$A$2:$AB$31,MATCH($C38,'SC Cost File'!$A$2:$A$31,0),MATCH(L$7,'SC Cost File'!$A$2:$AB$2,0))/COUNTIF($G$7:$CV$7,L$7)} -> 7500 | M38: {=INDEX('SC Cost File'!$A$2:$AB$31,MATCH($C38,'SC Cost File'!$A$2:$A$31,0),MATCH(M$7,'SC Cost File'!$A$2:$AB$2,0))/COUNTIF($G$7:$CV$7,M$7)} -> 7500 | N38: =SUMIF($O$8:$AV$8,">="&'CURRENT FORECAST START DATE'!$C$4,'Weekly Spend'!O38:AV38) -> 13384.62 | O38: 0 | P38: 0 | Q38: 0 | R38: 0 | S38: 0 | T38: 0 | U38: 31000 | V38: 0 | W38: 0 | X38: 29769.23 | Y38: 0 | Z38: =34169+162 -> 34331 | AA38: =34615 -> 34615 | AB38: 0 | AC38: 0 | AD38: =34950 -> 34950 | AE38: 0 | AF38: 0 | AG38: =36461.64+3692.31 -> 40153.95 | AI38: 40000 | AJ38: 0 | AK38: 31615.39 | AN38: 35307.69 | AO38: 13384.62 | AP38: 0 | AQ38: 0 | AR38: 0 | AS38: 0 | AT38: 0 | AU38: 0 | AV38: 0 | AW38: 0 | AX38: 0 | AY38: 0 | AZ38: 50000 | BA38: 0 | BB38: 0 | BC38: 50000 | BD38: 0 | BE38: 40000 | BG38: 0 | BH38: 0 | BI38: 35000 | BJ38: 0 | BK38: 0 | BL38: 40250 | BM38: 0 | BN38: 0 | BO38: 0 | BP38: 35000 | BQ38: 0 | BR38: 0 | BS38: 0 | BT38: 0 | BU38: 0 | BV38: 0 | BW38: 0 | BX38: 0 | BY38: 0 | BZ38: 0 | CA38: 0 | CB38: 0 | CC38: 0 | CD38: 0 | CE38: 0 | CF38: 0 | CG38: 0 | CH38: 0 | CI38: 0 | CJ38: 0 | CK38: 0 | CL38: 0 | CM38: 0 | CN38: 0 | CO38: 0 | CP38: 0 | CQ38: 0 | CR38: 0 | CS38: 0 | CT38: 0 | CU38: 0 | CV38: 0
A39: ST Cash File (Manual) | B39: =_xlfn.SINGLE(_xlfn.XLOOKUP(F39, $F$87:$F$95, $E$87:$E$95)) -> 2 | C39: K23 | D39: AWS | E39: Services | F39: OpEx | G39: 0 | H39: 0 | I39: 0 | J39: 0 | K39: 0 | L39: 0 | M39: 40000 | N39: =SUMIF($O$8:$AV$8,">="&'CURRENT FORECAST START DATE'!$C$4,'Weekly Spend'!O39:AV39) -> 40000 | O39: 0 | P39: 0 | Q39: 0 | R39: 40000 | S39: 0 | T39: 0 | U39: 0 | V39: 42853 | W39: 0 | X39: 0 | Y39: 0 | Z39: 42000 | AA39: 0 | AB39: 0 | AC39: 0 | AE39: 42000 | AF39: 0 | AG39: 0 | AI39: 0 | AJ39: 43500 | AK39: 0 | AM39: 0 | AN39: 40000 | AO39: 0 | AR39: 40000 | AS39: 0 | AU39: 0 | AW39: 40000 | AY39: 0 | BA39: 40000 | BC39: 0 | BE39: 40000 | BG39: 0 | BH39: 0 | BJ39: 40000 | BK39: 0 | BL39: 0 | BN39: 40000 | BO39: 0 | BP39: 0 | BR39: 40000 | BS39: 0 | BT39: 0 | BU39: 0 | CB39: 0 | CF39: 0 | CJ39: 0 | CO39: 0 | CQ39: 0 | CS39: 0 | CU39: 0
A40: ST Cash File (Manual) | B40: =_xlfn.SINGLE(_xlfn.XLOOKUP(F40, $F$87:$F$95, $E$87:$E$95)) -> 2 | C40: K39 | D40: CATV (Triage, Refurb, RMA) | E40: Services | F40: OpEx | M40: 50000 | N40: =SUMIF($O$8:$AV$8,">="&'CURRENT FORECAST START DATE'!$C$4,'Weekly Spend'!O40:AV40) -> 22572.5 | O40: 0 | P40: 0 | Q40: 3500 | R40: 0 | S40: 0 | T40: 0 | U40: 0 | V40: 0 | W40: 0 | X40: =1040+143 -> 1183 | Y40: =4030+65 -> 4095 | Z40: 2249 | AD40: 15704 | AE40: =250+3999.91 -> 4249.91 | AF40: 12493 | AG40: =1573 -> 1573 | AH40: =1495+2834+1521+10000 -> 15850 | AI40: 4000 | AJ40: 3484 | AK40: =1963+195 -> 2158 | AL40: 7000 | AM40: =338+2327+429 -> 3094 | AN40: =4797+767+17797 -> 23361 | AQ40: =1485+1087.5 -> 2572.5 | AR40: =3000+1000 -> 4000 | AS40: =3000+1000 -> 4000 | AT40: =3000+1000 -> 4000 | AU40: =3000+1000 -> 4000 | AV40: =3000+1000 -> 4000 | AW40: =3000+1000 -> 4000 | AX40: =3000+1000 -> 4000 | AY40: =3000+1000 -> 4000 | ... BL40: =3000+1000 -> 4000 | BO40: =3000+1000 -> 4000 | BP40: =3000+1000 -> 4000 | BQ40: =3000+1000 -> 4000 | BR40: =3000+1000 -> 4000 | BS40: =3000+1000 -> 4000 | BT40: =3000+1000 -> 4000 | BU40: =3000+1000 -> 4000 | BV40: =3000+1000 -> 4000 | ... CV40: =3000+1000 -> 4000
A41: Manual Invoice | B41: =_xlfn.SINGLE(_xlfn.XLOOKUP(F41, $F$87:$F$95, $E$87:$E$95)) -> 2 | C41: K46 | D41: Tide Rock | E41: Allocation | F41: OpEx | I41: 24152.95 | M41: =I41 -> 24152.95 | N41: =SUMIF($O$8:$AV$8,">="&'CURRENT FORECAST START DATE'!$C$4,'Weekly Spend'!O41:AV41) -> 44000 | O41: 0 | P41: 0 | Q41: 0 | R41: =I41 -> 24152.95 | S41: 0 | T41: 0 | U41: 0 | V41: 0 | W41: 0 | X41: 0 | Y41: 0 | Z41: =9300+15598 -> 24898 | AA41: 0 | AB41: 0 | AC41: 0 | AE41: 20000 | AF41: 0 | AG41: 0 | AH41: 0 | AI41: =AD41 -> 0 | AJ41: 0 | AK41: 0 | AL41: 0 | AM41: =AI41 -> 0 | AN41: 0 | AO41: 0 | AP41: 0 | AR41: 22000 | AS41: 0 | AT41: 0 | AU41: 0 | AV41: 22000 | AW41: 0 | AX41: 0 | AY41: 0 | AZ41: 22000 | BA41: 0 | BB41: 0 | BC41: 0 | BD41: 22000 | BE41: 0 | BF41: 0 | BG41: 0 | BH41: 0 | BI41: 22000 | BJ41: 0 | BK41: 0 | BL41: 0 | BM41: 22000 | BN41: 0 | BO41: 0 | BP41: 0 | BQ41: 22000 | BR41: 0 | BS41: 0 | BT41: 0 | BU41: 0 | BV41: 22000 | BW41: 0 | BX41: 0 | BY41: 0 | BZ41: 22000 | CA41: 0 | CB41: 0 | CC41: 0 | CD41: 0 | CE41: 22000 | CF41: 0 | CG41: 0 | CH41: 0 | CI41: 22000 | CJ41: 0 | CK41: 0 | CL41: 0 | CM41: 22000 | CN41: 0 | CO41: 0 | CP41: 0 | CQ41: 0 | CR41: 22000 | CS41: 0 | CT41: 0 | CU41: 0 | CV41: 22000
A42: SC File (Link) | B42: =_xlfn.SINGLE(_xlfn.XLOOKUP(F42, $F$87:$F$95, $E$87:$E$95)) -> 8 | C42: K29 | D42: CableLabs/Kyrio | E42: Services | F42: NRE | G42: {=INDEX('SC Cost File'!$A$2:$AB$31,MATCH($C42,'SC Cost File'!$A$2:$A$31,0),MATCH(G$7,'SC Cost File'!$A$2:$AB$2,0))/COUNTIF($G$7:$CV$7,G$7)} -> 0 | H42: {=INDEX('SC Cost File'!$A$2:$AB$31,MATCH($C42,'SC Cost File'!$A$2:$A$31,0),MATCH(H$7,'SC Cost File'!$A$2:$AB$2,0))/COUNTIF($G$7:$CV$7,H$7)} -> 0 | I42: {=INDEX('SC Cost File'!$A$2:$AB$31,MATCH($C42,'SC Cost File'!$A$2:$A$31,0),MATCH(I$7,'SC Cost File'!$A$2:$AB$2,0))/COUNTIF($G$7:$CV$7,I$7)} -> 0 | J42: {=INDEX('SC Cost File'!$A$2:$AB$31,MATCH($C42,'SC Cost File'!$A$2:$A$31,0),MATCH(J$7,'SC Cost File'!$A$2:$AB$2,0))/COUNTIF($G$7:$CV$7,J$7)} -> 0 | K42: {=INDEX('SC Cost File'!$A$2:$AB$31,MATCH($C42,'SC Cost File'!$A$2:$A$31,0),MATCH(K$7,'SC Cost File'!$A$2:$AB$2,0))/COUNTIF($G$7:$CV$7,K$7)} -> 0 | L42: {=INDEX('SC Cost File'!$A$2:$AB$31,MATCH($C42,'SC Cost File'!$A$2:$A$31,0),MATCH(L$7,'SC Cost File'!$A$2:$AB$2,0))/COUNTIF($G$7:$CV$7,L$7)} -> 0 | M42: {=INDEX('SC Cost File'!$A$2:$AB$31,MATCH($C42,'SC Cost File'!$A$2:$A$31,0),MATCH(M$7,'SC Cost File'!$A$2:$AB$2,0))/COUNTIF($G$7:$CV$7,M$7)} -> 0 | N42: =SUMIF($O$8:$AV$8,">="&'CURRENT FORECAST START DATE'!$C$4,'Weekly Spend'!O42:AV42) -> 0 | O42: {=INDEX('SC Cost File'!$A$2:$AB$31,MATCH($C42,'SC Cost File'!$A$2:$A$31,0),MATCH(O$7,'SC Cost File'!$A$2:$AB$2,0))/COUNTIF($G$7:$CV$7,O$7)} -> 0 | P42: {=INDEX('SC Cost File'!$A$2:$AB$31,MATCH($C42,'SC Cost File'!$A$2:$A$31,0),MATCH(P$7,'SC Cost File'!$A$2:$AB$2,0))/COUNTIF($G$7:$CV$7,P$7)} -> 0 | Q42: {=INDEX('SC Cost File'!$A$2:$AB$31,MATCH($C42,'SC Cost File'!$A$2:$A$31,0),MATCH(Q$7,'SC Cost File'!$A$2:$AB$2,0))/COUNTIF($G$7:$CV$7,Q$7)} -> 0 | R42: {=INDEX('SC Cost File'!$A$2:$AB$31,MATCH($C42,'SC Cost File'!$A$2:$A$31,0),MATCH(R$7,'SC Cost File'!$A$2:$AB$2,0))/COUNTIF($G$7:$CV$7,R$7)} -> 0 | S42: {=INDEX('SC Cost File'!$A$2:$AB$31,MATCH($C42,'SC Cost File'!$A$2:$A$31,0),MATCH(S$7,'SC Cost File'!$A$2:$AB$2,0))/COUNTIF($G$7:$CV$7,S$7)} -> 0 | T42: {=INDEX('SC Cost File'!$A$2:$AB$31,MATCH($C42,'SC Cost File'!$A$2:$A$31,0),MATCH(T$7,'SC Cost File'!$A$2:$AB$2,0))/COUNTIF($G$7:$CV$7,T$7)} -> 0 | U42: {=INDEX('SC Cost File'!$A$2:$AB$31,MATCH($C42,'SC Cost File'!$A$2:$A$31,0),MATCH(U$7,'SC Cost File'!$A$2:$AB$2,0))/COUNTIF($G$7:$CV$7,U$7)} -> 0 | V42: {=INDEX('SC Cost File'!$A$2:$AB$31,MATCH($C42,'SC Cost File'!$A$2:$A$31,0),MATCH(V$7,'SC Cost File'!$A$2:$AB$2,0))/COUNTIF($G$7:$CV$7,V$7)} -> 0 | ... AD42: {=INDEX('SC Cost File'!$A$2:$AB$31,MATCH($C42,'SC Cost File'!$A$2:$A$31,0),MATCH(AD$7,'SC Cost File'!$A$2:$AB$2,0))/COUNTIF($G$7:$CV$7,AD$7)} -> 0 | AF42: {=INDEX('SC Cost File'!$A$2:$AB$31,MATCH($C42,'SC Cost File'!$A$2:$A$31,0),MATCH(AF$7,'SC Cost File'!$A$2:$AB$2,0))/COUNTIF($G$7:$CV$7,AF$7)} -> 0 | AG42: {=INDEX('SC Cost File'!$A$2:$AB$31,MATCH($C42,'SC Cost File'!$A$2:$A$31,0),MATCH(AG$7,'SC Cost File'!$A$2:$AB$2,0))/COUNTIF($G$7:$CV$7,AG$7)} -> 0 | AH42: {=INDEX('SC Cost File'!$A$2:$AB$31,MATCH($C42,'SC Cost File'!$A$2:$A$31,0),MATCH(AH$7,'SC Cost File'!$A$2:$AB$2,0))/COUNTIF($G$7:$CV$7,AH$7)} -> 0 | AI42: {=INDEX('SC Cost File'!$A$2:$AB$31,MATCH($C42,'SC Cost File'!$A$2:$A$31,0),MATCH(AI$7,'SC Cost File'!$A$2:$AB$2,0))/COUNTIF($G$7:$CV$7,AI$7)} -> 0 | AJ42: {=INDEX('SC Cost File'!$A$2:$AB$31,MATCH($C42,'SC Cost File'!$A$2:$A$31,0),MATCH(AJ$7,'SC Cost File'!$A$2:$AB$2,0))/COUNTIF($G$7:$CV$7,AJ$7)} -> 0 | AM42: {=INDEX('SC Cost File'!$A$2:$AB$31,MATCH($C42,'SC Cost File'!$A$2:$A$31,0),MATCH(AM$7,'SC Cost File'!$A$2:$AB$2,0))/COUNTIF($G$7:$CV$7,AM$7)} -> 0 | AR42: {=INDEX('SC Cost File'!$A$2:$AB$31,MATCH($C42,'SC Cost File'!$A$2:$A$31,0),MATCH(AR$7,'SC Cost File'!$A$2:$AB$2,0))/COUNTIF($G$7:$CV$7,AR$7)} -> 0 | AS42: {=INDEX('SC Cost File'!$A$2:$AB$31,MATCH($C42,'SC Cost File'!$A$2:$A$31,0),MATCH(AS$7,'SC Cost File'!$A$2:$AB$2,0))/COUNTIF($G$7:$CV$7,AS$7)} -> 0 | AT42: {=INDEX('SC Cost File'!$A$2:$AB$31,MATCH($C42,'SC Cost File'!$A$2:$A$31,0),MATCH(AT$7,'SC Cost File'!$A$2:$AB$2,0))/COUNTIF($G$7:$CV$7,AT$7)} -> 0 | AV42: {=INDEX('SC Cost File'!$A$2:$AB$31,MATCH($C42,'SC Cost File'!$A$2:$A$31,0),MATCH(AV$7,'SC Cost File'!$A$2:$AB$2,0))/COUNTIF($G$7:$CV$7,AV$7)} -> 0 | AW42: {=INDEX('SC Cost File'!$A$2:$AB$31,MATCH($C42,'SC Cost File'!$A$2:$A$31,0),MATCH(AW$7,'SC Cost File'!$A$2:$AB$2,0))/COUNTIF($G$7:$CV$7,AW$7)} -> 0 | AX42: {=INDEX('SC Cost File'!$A$2:$AB$31,MATCH($C42,'SC Cost File'!$A$2:$A$31,0),MATCH(AX$7,'SC Cost File'!$A$2:$AB$2,0))/COUNTIF($G$7:$CV$7,AX$7)} -> 0 | AY42: {=INDEX('SC Cost File'!$A$2:$AB$31,MATCH($C42,'SC Cost File'!$A$2:$A$31,0),MATCH(AY$7,'SC Cost File'!$A$2:$AB$2,0))/COUNTIF($G$7:$CV$7,AY$7)} -> 0 | AZ42: {=INDEX('SC Cost File'!$A$2:$AB$31,MATCH($C42,'SC Cost File'!$A$2:$A$31,0),MATCH(AZ$7,'SC Cost File'!$A$2:$AB$2,0))/COUNTIF($G$7:$CV$7,AZ$7)} -> 0 | BA42: {=INDEX('SC Cost File'!$A$2:$AB$31,MATCH($C42,'SC Cost File'!$A$2:$A$31,0),MATCH(BA$7,'SC Cost File'!$A$2:$AB$2,0))/COUNTIF($G$7:$CV$7,BA$7)} -> 0 | BB42: {=INDEX('SC Cost File'!$A$2:$AB$31,MATCH($C42,'SC Cost File'!$A$2:$A$31,0),MATCH(BB$7,'SC Cost File'!$A$2:$AB$2,0))/COUNTIF($G$7:$CV$7,BB$7)} -> 0 | BC42: {=INDEX('SC Cost File'!$A$2:$AB$31,MATCH($C42,'SC Cost File'!$A$2:$A$31,0),MATCH(BC$7,'SC Cost File'!$A$2:$AB$2,0))/COUNTIF($G$7:$CV$7,BC$7)} -> 0 | ... CV42: {=INDEX('SC Cost File'!$A$2:$AB$31,MATCH($C42,'SC Cost File'!$A$2:$A$31,0),MATCH(CV$7,'SC Cost File'!$A$2:$AB$2,0))/COUNTIF($G$7:$CV$7,CV$7)} -> 0
D43: Cox | E43: Services | F43: NRE | N43: =SUMIF($O$8:$AV$8,">="&'CURRENT FORECAST START DATE'!$C$4,'Weekly Spend'!O43:AV43) -> 5000 | AU43: 5000
D44: Charter/Spectrum | E44: Services | F44: NRE | N44: =SUMIF($O$8:$AV$8,">="&'CURRENT FORECAST START DATE'!$C$4,'Weekly Spend'!O44:AV44) -> 12500 | AT44: 12500
D45: Comcast | E45: Services | F45: NRE | N45: =SUMIF($O$8:$AV$8,">="&'CURRENT FORECAST START DATE'!$C$4,'Weekly Spend'!O45:AV45) -> 28250 | AR45: 28250
A46: SC File (Link) | B46: =_xlfn.SINGLE(_xlfn.XLOOKUP(F46, $F$87:$F$95, $E$87:$E$95)) -> 2 | C46: K7 | D46: Arksaw | E46: Contract | F46: OpEx | G46: {=INDEX('SC Cost File'!$A$2:$AB$31,MATCH($C46,'SC Cost File'!$A$2:$A$31,0),MATCH(G$7,'SC Cost File'!$A$2:$AB$2,0))/COUNTIF($G$7:$CV$7,G$7)} -> 1000 | H46: {=INDEX('SC Cost File'!$A$2:$AB$31,MATCH($C46,'SC Cost File'!$A$2:$A$31,0),MATCH(H$7,'SC Cost File'!$A$2:$AB$2,0))/COUNTIF($G$7:$CV$7,H$7)} -> 1000 | I46: {=INDEX('SC Cost File'!$A$2:$AB$31,MATCH($C46,'SC Cost File'!$A$2:$A$31,0),MATCH(I$7,'SC Cost File'!$A$2:$AB$2,0))/COUNTIF($G$7:$CV$7,I$7)} -> 500 | J46: {=INDEX('SC Cost File'!$A$2:$AB$31,MATCH($C46,'SC Cost File'!$A$2:$A$31,0),MATCH(J$7,'SC Cost File'!$A$2:$AB$2,0))/COUNTIF($G$7:$CV$7,J$7)} -> 500 | K46: {=INDEX('SC Cost File'!$A$2:$AB$31,MATCH($C46,'SC Cost File'!$A$2:$A$31,0),MATCH(K$7,'SC Cost File'!$A$2:$AB$2,0))/COUNTIF($G$7:$CV$7,K$7)} -> 500 | L46: {=INDEX('SC Cost File'!$A$2:$AB$31,MATCH($C46,'SC Cost File'!$A$2:$A$31,0),MATCH(L$7,'SC Cost File'!$A$2:$AB$2,0))/COUNTIF($G$7:$CV$7,L$7)} -> 500 | M46: {=INDEX('SC Cost File'!$A$2:$AB$31,MATCH($C46,'SC Cost File'!$A$2:$A$31,0),MATCH(M$7,'SC Cost File'!$A$2:$AB$2,0))/COUNTIF($G$7:$CV$7,M$7)} -> 500 | N46: =SUMIF($O$8:$AV$8,">="&'CURRENT FORECAST START DATE'!$C$4,'Weekly Spend'!O46:AV46) -> 2663 | O46: {=INDEX('SC Cost File'!$A$2:$AB$31,MATCH($C46,'SC Cost File'!$A$2:$A$31,0),MATCH(O$7,'SC Cost File'!$A$2:$AB$2,0))/COUNTIF($G$7:$CV$7,O$7)} -> 500 | P46: {=INDEX('SC Cost File'!$A$2:$AB$31,MATCH($C46,'SC Cost File'!$A$2:$A$31,0),MATCH(P$7,'SC Cost File'!$A$2:$AB$2,0))/COUNTIF($G$7:$CV$7,P$7)} -> 500 | Q46: {=INDEX('SC Cost File'!$A$2:$AB$31,MATCH($C46,'SC Cost File'!$A$2:$A$31,0),MATCH(Q$7,'SC Cost File'!$A$2:$AB$2,0))/COUNTIF($G$7:$CV$7,Q$7)} -> 500 | R46: {=INDEX('SC Cost File'!$A$2:$AB$31,MATCH($C46,'SC Cost File'!$A$2:$A$31,0),MATCH(R$7,'SC Cost File'!$A$2:$AB$2,0))/COUNTIF($G$7:$CV$7,R$7)} -> 400 | S46: {=INDEX('SC Cost File'!$A$2:$AB$31,MATCH($C46,'SC Cost File'!$A$2:$A$31,0),MATCH(S$7,'SC Cost File'!$A$2:$AB$2,0))/COUNTIF($G$7:$CV$7,S$7)} -> 400 | T46: {=INDEX('SC Cost File'!$A$2:$AB$31,MATCH($C46,'SC Cost File'!$A$2:$A$31,0),MATCH(T$7,'SC Cost File'!$A$2:$AB$2,0))/COUNTIF($G$7:$CV$7,T$7)} -> 400 | U46: {=INDEX('SC Cost File'!$A$2:$AB$31,MATCH($C46,'SC Cost File'!$A$2:$A$31,0),MATCH(U$7,'SC Cost File'!$A$2:$AB$2,0))/COUNTIF($G$7:$CV$7,U$7)} -> 400 | V46: 0 | W46: 0 | X46: {=INDEX('SC Cost File'!$A$2:$AB$31,MATCH($C46,'SC Cost File'!$A$2:$A$31,0),MATCH(X$7,'SC Cost File'!$A$2:$AB$2,0))/COUNTIF($G$7:$CV$7,X$7)} -> 500 | Y46: {=INDEX('SC Cost File'!$A$2:$AB$31,MATCH($C46,'SC Cost File'!$A$2:$A$31,0),MATCH(Y$7,'SC Cost File'!$A$2:$AB$2,0))/COUNTIF($G$7:$CV$7,Y$7)} -> 500 | Z46: {=INDEX('SC Cost File'!$A$2:$AB$31,MATCH($C46,'SC Cost File'!$A$2:$A$31,0),MATCH(Z$7,'SC Cost File'!$A$2:$AB$2,0))/COUNTIF($G$7:$CV$7,Z$7)} -> 500 | AA46: {=INDEX('SC Cost File'!$A$2:$AB$31,MATCH($C46,'SC Cost File'!$A$2:$A$31,0),MATCH(AA$7,'SC Cost File'!$A$2:$AB$2,0))/COUNTIF($G$7:$CV$7,AA$7)} -> 500 | AE46: 1062 | AJ46: 2921 | AN46: 1062.5 | AR46: 1063 | AS46: {=INDEX('SC Cost File'!$A$2:$AB$31,MATCH($C46,'SC Cost File'!$A$2:$A$31,0),MATCH(AS$7,'SC Cost File'!$A$2:$AB$2,0))/COUNTIF($G$7:$CV$7,AS$7)} -> 400 | AT46: {=INDEX('SC Cost File'!$A$2:$AB$31,MATCH($C46,'SC Cost File'!$A$2:$A$31,0),MATCH(AT$7,'SC Cost File'!$A$2:$AB$2,0))/COUNTIF($G$7:$CV$7,AT$7)} -> 400 | AU46: {=INDEX('SC Cost File'!$A$2:$AB$31,MATCH($C46,'SC Cost File'!$A$2:$A$31,0),MATCH(AU$7,'SC Cost File'!$A$2:$AB$2,0))/COUNTIF($G$7:$CV$7,AU$7)} -> 400 | AV46: {=INDEX('SC Cost File'!$A$2:$AB$31,MATCH($C46,'SC Cost File'!$A$2:$A$31,0),MATCH(AV$7,'SC Cost File'!$A$2:$AB$2,0))/COUNTIF($G$7:$CV$7,AV$7)} -> 400 | AW46: {=INDEX('SC Cost File'!$A$2:$AB$31,MATCH($C46,'SC Cost File'!$A$2:$A$31,0),MATCH(AW$7,'SC Cost File'!$A$2:$AB$2,0))/COUNTIF($G$7:$CV$7,AW$7)} -> 500 | AX46: {=INDEX('SC Cost File'!$A$2:$AB$31,MATCH($C46,'SC Cost File'!$A$2:$A$31,0),MATCH(AX$7,'SC Cost File'!$A$2:$AB$2,0))/COUNTIF($G$7:$CV$7,AX$7)} -> 500 | AY46: {=INDEX('SC Cost File'!$A$2:$AB$31,MATCH($C46,'SC Cost File'!$A$2:$A$31,0),MATCH(AY$7,'SC Cost File'!$A$2:$AB$2,0))/COUNTIF($G$7:$CV$7,AY$7)} -> 500 | AZ46: {=INDEX('SC Cost File'!$A$2:$AB$31,MATCH($C46,'SC Cost File'!$A$2:$A$31,0),MATCH(AZ$7,'SC Cost File'!$A$2:$AB$2,0))/COUNTIF($G$7:$CV$7,AZ$7)} -> 500 | ... CV46: {=INDEX('SC Cost File'!$A$2:$AB$31,MATCH($C46,'SC Cost File'!$A$2:$A$31,0),MATCH(CV$7,'SC Cost File'!$A$2:$AB$2,0))/COUNTIF($G$7:$CV$7,CV$7)} -> 500
A47: SC File (Link) | B47: =_xlfn.SINGLE(_xlfn.XLOOKUP(F47, $F$87:$F$95, $E$87:$E$95)) -> 2 | C47: K25 | D47: JustCall | E47: Services | F47: OpEx | G47: {=INDEX('SC Cost File'!$A$2:$AB$31,MATCH($C47,'SC Cost File'!$A$2:$A$31,0),MATCH(G$7,'SC Cost File'!$A$2:$AB$2,0))/COUNTIF($G$7:$CV$7,G$7)} -> 0 | H47: {=INDEX('SC Cost File'!$A$2:$AB$31,MATCH($C47,'SC Cost File'!$A$2:$A$31,0),MATCH(H$7,'SC Cost File'!$A$2:$AB$2,0))/COUNTIF($G$7:$CV$7,H$7)} -> 0 | I47: {=INDEX('SC Cost File'!$A$2:$AB$31,MATCH($C47,'SC Cost File'!$A$2:$A$31,0),MATCH(I$7,'SC Cost File'!$A$2:$AB$2,0))/COUNTIF($G$7:$CV$7,I$7)} -> 0 | J47: {=INDEX('SC Cost File'!$A$2:$AB$31,MATCH($C47,'SC Cost File'!$A$2:$A$31,0),MATCH(J$7,'SC Cost File'!$A$2:$AB$2,0))/COUNTIF($G$7:$CV$7,J$7)} -> 0 | K47: {=INDEX('SC Cost File'!$A$2:$AB$31,MATCH($C47,'SC Cost File'!$A$2:$A$31,0),MATCH(K$7,'SC Cost File'!$A$2:$AB$2,0))/COUNTIF($G$7:$CV$7,K$7)} -> 0 | L47: {=INDEX('SC Cost File'!$A$2:$AB$31,MATCH($C47,'SC Cost File'!$A$2:$A$31,0),MATCH(L$7,'SC Cost File'!$A$2:$AB$2,0))/COUNTIF($G$7:$CV$7,L$7)} -> 0 | M47: {=INDEX('SC Cost File'!$A$2:$AB$31,MATCH($C47,'SC Cost File'!$A$2:$A$31,0),MATCH(M$7,'SC Cost File'!$A$2:$AB$2,0))/COUNTIF($G$7:$CV$7,M$7)} -> 0 | N47: =SUMIF($O$8:$AV$8,">="&'CURRENT FORECAST START DATE'!$C$4,'Weekly Spend'!O47:AV47) -> 0 | O47: {=INDEX('SC Cost File'!$A$2:$AB$31,MATCH($C47,'SC Cost File'!$A$2:$A$31,0),MATCH(O$7,'SC Cost File'!$A$2:$AB$2,0))/COUNTIF($G$7:$CV$7,O$7)} -> 0 | P47: {=INDEX('SC Cost File'!$A$2:$AB$31,MATCH($C47,'SC Cost File'!$A$2:$A$31,0),MATCH(P$7,'SC Cost File'!$A$2:$AB$2,0))/COUNTIF($G$7:$CV$7,P$7)} -> 0 | Q47: {=INDEX('SC Cost File'!$A$2:$AB$31,MATCH($C47,'SC Cost File'!$A$2:$A$31,0),MATCH(Q$7,'SC Cost File'!$A$2:$AB$2,0))/COUNTIF($G$7:$CV$7,Q$7)} -> 0 | R47: {=INDEX('SC Cost File'!$A$2:$AB$31,MATCH($C47,'SC Cost File'!$A$2:$A$31,0),MATCH(R$7,'SC Cost File'!$A$2:$AB$2,0))/COUNTIF($G$7:$CV$7,R$7)} -> 0 | S47: {=INDEX('SC Cost File'!$A$2:$AB$31,MATCH($C47,'SC Cost File'!$A$2:$A$31,0),MATCH(S$7,'SC Cost File'!$A$2:$AB$2,0))/COUNTIF($G$7:$CV$7,S$7)} -> 0 | T47: {=INDEX('SC Cost File'!$A$2:$AB$31,MATCH($C47,'SC Cost File'!$A$2:$A$31,0),MATCH(T$7,'SC Cost File'!$A$2:$AB$2,0))/COUNTIF($G$7:$CV$7,T$7)} -> 0 | U47: {=INDEX('SC Cost File'!$A$2:$AB$31,MATCH($C47,'SC Cost File'!$A$2:$A$31,0),MATCH(U$7,'SC Cost File'!$A$2:$AB$2,0))/COUNTIF($G$7:$CV$7,U$7)} -> 0 | V47: {=INDEX('SC Cost File'!$A$2:$AB$31,MATCH($C47,'SC Cost File'!$A$2:$A$31,0),MATCH(V$7,'SC Cost File'!$A$2:$AB$2,0))/COUNTIF($G$7:$CV$7,V$7)} -> 0 | W47: 0 | X47: {=INDEX('SC Cost File'!$A$2:$AB$31,MATCH($C47,'SC Cost File'!$A$2:$A$31,0),MATCH(X$7,'SC Cost File'!$A$2:$AB$2,0))/COUNTIF($G$7:$CV$7,X$7)} -> 1008 | Y47: {=INDEX('SC Cost File'!$A$2:$AB$31,MATCH($C47,'SC Cost File'!$A$2:$A$31,0),MATCH(Y$7,'SC Cost File'!$A$2:$AB$2,0))/COUNTIF($G$7:$CV$7,Y$7)} -> 1008 | Z47: {=INDEX('SC Cost File'!$A$2:$AB$31,MATCH($C47,'SC Cost File'!$A$2:$A$31,0),MATCH(Z$7,'SC Cost File'!$A$2:$AB$2,0))/COUNTIF($G$7:$CV$7,Z$7)} -> 1008 | AA47: 2500 | AB47: {=INDEX('SC Cost File'!$A$2:$AB$31,MATCH($C47,'SC Cost File'!$A$2:$A$31,0),MATCH(AB$7,'SC Cost File'!$A$2:$AB$2,0))/COUNTIF($G$7:$CV$7,AB$7)} -> 0 | AC47: {=INDEX('SC Cost File'!$A$2:$AB$31,MATCH($C47,'SC Cost File'!$A$2:$A$31,0),MATCH(AC$7,'SC Cost File'!$A$2:$AB$2,0))/COUNTIF($G$7:$CV$7,AC$7)} -> 0 | AD47: {=INDEX('SC Cost File'!$A$2:$AB$31,MATCH($C47,'SC Cost File'!$A$2:$A$31,0),MATCH(AD$7,'SC Cost File'!$A$2:$AB$2,0))/COUNTIF($G$7:$CV$7,AD$7)} -> 0 | AE47: {=INDEX('SC Cost File'!$A$2:$AB$31,MATCH($C47,'SC Cost File'!$A$2:$A$31,0),MATCH(AE$7,'SC Cost File'!$A$2:$AB$2,0))/COUNTIF($G$7:$CV$7,AE$7)} -> 0 | AF47: {=INDEX('SC Cost File'!$A$2:$AB$31,MATCH($C47,'SC Cost File'!$A$2:$A$31,0),MATCH(AF$7,'SC Cost File'!$A$2:$AB$2,0))/COUNTIF($G$7:$CV$7,AF$7)} -> 0 | AG47: {=INDEX('SC Cost File'!$A$2:$AB$31,MATCH($C47,'SC Cost File'!$A$2:$A$31,0),MATCH(AG$7,'SC Cost File'!$A$2:$AB$2,0))/COUNTIF($G$7:$CV$7,AG$7)} -> 0 | AH47: {=INDEX('SC Cost File'!$A$2:$AB$31,MATCH($C47,'SC Cost File'!$A$2:$A$31,0),MATCH(AH$7,'SC Cost File'!$A$2:$AB$2,0))/COUNTIF($G$7:$CV$7,AH$7)} -> 0 | AI47: {=INDEX('SC Cost File'!$A$2:$AB$31,MATCH($C47,'SC Cost File'!$A$2:$A$31,0),MATCH(AI$7,'SC Cost File'!$A$2:$AB$2,0))/COUNTIF($G$7:$CV$7,AI$7)} -> 0 | ... CV47: {=INDEX('SC Cost File'!$A$2:$AB$31,MATCH($C47,'SC Cost File'!$A$2:$A$31,0),MATCH(CV$7,'SC Cost File'!$A$2:$AB$2,0))/COUNTIF($G$7:$CV$7,CV$7)} -> 0
A48: SC File (Link) | B48: =_xlfn.SINGLE(_xlfn.XLOOKUP(F48, $F$87:$F$95, $E$87:$E$95)) -> 2 | C48: K24 | D48: Jira | E48: Services | F48: OpEx | G48: {=INDEX('SC Cost File'!$A$2:$AB$31,MATCH($C48,'SC Cost File'!$A$2:$A$31,0),MATCH(G$7,'SC Cost File'!$A$2:$AB$2,0))/COUNTIF($G$7:$CV$7,G$7)} -> 75 | H48: {=INDEX('SC Cost File'!$A$2:$AB$31,MATCH($C48,'SC Cost File'!$A$2:$A$31,0),MATCH(H$7,'SC Cost File'!$A$2:$AB$2,0))/COUNTIF($G$7:$CV$7,H$7)} -> 75 | I48: {=INDEX('SC Cost File'!$A$2:$AB$31,MATCH($C48,'SC Cost File'!$A$2:$A$31,0),MATCH(I$7,'SC Cost File'!$A$2:$AB$2,0))/COUNTIF($G$7:$CV$7,I$7)} -> 37.5 | J48: {=INDEX('SC Cost File'!$A$2:$AB$31,MATCH($C48,'SC Cost File'!$A$2:$A$31,0),MATCH(J$7,'SC Cost File'!$A$2:$AB$2,0))/COUNTIF($G$7:$CV$7,J$7)} -> 37.5 | K48: {=INDEX('SC Cost File'!$A$2:$AB$31,MATCH($C48,'SC Cost File'!$A$2:$A$31,0),MATCH(K$7,'SC Cost File'!$A$2:$AB$2,0))/COUNTIF($G$7:$CV$7,K$7)} -> 37.5 | L48: {=INDEX('SC Cost File'!$A$2:$AB$31,MATCH($C48,'SC Cost File'!$A$2:$A$31,0),MATCH(L$7,'SC Cost File'!$A$2:$AB$2,0))/COUNTIF($G$7:$CV$7,L$7)} -> 37.5 | M48: {=INDEX('SC Cost File'!$A$2:$AB$31,MATCH($C48,'SC Cost File'!$A$2:$A$31,0),MATCH(M$7,'SC Cost File'!$A$2:$AB$2,0))/COUNTIF($G$7:$CV$7,M$7)} -> 37.5 | N48: =SUMIF($O$8:$AV$8,">="&'CURRENT FORECAST START DATE'!$C$4,'Weekly Spend'!O48:AV48) -> 875 | O48: {=INDEX('SC Cost File'!$A$2:$AB$31,MATCH($C48,'SC Cost File'!$A$2:$A$31,0),MATCH(O$7,'SC Cost File'!$A$2:$AB$2,0))/COUNTIF($G$7:$CV$7,O$7)} -> 37.5 | P48: {=INDEX('SC Cost File'!$A$2:$AB$31,MATCH($C48,'SC Cost File'!$A$2:$A$31,0),MATCH(P$7,'SC Cost File'!$A$2:$AB$2,0))/COUNTIF($G$7:$CV$7,P$7)} -> 37.5 | Q48: {=INDEX('SC Cost File'!$A$2:$AB$31,MATCH($C48,'SC Cost File'!$A$2:$A$31,0),MATCH(Q$7,'SC Cost File'!$A$2:$AB$2,0))/COUNTIF($G$7:$CV$7,Q$7)} -> 37.5 | R48: {=INDEX('SC Cost File'!$A$2:$AB$31,MATCH($C48,'SC Cost File'!$A$2:$A$31,0),MATCH(R$7,'SC Cost File'!$A$2:$AB$2,0))/COUNTIF($G$7:$CV$7,R$7)} -> 30 | S48: {=INDEX('SC Cost File'!$A$2:$AB$31,MATCH($C48,'SC Cost File'!$A$2:$A$31,0),MATCH(S$7,'SC Cost File'!$A$2:$AB$2,0))/COUNTIF($G$7:$CV$7,S$7)} -> 30 | T48: {=INDEX('SC Cost File'!$A$2:$AB$31,MATCH($C48,'SC Cost File'!$A$2:$A$31,0),MATCH(T$7,'SC Cost File'!$A$2:$AB$2,0))/COUNTIF($G$7:$CV$7,T$7)} -> 30 | U48: {=INDEX('SC Cost File'!$A$2:$AB$31,MATCH($C48,'SC Cost File'!$A$2:$A$31,0),MATCH(U$7,'SC Cost File'!$A$2:$AB$2,0))/COUNTIF($G$7:$CV$7,U$7)} -> 30 | V48: 0 | W48: 0 | X48: {=INDEX('SC Cost File'!$A$2:$AB$31,MATCH($C48,'SC Cost File'!$A$2:$A$31,0),MATCH(X$7,'SC Cost File'!$A$2:$AB$2,0))/COUNTIF($G$7:$CV$7,X$7)} -> 125 | Y48: {=INDEX('SC Cost File'!$A$2:$AB$31,MATCH($C48,'SC Cost File'!$A$2:$A$31,0),MATCH(Y$7,'SC Cost File'!$A$2:$AB$2,0))/COUNTIF($G$7:$CV$7,Y$7)} -> 125 | Z48: {=INDEX('SC Cost File'!$A$2:$AB$31,MATCH($C48,'SC Cost File'!$A$2:$A$31,0),MATCH(Z$7,'SC Cost File'!$A$2:$AB$2,0))/COUNTIF($G$7:$CV$7,Z$7)} -> 125 | AA48: {=INDEX('SC Cost File'!$A$2:$AB$31,MATCH($C48,'SC Cost File'!$A$2:$A$31,0),MATCH(AA$7,'SC Cost File'!$A$2:$AB$2,0))/COUNTIF($G$7:$CV$7,AA$7)} -> 125 | AB48: {=INDEX('SC Cost File'!$A$2:$AB$31,MATCH($C48,'SC Cost File'!$A$2:$A$31,0),MATCH(AB$7,'SC Cost File'!$A$2:$AB$2,0))/COUNTIF($G$7:$CV$7,AB$7)} -> 125 | AC48: {=INDEX('SC Cost File'!$A$2:$AB$31,MATCH($C48,'SC Cost File'!$A$2:$A$31,0),MATCH(AC$7,'SC Cost File'!$A$2:$AB$2,0))/COUNTIF($G$7:$CV$7,AC$7)} -> 125 | AD48: {=INDEX('SC Cost File'!$A$2:$AB$31,MATCH($C48,'SC Cost File'!$A$2:$A$31,0),MATCH(AD$7,'SC Cost File'!$A$2:$AB$2,0))/COUNTIF($G$7:$CV$7,AD$7)} -> 125 | AE48: {=INDEX('SC Cost File'!$A$2:$AB$31,MATCH($C48,'SC Cost File'!$A$2:$A$31,0),MATCH(AE$7,'SC Cost File'!$A$2:$AB$2,0))/COUNTIF($G$7:$CV$7,AE$7)} -> 100 | ... CV48: {=INDEX('SC Cost File'!$A$2:$AB$31,MATCH($C48,'SC Cost File'!$A$2:$A$31,0),MATCH(CV$7,'SC Cost File'!$A$2:$AB$2,0))/COUNTIF($G$7:$CV$7,CV$7)} -> 125
A49: SC File (Link) | B49: =_xlfn.SINGLE(_xlfn.XLOOKUP(F49, $F$87:$F$95, $E$87:$E$95)) -> 2 | C49: K26 | D49: ReAamze | E49: Services | F49: OpEx | G49: {=INDEX('SC Cost File'!$A$2:$AB$31,MATCH($C49,'SC Cost File'!$A$2:$A$31,0),MATCH(G$7,'SC Cost File'!$A$2:$AB$2,0))/COUNTIF($G$7:$CV$7,G$7)} -> 0 | H49: {=INDEX('SC Cost File'!$A$2:$AB$31,MATCH($C49,'SC Cost File'!$A$2:$A$31,0),MATCH(H$7,'SC Cost File'!$A$2:$AB$2,0))/COUNTIF($G$7:$CV$7,H$7)} -> 0 | I49: {=INDEX('SC Cost File'!$A$2:$AB$31,MATCH($C49,'SC Cost File'!$A$2:$A$31,0),MATCH(I$7,'SC Cost File'!$A$2:$AB$2,0))/COUNTIF($G$7:$CV$7,I$7)} -> 0 | J49: {=INDEX('SC Cost File'!$A$2:$AB$31,MATCH($C49,'SC Cost File'!$A$2:$A$31,0),MATCH(J$7,'SC Cost File'!$A$2:$AB$2,0))/COUNTIF($G$7:$CV$7,J$7)} -> 0 | K49: {=INDEX('SC Cost File'!$A$2:$AB$31,MATCH($C49,'SC Cost File'!$A$2:$A$31,0),MATCH(K$7,'SC Cost File'!$A$2:$AB$2,0))/COUNTIF($G$7:$CV$7,K$7)} -> 0 | L49: {=INDEX('SC Cost File'!$A$2:$AB$31,MATCH($C49,'SC Cost File'!$A$2:$A$31,0),MATCH(L$7,'SC Cost File'!$A$2:$AB$2,0))/COUNTIF($G$7:$CV$7,L$7)} -> 0 | M49: {=INDEX('SC Cost File'!$A$2:$AB$31,MATCH($C49,'SC Cost File'!$A$2:$A$31,0),MATCH(M$7,'SC Cost File'!$A$2:$AB$2,0))/COUNTIF($G$7:$CV$7,M$7)} -> 0 | N49: =SUMIF($O$8:$AV$8,">="&'CURRENT FORECAST START DATE'!$C$4,'Weekly Spend'!O49:AV49) -> 0 | O49: {=INDEX('SC Cost File'!$A$2:$AB$31,MATCH($C49,'SC Cost File'!$A$2:$A$31,0),MATCH(O$7,'SC Cost File'!$A$2:$AB$2,0))/COUNTIF($G$7:$CV$7,O$7)} -> 0 | P49: {=INDEX('SC Cost File'!$A$2:$AB$31,MATCH($C49,'SC Cost File'!$A$2:$A$31,0),MATCH(P$7,'SC Cost File'!$A$2:$AB$2,0))/COUNTIF($G$7:$CV$7,P$7)} -> 0 | Q49: {=INDEX('SC Cost File'!$A$2:$AB$31,MATCH($C49,'SC Cost File'!$A$2:$A$31,0),MATCH(Q$7,'SC Cost File'!$A$2:$AB$2,0))/COUNTIF($G$7:$CV$7,Q$7)} -> 0 | R49: {=INDEX('SC Cost File'!$A$2:$AB$31,MATCH($C49,'SC Cost File'!$A$2:$A$31,0),MATCH(R$7,'SC Cost File'!$A$2:$AB$2,0))/COUNTIF($G$7:$CV$7,R$7)} -> 0 | S49: {=INDEX('SC Cost File'!$A$2:$AB$31,MATCH($C49,'SC Cost File'!$A$2:$A$31,0),MATCH(S$7,'SC Cost File'!$A$2:$AB$2,0))/COUNTIF($G$7:$CV$7,S$7)} -> 0 | T49: {=INDEX('SC Cost File'!$A$2:$AB$31,MATCH($C49,'SC Cost File'!$A$2:$A$31,0),MATCH(T$7,'SC Cost File'!$A$2:$AB$2,0))/COUNTIF($G$7:$CV$7,T$7)} -> 0 | U49: {=INDEX('SC Cost File'!$A$2:$AB$31,MATCH($C49,'SC Cost File'!$A$2:$A$31,0),MATCH(U$7,'SC Cost File'!$A$2:$AB$2,0))/COUNTIF($G$7:$CV$7,U$7)} -> 0 | V49: {=INDEX('SC Cost File'!$A$2:$AB$31,MATCH($C49,'SC Cost File'!$A$2:$A$31,0),MATCH(V$7,'SC Cost File'!$A$2:$AB$2,0))/COUNTIF($G$7:$CV$7,V$7)} -> 0 | W49: 7455 | X49: 0 | Y49: 0 | Z49: 0 | AA49: {=INDEX('SC Cost File'!$A$2:$AB$31,MATCH($C49,'SC Cost File'!$A$2:$A$31,0),MATCH(AA$7,'SC Cost File'!$A$2:$AB$2,0))/COUNTIF($G$7:$CV$7,AA$7)} -> 0 | AB49: {=INDEX('SC Cost File'!$A$2:$AB$31,MATCH($C49,'SC Cost File'!$A$2:$A$31,0),MATCH(AB$7,'SC Cost File'!$A$2:$AB$2,0))/COUNTIF($G$7:$CV$7,AB$7)} -> 0 | AC49: {=INDEX('SC Cost File'!$A$2:$AB$31,MATCH($C49,'SC Cost File'!$A$2:$A$31,0),MATCH(AC$7,'SC Cost File'!$A$2:$AB$2,0))/COUNTIF($G$7:$CV$7,AC$7)} -> 0 | AD49: {=INDEX('SC Cost File'!$A$2:$AB$31,MATCH($C49,'SC Cost File'!$A$2:$A$31,0),MATCH(AD$7,'SC Cost File'!$A$2:$AB$2,0))/COUNTIF($G$7:$CV$7,AD$7)} -> 0 | AE49: {=INDEX('SC Cost File'!$A$2:$AB$31,MATCH($C49,'SC Cost File'!$A$2:$A$31,0),MATCH(AE$7,'SC Cost File'!$A$2:$AB$2,0))/COUNTIF($G$7:$CV$7,AE$7)} -> 0 | AF49: {=INDEX('SC Cost File'!$A$2:$AB$31,MATCH($C49,'SC Cost File'!$A$2:$A$31,0),MATCH(AF$7,'SC Cost File'!$A$2:$AB$2,0))/COUNTIF($G$7:$CV$7,AF$7)} -> 0 | AG49: {=INDEX('SC Cost File'!$A$2:$AB$31,MATCH($C49,'SC Cost File'!$A$2:$A$31,0),MATCH(AG$7,'SC Cost File'!$A$2:$AB$2,0))/COUNTIF($G$7:$CV$7,AG$7)} -> 0 | AH49: {=INDEX('SC Cost File'!$A$2:$AB$31,MATCH($C49,'SC Cost File'!$A$2:$A$31,0),MATCH(AH$7,'SC Cost File'!$A$2:$AB$2,0))/COUNTIF($G$7:$CV$7,AH$7)} -> 0 | ... CV49: {=INDEX('SC Cost File'!$A$2:$AB$31,MATCH($C49,'SC Cost File'!$A$2:$A$31,0),MATCH(CV$7,'SC Cost File'!$A$2:$AB$2,0))/COUNTIF($G$7:$CV$7,CV$7)} -> 0
A50: SC File (Link) | B50: =_xlfn.SINGLE(_xlfn.XLOOKUP(F50, $F$87:$F$95, $E$87:$E$95)) -> 2 | C50: K27 | D50: Kiteworks | E50: Services | F50: OpEx | G50: {=INDEX('SC Cost File'!$A$2:$AB$31,MATCH($C50,'SC Cost File'!$A$2:$A$31,0),MATCH(G$7,'SC Cost File'!$A$2:$AB$2,0))/COUNTIF($G$7:$CV$7,G$7)} -> 100 | H50: {=INDEX('SC Cost File'!$A$2:$AB$31,MATCH($C50,'SC Cost File'!$A$2:$A$31,0),MATCH(H$7,'SC Cost File'!$A$2:$AB$2,0))/COUNTIF($G$7:$CV$7,H$7)} -> 100 | I50: {=INDEX('SC Cost File'!$A$2:$AB$31,MATCH($C50,'SC Cost File'!$A$2:$A$31,0),MATCH(I$7,'SC Cost File'!$A$2:$AB$2,0))/COUNTIF($G$7:$CV$7,I$7)} -> 50 | J50: {=INDEX('SC Cost File'!$A$2:$AB$31,MATCH($C50,'SC Cost File'!$A$2:$A$31,0),MATCH(J$7,'SC Cost File'!$A$2:$AB$2,0))/COUNTIF($G$7:$CV$7,J$7)} -> 50 | K50: {=INDEX('SC Cost File'!$A$2:$AB$31,MATCH($C50,'SC Cost File'!$A$2:$A$31,0),MATCH(K$7,'SC Cost File'!$A$2:$AB$2,0))/COUNTIF($G$7:$CV$7,K$7)} -> 50 | L50: {=INDEX('SC Cost File'!$A$2:$AB$31,MATCH($C50,'SC Cost File'!$A$2:$A$31,0),MATCH(L$7,'SC Cost File'!$A$2:$AB$2,0))/COUNTIF($G$7:$CV$7,L$7)} -> 50 | M50: {=INDEX('SC Cost File'!$A$2:$AB$31,MATCH($C50,'SC Cost File'!$A$2:$A$31,0),MATCH(M$7,'SC Cost File'!$A$2:$AB$2,0))/COUNTIF($G$7:$CV$7,M$7)} -> 50 | N50: =SUMIF($O$8:$AV$8,">="&'CURRENT FORECAST START DATE'!$C$4,'Weekly Spend'!O50:AV50) -> 0 | O50: 0 | P50: 0 | Q50: 0 | R50: 0 | S50: 0 | T50: 0 | U50: 0 | V50: 0 | W50: 0 | X50: 0 | Y50: 0 | Z50: 0 | AA50: 0 | AB50: 0 | AC50: 0 | AD50: 0 | AE50: 0 | AF50: 0 | AG50: 0 | AH50: 0 | AI50: 0 | AJ50: 0 | AK50: 0 | AL50: 0 | AM50: 0 | AN50: 0 | AO50: 0 | AP50: 0 | AQ50: 0 | AR50: 0 | AS50: 0 | AT50: 0 | AU50: 0 | AV50: 0 | AW50: 0 | AX50: 0 | AY50: 0 | AZ50: 0 | BA50: 0 | BB50: 0 | BC50: 0 | BD50: 0 | BE50: 0 | BF50: 0 | BG50: 0 | BH50: 0 | BI50: 0 | BJ50: 0 | BK50: 0 | BL50: 0 | BM50: 0 | BN50: 0 | BO50: 0 | BP50: 0 | BQ50: 0 | BR50: 0 | BS50: 0 | BT50: 0 | BU50: 0 | BV50: 0 | BW50: 0 | BX50: 0 | BY50: 0 | BZ50: 0 | CA50: 0 | CB50: 0 | CC50: 0 | CD50: 0 | CE50: 0 | CF50: 0 | CG50: 0 | CH50: 0 | CI50: 0 | CJ50: 0 | CK50: 0 | CL50: 0 | CM50: 0 | CN50: 0 | CO50: 0 | CP50: 0 | CQ50: 0 | CR50: 0 | CS50: 0 | CT50: 0 | CU50: 0 | CV50: 0
A51: SC File (Link) | B51: =_xlfn.SINGLE(_xlfn.XLOOKUP(F51, $F$87:$F$95, $E$87:$E$95)) -> 2 | C51: K16 | D51: Syntes Language Group | E51: Contract | F51: OpEx | G51: {=INDEX('SC Cost File'!$A$2:$AB$31,MATCH($C51,'SC Cost File'!$A$2:$A$31,0),MATCH(G$7,'SC Cost File'!$A$2:$AB$2,0))/COUNTIF($G$7:$CV$7,G$7)} -> 562.5 | H51: {=INDEX('SC Cost File'!$A$2:$AB$31,MATCH($C51,'SC Cost File'!$A$2:$A$31,0),MATCH(H$7,'SC Cost File'!$A$2:$AB$2,0))/COUNTIF($G$7:$CV$7,H$7)} -> 562.5 | I51: {=INDEX('SC Cost File'!$A$2:$AB$31,MATCH($C51,'SC Cost File'!$A$2:$A$31,0),MATCH(I$7,'SC Cost File'!$A$2:$AB$2,0))/COUNTIF($G$7:$CV$7,I$7)} -> 0 | J51: {=INDEX('SC Cost File'!$A$2:$AB$31,MATCH($C51,'SC Cost File'!$A$2:$A$31,0),MATCH(J$7,'SC Cost File'!$A$2:$AB$2,0))/COUNTIF($G$7:$CV$7,J$7)} -> 0 | K51: {=INDEX('SC Cost File'!$A$2:$AB$31,MATCH($C51,'SC Cost File'!$A$2:$A$31,0),MATCH(K$7,'SC Cost File'!$A$2:$AB$2,0))/COUNTIF($G$7:$CV$7,K$7)} -> 0 | L51: {=INDEX('SC Cost File'!$A$2:$AB$31,MATCH($C51,'SC Cost File'!$A$2:$A$31,0),MATCH(L$7,'SC Cost File'!$A$2:$AB$2,0))/COUNTIF($G$7:$CV$7,L$7)} -> 0 | M51: {=INDEX('SC Cost File'!$A$2:$AB$31,MATCH($C51,'SC Cost File'!$A$2:$A$31,0),MATCH(M$7,'SC Cost File'!$A$2:$AB$2,0))/COUNTIF($G$7:$CV$7,M$7)} -> 0 | N51: =SUMIF($O$8:$AV$8,">="&'CURRENT FORECAST START DATE'!$C$4,'Weekly Spend'!O51:AV51) -> 0 | O51: {=INDEX('SC Cost File'!$A$2:$AB$31,MATCH($C51,'SC Cost File'!$A$2:$A$31,0),MATCH(O$7,'SC Cost File'!$A$2:$AB$2,0))/COUNTIF($G$7:$CV$7,O$7)} -> 0 | P51: {=INDEX('SC Cost File'!$A$2:$AB$31,MATCH($C51,'SC Cost File'!$A$2:$A$31,0),MATCH(P$7,'SC Cost File'!$A$2:$AB$2,0))/COUNTIF($G$7:$CV$7,P$7)} -> 0 | Q51: {=INDEX('SC Cost File'!$A$2:$AB$31,MATCH($C51,'SC Cost File'!$A$2:$A$31,0),MATCH(Q$7,'SC Cost File'!$A$2:$AB$2,0))/COUNTIF($G$7:$CV$7,Q$7)} -> 0 | R51: {=INDEX('SC Cost File'!$A$2:$AB$31,MATCH($C51,'SC Cost File'!$A$2:$A$31,0),MATCH(R$7,'SC Cost File'!$A$2:$AB$2,0))/COUNTIF($G$7:$CV$7,R$7)} -> 0 | S51: {=INDEX('SC Cost File'!$A$2:$AB$31,MATCH($C51,'SC Cost File'!$A$2:$A$31,0),MATCH(S$7,'SC Cost File'!$A$2:$AB$2,0))/COUNTIF($G$7:$CV$7,S$7)} -> 0 | T51: {=INDEX('SC Cost File'!$A$2:$AB$31,MATCH($C51,'SC Cost File'!$A$2:$A$31,0),MATCH(T$7,'SC Cost File'!$A$2:$AB$2,0))/COUNTIF($G$7:$CV$7,T$7)} -> 0 | U51: {=INDEX('SC Cost File'!$A$2:$AB$31,MATCH($C51,'SC Cost File'!$A$2:$A$31,0),MATCH(U$7,'SC Cost File'!$A$2:$AB$2,0))/COUNTIF($G$7:$CV$7,U$7)} -> 0 | V51: {=INDEX('SC Cost File'!$A$2:$AB$31,MATCH($C51,'SC Cost File'!$A$2:$A$31,0),MATCH(V$7,'SC Cost File'!$A$2:$AB$2,0))/COUNTIF($G$7:$CV$7,V$7)} -> 0 | ... CV51: {=INDEX('SC Cost File'!$A$2:$AB$31,MATCH($C51,'SC Cost File'!$A$2:$A$31,0),MATCH(CV$7,'SC Cost File'!$A$2:$AB$2,0))/COUNTIF($G$7:$CV$7,CV$7)} -> 281.25
D52: Legal Fees/Accounting | E52: Services | F52: OpEx | N52: =SUMIF($O$8:$AV$8,">="&'CURRENT FORECAST START DATE'!$C$4,'Weekly Spend'!O52:AV52) -> 53376.8 | O52: 0 | P52: 0 | Q52: 0 | R52: 0 | S52: 0 | T52: 0 | U52: 0 | V52: 0 | W52: 0 | X52: 0 | Y52: 0 | AA52: 0 | AO52: 3376.8 | AP52: 0 | AQ52: 0 | AR52: 0 | AS52: 0 | AT52: 0 | AU52: =25000+25000 -> 50000 | AV52: 0 | AW52: 0 | AZ52: 0 | BC52: 0 | BD52: 0 | BE52: 0 | BF52: 0 | BG52: 0 | BH52: 0 | BI52: 0 | BJ52: 0 | BK52: 0 | BL52: 0 | BM52: 0 | BN52: 0 | BO52: 0 | BP52: 0 | BQ52: 0 | BR52: 0 | BS52: 0 | BT52: 0 | BU52: 0 | BV52: 0 | BW52: 0 | BX52: 0 | BY52: 0 | BZ52: 0 | CA52: 0 | CB52: 0 | CC52: 0 | CD52: 0 | CE52: 0 | CF52: 0 | CG52: 0 | CH52: 0 | CI52: 0 | CJ52: 0 | CK52: 0 | CL52: 0 | CM52: 0 | CN52: 0 | CO52: 0 | CP52: 0 | CQ52: 0 | CR52: 0 | CS52: 0 | CT52: 0 | CU52: 0 | CV52: 0
D53: Other Audit cert Pro/Import | E53: Services | F53: OpEx | N53: =SUMIF($O$8:$AV$8,">="&'CURRENT FORECAST START DATE'!$C$4,'Weekly Spend'!O53:AV53) -> 0 | AM53: 170 | AN53: 1577.91
A54: ST Cash File (Manual) | D54: Insurance | E54: Services | F54: OpEx | N54: =SUMIF($O$8:$AV$8,">="&'CURRENT FORECAST START DATE'!$C$4,'Weekly Spend'!O54:AV54) -> 0 | O54: 27202.56 | P54: 0 | Q54: 0 | R54: 0 | S54: 0 | T54: 0 | U54: 0 | V54: 0 | W54: 0 | X54: 0 | Y54: 0 | Z54: 0 | AA54: 0 | AB54: 0 | AC54: 0 | AD54: 0 | AE54: 0 | AF54: 0 | AG54: 0 | AH54: 0 | AI54: 0 | AJ54: 0 | AK54: 0 | AL54: 0 | AM54: 0 | AN54: 0 | AO54: 0 | AP54: 0 | AQ54: 0 | AR54: 0 | AS54: 0 | AT54: 0 | AU54: 0 | AV54: 0 | AW54: 0 | AX54: 0 | AY54: 0 | AZ54: 0 | BA54: 0 | BB54: 0 | BC54: 0 | BD54: 0 | BE54: 0 | BF54: 0 | BG54: 0 | BH54: 0 | BI54: 0 | BJ54: 0 | BK54: 0 | BL54: 0 | BM54: 0 | BN54: 0 | BO54: 0 | BP54: 0 | BQ54: 0 | BR54: 30000 | BS54: 0 | BT54: 0 | BU54: 0 | BV54: 0 | BW54: 0 | BX54: 0 | BY54: 0 | BZ54: 0 | CA54: 0 | CB54: 0 | CC54: 0 | CD54: 0 | CE54: 0 | CF54: 0 | CG54: 0 | CH54: 0 | CI54: 0 | CJ54: 0 | CK54: 0 | CL54: 0 | CM54: 0 | CN54: 0 | CO54: 0 | CP54: 0 | CQ54: 0 | CR54: 0 | CS54: 0 | CT54: 0 | CU54: 0 | CV54: 0
A55: Manual Invoice | B55: =_xlfn.SINGLE(_xlfn.XLOOKUP(F55, $F$87:$F$95, $E$87:$E$95)) -> 8 | C55: K42 | D55: BACL | E55: Q20 FCC Approval | F55: NRE | I55: 9000 | N55: =SUMIF($O$8:$AV$8,">="&'CURRENT FORECAST START DATE'!$C$4,'Weekly Spend'!O55:AV55) -> 0 | O55: 0 | P55: 0 | Q55: 0 | R55: 0 | S55: 0 | T55: 0 | U55: 0 | V55: 0 | W55: 0 | X55: 0 | Y55: 0 | Z55: 0 | AA55: 0 | AB55: 0 | AC55: 0 | AD55: 0 | AE55: 0 | AF55: 0 | AG55: 0 | AH55: 0 | AI55: 0 | AJ55: 0 | AK55: 0 | AL55: 0 | AM55: 0 | AN55: 0 | AO55: 0 | AP55: 0 | AQ55: 0 | AR55: 0 | AS55: 0 | AT55: 0 | AU55: 0 | AV55: 0 | AW55: 0 | AX55: 0 | AY55: 0 | AZ55: 0 | BA55: 0 | BB55: 0 | BC55: 0 | BD55: 0 | BE55: 0 | BF55: 0 | BG55: 0 | BH55: 0 | BI55: 0 | BJ55: 0 | BK55: 0 | BL55: 0 | BM55: 0 | BN55: 0 | BO55: 0 | BP55: 0 | BQ55: 0 | BR55: 0 | BS55: 0 | BT55: 0 | BU55: 0 | BV55: 0 | BW55: 0 | BX55: 0 | BY55: 0 | BZ55: 0 | CA55: 0 | CB55: 0 | CC55: 0 | CD55: 0 | CE55: 0 | CF55: 0 | CG55: 0 | CH55: 0 | CI55: 0 | CJ55: 0 | CK55: 0 | CL55: 0 | CM55: 0 | CN55: 0 | CO55: 0 | CP55: 0 | CQ55: 0 | CR55: 0 | CS55: 0 | CT55: 0 | CU55: 0 | CV55: 0
D56: Travel | E56: Opex | F56: OpEx | N56: =SUMIF($O$8:$AV$8,">="&'CURRENT FORECAST START DATE'!$C$4,'Weekly Spend'!O56:AV56) -> 20000 | O56: 0 | P56: 0 | Q56: 0 | R56: 0 | S56: 0 | T56: 0 | U56: =280.12 -> 280.12 | V56: 0 | W56: =2434.61 -> 2434.61 | X56: 523 | Y56: 0 | Z56: 10000 | AA56: 0 | AB56: 0 | AC56: 0 | AD56: 0 | AE56: 0 | AF56: 15000 | AG56: 10000 | AH56: 0 | AI56: 10000 | AJ56: =15000+196.52+1422.05 -> 16618.57 | AK56: 15000 | AL56: 0 | AM56: 0 | AN56: 10000 | AO56: 0 | AP56: 0 | AQ56: 10000 | AR56: 0 | AS56: 0 | AT56: 10000 | AU56: 0 | AV56: 0 | AW56: 0 | AX56: 0 | AY56: 20000 | AZ56: 0 | BA56: 0 | BB56: 0 | BC56: 0 | BD56: 20000 | BE56: 0 | BF56: 0 | BG56: 0 | BH56: 0 | BI56: 10000 | BJ56: 0 | BK56: 0 | BL56: 0 | BM56: 0 | BN56: 0 | BO56: 0 | BP56: 0 | BQ56: 0 | BR56: 0 | BS56: 0 | BT56: 0 | BU56: 0 | BV56: 0 | BW56: 0 | BX56: 0 | BY56: 0 | BZ56: 0 | CA56: 0 | CB56: 0 | CC56: 0 | CD56: 0 | CE56: 0 | CF56: 0 | CG56: 0 | CH56: 0 | CI56: 0 | CJ56: 0 | CK56: 0 | CL56: 0 | CM56: 0 | CN56: 0 | CO56: 0 | CP56: 0 | CQ56: 0 | CR56: 0 | CS56: 0 | CT56: 0 | CU56: 0 | CV56: 0
D57: Other Marketing | E57: Services | F57: Marketing | N57: =SUMIF($O$8:$AV$8,">="&'CURRENT FORECAST START DATE'!$C$4,'Weekly Spend'!O57:AV57) -> 19250 | Z57: 2000 | AD57: 2000 | AI57: 4000 | AJ57: =5250+3500 -> 8750 | AM57: 4000 | AN57: 2500 | AP57: 5250 | AQ57: 6000 | AV57: 8000 | AZ57: 8000 | BD57: 8000
D58: Exhibitions | E58: Services | F58: Marketing | N58: =SUMIF($O$8:$AV$8,">="&'CURRENT FORECAST START DATE'!$C$4,'Weekly Spend'!O58:AV58) -> 25000 | AB58: 7000 | AC58: 6000 | AF58: 18400 | AQ58: 25000 | BA58: =300 -> 300
D59: Gale Strategies | E59: Opex | F59: Marketing | N59: =SUMIF($O$8:$AV$8,">="&'CURRENT FORECAST START DATE'!$C$4,'Weekly Spend'!O59:AV59) -> 22200 | O59: 0 | P59: 0 | Q59: 0 | R59: 0 | S59: 0 | T59: 0 | U59: 3884.4 | V59: 0 | W59: 0 | X59: 0 | Y59: 6508 | Z59: 0 | AA59: 0 | AB59: 0 | AC59: 0 | AE59: 6509 | AF59: 0 | AG59: 0 | AH59: 6509 | AI59: 0 | AJ59: 0 | AK59: 0 | AL59: 0 | AM59: ='Labor Spend'!G61+'Labor Spend'!G62 -> 9500 | AN59: 0 | AO59: 0 | AP59: 0 | AQ59: ='Labor Spend'!K61+'Labor Spend'!K62 -> 11500 | AR59: 0 | AS59: 0 | AT59: 0 | AU59: ='Labor Spend'!I61+'Labor Spend'!I62 -> 10700 | AV59: ='Labor Spend'!P61 -> 0 | AW59: 0 | AX59: 0 | AY59: ='Labor Spend'!M61+'Labor Spend'!M62 -> 0 | AZ59: ='Labor Spend'!J61+'Labor Spend'!J62 -> 11500 | BA59: 0 | BB59: 0 | BC59: 0 | BD59: ='Labor Spend'!K61+'Labor Spend'!K62 -> 11500 | BE59: 0 | BF59: 0 | BG59: 0 | BH59: 8700 | BI59: 0 | BJ59: 0 | BK59: 0 | BL59: 0 | BM59: 0 | BN59: 0 | BO59: 0 | BP59: 0 | BQ59: 0 | BR59: 0 | BS59: 0 | BT59: 0 | BU59: 0 | BV59: 0 | BW59: 0 | BX59: 0 | BY59: 0 | BZ59: 0 | CA59: 0 | CB59: 0 | CC59: 0 | CD59: 0 | CE59: 0 | CF59: 0 | CG59: 0 | CH59: 0 | CI59: 0 | CJ59: 0 | CK59: 0 | CL59: 0 | CM59: 0 | CN59: 0 | CO59: 0 | CP59: 0 | CQ59: 0 | CR59: 0 | CS59: 0 | CT59: 0 | CU59: 0 | CV59: 0
A60: Manual Invoice | B60: =_xlfn.SINGLE(_xlfn.XLOOKUP(F60, $F$87:$F$95, $E$87:$E$95)) -> 2 | C60: K43 | D60: Ramp | E60: Annual Subscription | F60: OpEx | I60: 800 | N60: =SUMIF($O$8:$AV$8,">="&'CURRENT FORECAST START DATE'!$C$4,'Weekly Spend'!O60:AV60) -> 0 | O60: 0 | P60: 0 | Q60: 0 | R60: 0 | S60: 0 | T60: 0 | U60: 9132.85 | V60: 0 | W60: 0 | X60: 0 | Y60: 18000 | Z60: 0 | AA60: 0 | AB60: 0 | AC60: 0 | AD60: 0 | AE60: 0 | AF60: 0 | AG60: 0 | AH60: 0 | AI60: 0 | AJ60: 0 | AK60: 0 | AL60: 0 | AM60: 0 | AN60: 0 | AO60: 0 | AP60: 0 | AQ60: 0 | AR60: 0 | AS60: 0 | AT60: 0 | AU60: 0 | AV60: 0 | AW60: 0 | AX60: 0 | AY60: 0 | AZ60: 0 | BA60: 0 | BB60: 0 | BC60: 0 | BD60: 0 | BE60: 0 | BF60: 0 | BG60: 0 | BH60: 0 | BI60: 0 | BJ60: 0 | BK60: 0 | BL60: 0 | BM60: 0 | BN60: 0 | BO60: 0 | BP60: 0 | BQ60: 0 | BR60: 0 | BS60: 0 | BT60: 0 | BU60: 0 | BV60: 0 | BW60: 0 | BX60: 0 | BY60: 0 | BZ60: 0 | CA60: 0 | CB60: 0 | CC60: 0 | CD60: 0 | CE60: 0 | CF60: 0 | CG60: 0 | CH60: 0 | CI60: 0 | CJ60: 0 | CK60: 0 | CL60: 0 | CM60: 0 | CN60: 0 | CO60: 0 | CP60: 0 | CQ60: 0 | CR60: 0 | CS60: 0 | CT60: 0 | CU60: 0 | CV60: 0
A61: Manual Invoice | B61: =_xlfn.SINGLE(_xlfn.XLOOKUP(F61, $F$87:$F$95, $E$87:$E$95)) -> 4 | C61: K44 | D61: Klavio | E61: Annual Subscription | F61: Marketing | I61: 8169.12 | N61: =SUMIF($O$8:$AV$8,">="&'CURRENT FORECAST START DATE'!$C$4,'Weekly Spend'!O61:AV61) -> 3000 | O61: 0 | P61: 0 | Q61: 0 | R61: 0 | S61: 0 | T61: 0 | U61: 0 | V61: 0 | W61: 0 | X61: 0 | Y61: 0 | Z61: 1000 | AA61: 0 | AB61: 0 | AC61: 0 | AD61: 1200 | AE61: 0 | AF61: 0 | AG61: 0 | AH61: 0 | AI61: 1200 | AJ61: 0 | AK61: 0 | AL61: 0 | AM61: 1200 | AN61: 0 | AO61: 0 | AP61: 0 | AQ61: 1500 | AR61: 0 | AS61: 0 | AT61: 0 | AU61: 0 | AV61: 1500 | AW61: 0 | AX61: 0 | AY61: 0 | AZ61: 2000 | BA61: 0 | BB61: 0 | BC61: 0 | BD61: 2500 | BE61: 0 | BF61: 0 | BG61: 0 | BH61: 0 | BI61: 3000 | BJ61: 0 | BK61: 0 | BL61: 0 | BM61: 0 | BN61: 0 | BO61: 0 | BP61: 0 | BQ61: 0 | BR61: 0 | BS61: 0 | BT61: 0 | BU61: 0 | BV61: 0 | BW61: 0 | BX61: 0 | BY61: 0 | BZ61: 0 | CA61: 0 | CB61: 0 | CC61: 0 | CD61: 0 | CE61: 0 | CF61: 0 | CG61: 0 | CH61: 0 | CI61: 0 | CJ61: 0 | CK61: 0 | CL61: 0 | CM61: 0 | CN61: 0 | CO61: 0 | CP61: 0 | CQ61: 0 | CR61: 0 | CS61: 0 | CT61: 0 | CU61: 0 | CV61: 0
D62: Berkley Tech | E62: Insurance | F62: OpEx | N62: =SUMIF($O$8:$AV$8,">="&'CURRENT FORECAST START DATE'!$C$4,'Weekly Spend'!O62:AV62) -> 2004 | O62: 0 | P62: 0 | Q62: 0 | R62: 0 | S62: 0 | T62: 0 | U62: 0 | V62: 4032 | W62: 0 | X62: 0 | Y62: 2004 | Z62: 0 | AA62: 0 | AB62: 0 | AC62: 0 | AD62: 2004 | AE62: 0 | AF62: 0 | AG62: 0 | AH62: 2004 | AI62: 0 | AJ62: 0 | AK62: 0 | AL62: 2004 | AM62: 0 | AN62: 0 | AO62: 2004 | AP62: 0 | AR62: 0 | AS62: 0 | AT62: 0 | AU62: 0 | AV62: 0 | AW62: 0 | AX62: 0 | AY62: 0 | AZ62: 0 | BA62: 0 | BB62: 0 | BC62: 0 | BD62: 0 | BE62: 0 | BF62: 0 | BG62: 0 | BH62: 0 | BI62: 0 | BJ62: 0 | BK62: 0 | BL62: 0 | BM62: 0 | BN62: 0 | BO62: 0 | BP62: 0 | BQ62: 0 | BR62: 0 | BS62: 0 | BT62: 0 | BU62: 0 | BV62: 0 | BW62: 0 | BX62: 0 | BY62: 0 | BZ62: 0 | CA62: 0 | CB62: 0 | CC62: 0 | CD62: 0 | CE62: 0 | CF62: 0 | CG62: 0 | CH62: 0 | CI62: 0 | CJ62: 0 | CK62: 0 | CL62: 0 | CM62: 0 | CN62: 0 | CO62: 0 | CP62: 0 | CQ62: 0 | CR62: 0 | CS62: 0 | CT62: 0 | CU62: 0 | CV62: 0
D63: Rosenthal | E63: Set up Fees/Maintenance | F63: OpEx | N63: =SUMIF($O$8:$AV$8,">="&'CURRENT FORECAST START DATE'!$C$4,'Weekly Spend'!O63:AV63) -> 0 | O63: 0 | P63: 0 | Q63: 0 | R63: 0 | S63: 0 | T63: 0 | U63: 0 | V63: 0 | W63: 0 | X63: 0 | Y63: 5000 | Z63: 0 | AA63: 0 | AB63: 0 | AC63: 0 | AD63: 0 | AE63: 0 | AF63: 0 | AG63: 0 | AH63: 0 | AI63: 0 | AJ63: 0 | AK63: 0 | AL63: 0 | AM63: 0 | AN63: 0 | AO63: 0 | AP63: 0 | AQ63: 0 | AR63: 0 | AS63: 0 | AT63: 0 | AU63: 0 | AV63: 0 | AW63: 0 | AX63: 0 | AY63: 0 | AZ63: 0 | BA63: 0 | BB63: 0 | BC63: 0 | BD63: 0 | BE63: 0 | BF63: 0 | BG63: 0 | BH63: 0 | BI63: 0 | BJ63: 0 | BK63: 0 | BL63: 0 | BM63: 0 | BN63: 0 | BO63: 0 | BP63: 0 | BQ63: 0 | BR63: 0 | BS63: 0 | BT63: 0 | BU63: 0 | BV63: 0 | BW63: 0 | BX63: 0 | BY63: 0 | BZ63: 0 | CA63: 0 | CB63: 0 | CC63: 0 | CD63: 0 | CE63: 0 | CF63: 0 | CG63: 0 | CH63: 0 | CI63: 0 | CJ63: 0 | CK63: 0 | CL63: 0 | CM63: 0 | CN63: 0 | CO63: 0 | CP63: 0 | CQ63: 0 | CR63: 0 | CS63: 0 | CT63: 0 | CU63: 0 | CV63: 0
D64: Impello | E64: AR Insurance | F64: OpEx | N64: =SUMIF($O$8:$AV$8,">="&'CURRENT FORECAST START DATE'!$C$4,'Weekly Spend'!O64:AV64) -> 0 | O64: 0 | P64: 0 | Q64: 0 | R64: 0 | S64: 0 | T64: 0 | U64: 0 | V64: 0 | W64: 0 | X64: 0 | Y64: 0 | Z64: 0 | AB64: 0 | AC64: 0 | AE64: 0 | AF64: 0 | AG64: 0 | AH64: 0 | AI64: 4500 | AJ64: 0 | AK64: 0 | AL64: 0 | AN64: 0 | AO64: 0 | AP64: 0 | AQ64: 0 | AR64: 0 | AS64: 0 | AT64: 0 | AU64: 0 | AV64: 0 | AW64: 0 | AX64: 0 | AY64: 0 | AZ64: 0 | BA64: 5000 | BB64: 0 | BC64: 0 | BD64: 0 | BE64: 0 | BF64: 0 | BG64: 0 | BH64: 0 | BI64: 0 | BJ64: 0 | BK64: 0 | BL64: 0 | BM64: 0 | BN64: 5000 | BO64: 0 | BP64: 0 | BQ64: 0 | BR64: 0 | BS64: 0 | BT64: 0 | BU64: 0 | BV64: 0 | BW64: 0 | BX64: 0 | BY64: 0 | BZ64: 0 | CA64: 5000 | CB64: 0 | CC64: 0 | CD64: 0 | CE64: 0 | CF64: 0 | CG64: 0 | CH64: 0 | CI64: 0 | CJ64: 0 | CK64: 0 | CL64: 0 | CM64: 0 | CN64: 0 | CO64: 0 | CP64: 0 | CQ64: 0 | CR64: 0 | CS64: 0 | CT64: 0 | CU64: 0 | CV64: 0
D65: Rosenthal | E65: Admin Cost | F65: OpEx | N65: =SUMIF($O$8:$AV$8,">="&'CURRENT FORECAST START DATE'!$C$4,'Weekly Spend'!O65:AV65) -> 0 | O65: 0 | P65: 0 | Q65: 0 | R65: 0 | S65: 0 | T65: 0 | U65: 0 | V65: 0 | W65: 0 | X65: 0 | Y65: 0 | Z65: 0 | AA65: 0 | AB65: 0 | AC65: 0 | AD65: 0 | AE65: 0 | AF65: 0 | AG65: 0 | AH65: 0 | AI65: 0 | AJ65: 0 | AK65: 0 | AL65: 0 | AM65: 0 | AN65: 0 | AO65: 0 | AP65: 0 | AQ65: 0 | AR65: 0 | AS65: 0 | AT65: 0 | AU65: 0 | AV65: 0 | AW65: 0 | AX65: 0 | AY65: 0 | AZ65: 0 | BA65: 0 | BB65: 0 | BC65: 0 | BD65: 0 | BE65: 0 | BF65: 0 | BG65: 0 | BH65: 0 | BI65: 0 | BJ65: 0 | BK65: 0 | BL65: 0 | BM65: 0 | BN65: 0 | BO65: 0 | BP65: 0 | BQ65: 0 | BR65: 0 | BS65: 0 | BT65: 0 | BU65: 0 | BV65: 0 | BW65: 0 | BX65: 0 | BY65: 0 | BZ65: 0 | CA65: 0 | CB65: 0 | CC65: 0 | CD65: 0 | CE65: 0 | CF65: 0 | CG65: 0 | CH65: 0 | CI65: 0 | CJ65: 0 | CK65: 0 | CL65: 0 | CM65: 0 | CN65: 0 | CO65: 0 | CP65: 0 | CQ65: 0 | CR65: 0 | CS65: 0 | CT65: 0 | CU65: 0 | CV65: 0
D66: Rosenthal | E66: Factoring Invoice Cost | F66: OpEx | N66: =SUMIF($O$8:$AV$8,">="&'CURRENT FORECAST START DATE'!$C$4,'Weekly Spend'!O66:AV66) -> 0 | O66: 0 | P66: 0 | Q66: 0 | R66: 0 | S66: 0 | T66: 0 | U66: 0 | V66: 0 | W66: 0 | X66: 0 | Y66: 0 | Z66: 0 | AA66: 0 | AB66: 0 | AC66: 0 | AD66: 0 | AE66: 0 | AF66: 0 | AG66: 0 | AH66: 0 | AI66: 0 | AJ66: 0 | AK66: 0 | AL66: 0 | AM66: 0 | AN66: 0 | AO66: 0 | AP66: 0 | AQ66: 0 | AR66: 0 | AS66: 0 | AT66: 0 | AU66: 0 | AV66: 0 | AW66: 0 | AX66: 0 | AY66: 0 | AZ66: 0 | BA66: 0 | BB66: 0 | BC66: 0 | BD66: 0 | BE66: 0 | BF66: 0 | BG66: 0 | BH66: 0 | BI66: 0 | BJ66: 0 | BK66: 0 | BL66: 0 | BM66: 0 | BN66: 0 | BO66: 0 | BP66: 0 | BQ66: 0 | BR66: 0 | BS66: 0 | BT66: 0 | BU66: 0 | BV66: 0 | BW66: 0 | BX66: 0 | BY66: 0 | BZ66: 0 | CA66: 0 | CB66: 0 | CC66: 0 | CD66: 0 | CE66: 0 | CF66: 0 | CG66: 0 | CH66: 0 | CI66: 0 | CJ66: 0 | CK66: 0 | CL66: 0 | CM66: 0 | CN66: 0 | CO66: 0 | CP66: 0 | CQ66: 0 | CR66: 0 | CS66: 0 | CT66: 0 | CU66: 0 | CV66: 0
D67: Perenial Sales | E67: Commisson | F67: Labor | N67: =SUMIF($O$8:$AV$8,">="&'CURRENT FORECAST START DATE'!$C$4,'Weekly Spend'!O67:AV67) -> 0 | AC67: 10468
D68: Joseph Resinger | E68: Commisson | F68: Labor | AI68: 18722.2
D69: Harpia | E69: Contract | F69: Marketing | N69: =SUMIF($O$8:$AV$8,">="&'CURRENT FORECAST START DATE'!$C$4,'Weekly Spend'!O69:AV69) -> 0 | AD69: 6500
A70: SC File (Link) | B70: =_xlfn.SINGLE(_xlfn.XLOOKUP(F70, $F$87:$F$95, $E$87:$E$95)) -> 4 | C70: K13 | D70: JG Group | E70: Contract | F70: Marketing | G70: {=INDEX('SC Cost File'!$A$2:$AB$31,MATCH($C70,'SC Cost File'!$A$2:$A$31,0),MATCH(G$7,'SC Cost File'!$A$2:$AB$2,0))/COUNTIF($G$7:$CV$7,G$7)} -> 0 | H70: {=INDEX('SC Cost File'!$A$2:$AB$31,MATCH($C70,'SC Cost File'!$A$2:$A$31,0),MATCH(H$7,'SC Cost File'!$A$2:$AB$2,0))/COUNTIF($G$7:$CV$7,H$7)} -> 0 | I70: {=INDEX('SC Cost File'!$A$2:$AB$31,MATCH($C70,'SC Cost File'!$A$2:$A$31,0),MATCH(I$7,'SC Cost File'!$A$2:$AB$2,0))/COUNTIF($G$7:$CV$7,I$7)} -> 0 | J70: {=INDEX('SC Cost File'!$A$2:$AB$31,MATCH($C70,'SC Cost File'!$A$2:$A$31,0),MATCH(J$7,'SC Cost File'!$A$2:$AB$2,0))/COUNTIF($G$7:$CV$7,J$7)} -> 0 | K70: {=INDEX('SC Cost File'!$A$2:$AB$31,MATCH($C70,'SC Cost File'!$A$2:$A$31,0),MATCH(K$7,'SC Cost File'!$A$2:$AB$2,0))/COUNTIF($G$7:$CV$7,K$7)} -> 0 | L70: {=INDEX('SC Cost File'!$A$2:$AB$31,MATCH($C70,'SC Cost File'!$A$2:$A$31,0),MATCH(L$7,'SC Cost File'!$A$2:$AB$2,0))/COUNTIF($G$7:$CV$7,L$7)} -> 0 | M70: {=INDEX('SC Cost File'!$A$2:$AB$31,MATCH($C70,'SC Cost File'!$A$2:$A$31,0),MATCH(M$7,'SC Cost File'!$A$2:$AB$2,0))/COUNTIF($G$7:$CV$7,M$7)} -> 0 | N70: =SUMIF($O$8:$AV$8,">="&'CURRENT FORECAST START DATE'!$C$4,'Weekly Spend'!O70:AV70) -> 0 | O70: {=INDEX('SC Cost File'!$A$2:$AB$31,MATCH($C70,'SC Cost File'!$A$2:$A$31,0),MATCH(O$7,'SC Cost File'!$A$2:$AB$2,0))/COUNTIF($G$7:$CV$7,O$7)} -> 0 | P70: {=INDEX('SC Cost File'!$A$2:$AB$31,MATCH($C70,'SC Cost File'!$A$2:$A$31,0),MATCH(P$7,'SC Cost File'!$A$2:$AB$2,0))/COUNTIF($G$7:$CV$7,P$7)} -> 0 | Q70: {=INDEX('SC Cost File'!$A$2:$AB$31,MATCH($C70,'SC Cost File'!$A$2:$A$31,0),MATCH(Q$7,'SC Cost File'!$A$2:$AB$2,0))/COUNTIF($G$7:$CV$7,Q$7)} -> 0 | R70: {=INDEX('SC Cost File'!$A$2:$AB$31,MATCH($C70,'SC Cost File'!$A$2:$A$31,0),MATCH(R$7,'SC Cost File'!$A$2:$AB$2,0))/COUNTIF($G$7:$CV$7,R$7)} -> 0 | S70: {=INDEX('SC Cost File'!$A$2:$AB$31,MATCH($C70,'SC Cost File'!$A$2:$A$31,0),MATCH(S$7,'SC Cost File'!$A$2:$AB$2,0))/COUNTIF($G$7:$CV$7,S$7)} -> 0 | T70: {=INDEX('SC Cost File'!$A$2:$AB$31,MATCH($C70,'SC Cost File'!$A$2:$A$31,0),MATCH(T$7,'SC Cost File'!$A$2:$AB$2,0))/COUNTIF($G$7:$CV$7,T$7)} -> 0 | U70: {=INDEX('SC Cost File'!$A$2:$AB$31,MATCH($C70,'SC Cost File'!$A$2:$A$31,0),MATCH(U$7,'SC Cost File'!$A$2:$AB$2,0))/COUNTIF($G$7:$CV$7,U$7)} -> 0 | V70: {=INDEX('SC Cost File'!$A$2:$AB$31,MATCH($C70,'SC Cost File'!$A$2:$A$31,0),MATCH(V$7,'SC Cost File'!$A$2:$AB$2,0))/COUNTIF($G$7:$CV$7,V$7)} -> 0 | ... AM70: {=INDEX('SC Cost File'!$A$2:$AB$31,MATCH($C70,'SC Cost File'!$A$2:$A$31,0),MATCH(AM$7,'SC Cost File'!$A$2:$AB$2,0))/COUNTIF($G$7:$CV$7,AM$7)} -> 1125 | AW70: {=INDEX('SC Cost File'!$A$2:$AB$31,MATCH($C70,'SC Cost File'!$A$2:$A$31,0),MATCH(AW$7,'SC Cost File'!$A$2:$AB$2,0))/COUNTIF($G$7:$CV$7,AW$7)} -> 2500 | AX70: {=INDEX('SC Cost File'!$A$2:$AB$31,MATCH($C70,'SC Cost File'!$A$2:$A$31,0),MATCH(AX$7,'SC Cost File'!$A$2:$AB$2,0))/COUNTIF($G$7:$CV$7,AX$7)} -> 2500 | AY70: {=INDEX('SC Cost File'!$A$2:$AB$31,MATCH($C70,'SC Cost File'!$A$2:$A$31,0),MATCH(AY$7,'SC Cost File'!$A$2:$AB$2,0))/COUNTIF($G$7:$CV$7,AY$7)} -> 2500 | AZ70: {=INDEX('SC Cost File'!$A$2:$AB$31,MATCH($C70,'SC Cost File'!$A$2:$A$31,0),MATCH(AZ$7,'SC Cost File'!$A$2:$AB$2,0))/COUNTIF($G$7:$CV$7,AZ$7)} -> 2500 | BA70: {=INDEX('SC Cost File'!$A$2:$AB$31,MATCH($C70,'SC Cost File'!$A$2:$A$31,0),MATCH(BA$7,'SC Cost File'!$A$2:$AB$2,0))/COUNTIF($G$7:$CV$7,BA$7)} -> 2500 | BB70: {=INDEX('SC Cost File'!$A$2:$AB$31,MATCH($C70,'SC Cost File'!$A$2:$A$31,0),MATCH(BB$7,'SC Cost File'!$A$2:$AB$2,0))/COUNTIF($G$7:$CV$7,BB$7)} -> 2500 | BC70: {=INDEX('SC Cost File'!$A$2:$AB$31,MATCH($C70,'SC Cost File'!$A$2:$A$31,0),MATCH(BC$7,'SC Cost File'!$A$2:$AB$2,0))/COUNTIF($G$7:$CV$7,BC$7)} -> 2500 | BD70: {=INDEX('SC Cost File'!$A$2:$AB$31,MATCH($C70,'SC Cost File'!$A$2:$A$31,0),MATCH(BD$7,'SC Cost File'!$A$2:$AB$2,0))/COUNTIF($G$7:$CV$7,BD$7)} -> 2500 | ... BJ70: {=INDEX('SC Cost File'!$A$2:$AB$31,MATCH($C70,'SC Cost File'!$A$2:$A$31,0),MATCH(BJ$7,'SC Cost File'!$A$2:$AB$2,0))/COUNTIF($G$7:$CV$7,BJ$7)} -> 2500 | BP70: {=INDEX('SC Cost File'!$A$2:$AB$31,MATCH($C70,'SC Cost File'!$A$2:$A$31,0),MATCH(BP$7,'SC Cost File'!$A$2:$AB$2,0))/COUNTIF($G$7:$CV$7,BP$7)} -> 2500 | BQ70: {=INDEX('SC Cost File'!$A$2:$AB$31,MATCH($C70,'SC Cost File'!$A$2:$A$31,0),MATCH(BQ$7,'SC Cost File'!$A$2:$AB$2,0))/COUNTIF($G$7:$CV$7,BQ$7)} -> 2500 | BR70: {=INDEX('SC Cost File'!$A$2:$AB$31,MATCH($C70,'SC Cost File'!$A$2:$A$31,0),MATCH(BR$7,'SC Cost File'!$A$2:$AB$2,0))/COUNTIF($G$7:$CV$7,BR$7)} -> 2000 | BS70: {=INDEX('SC Cost File'!$A$2:$AB$31,MATCH($C70,'SC Cost File'!$A$2:$A$31,0),MATCH(BS$7,'SC Cost File'!$A$2:$AB$2,0))/COUNTIF($G$7:$CV$7,BS$7)} -> 2000 | BT70: {=INDEX('SC Cost File'!$A$2:$AB$31,MATCH($C70,'SC Cost File'!$A$2:$A$31,0),MATCH(BT$7,'SC Cost File'!$A$2:$AB$2,0))/COUNTIF($G$7:$CV$7,BT$7)} -> 2000 | BU70: {=INDEX('SC Cost File'!$A$2:$AB$31,MATCH($C70,'SC Cost File'!$A$2:$A$31,0),MATCH(BU$7,'SC Cost File'!$A$2:$AB$2,0))/COUNTIF($G$7:$CV$7,BU$7)} -> 2000 | BV70: {=INDEX('SC Cost File'!$A$2:$AB$31,MATCH($C70,'SC Cost File'!$A$2:$A$31,0),MATCH(BV$7,'SC Cost File'!$A$2:$AB$2,0))/COUNTIF($G$7:$CV$7,BV$7)} -> 2000 | BW70: {=INDEX('SC Cost File'!$A$2:$AB$31,MATCH($C70,'SC Cost File'!$A$2:$A$31,0),MATCH(BW$7,'SC Cost File'!$A$2:$AB$2,0))/COUNTIF($G$7:$CV$7,BW$7)} -> 2500 | ... CV70: {=INDEX('SC Cost File'!$A$2:$AB$31,MATCH($C70,'SC Cost File'!$A$2:$A$31,0),MATCH(CV$7,'SC Cost File'!$A$2:$AB$2,0))/COUNTIF($G$7:$CV$7,CV$7)} -> 2500
A71: Labor Spend Tab (Link) | B71: =_xlfn.SINGLE(_xlfn.XLOOKUP(F71, $F$87:$F$95, $E$87:$E$95)) -> 3 | C71: K18 | D71: Labor | E71: Payroll | F71: Labor | G71: {=IFERROR(INDEX('Labor Spend'!$A$8:$AX$16,MATCH('Weekly Spend'!#REF!,'Labor Spend'!$A$8:$A$16,0),MATCH('Weekly Spend'!G$8,'Labor Spend'!$A$8:$AX$8,0)),0)} -> 0 | H71: {=IFERROR(INDEX('Labor Spend'!$A$8:$AX$16,MATCH('Weekly Spend'!#REF!,'Labor Spend'!$A$8:$A$16,0),MATCH('Weekly Spend'!H$8,'Labor Spend'!$A$8:$AX$8,0)),0)} -> 0 | I71: {=IFERROR(INDEX('Labor Spend'!$A$8:$AX$16,MATCH('Weekly Spend'!#REF!,'Labor Spend'!$A$8:$A$16,0),MATCH('Weekly Spend'!I$8,'Labor Spend'!$A$8:$AX$8,0)),0)} -> 0 | J71: {=IFERROR(INDEX('Labor Spend'!$A$8:$AX$16,MATCH('Weekly Spend'!#REF!,'Labor Spend'!$A$8:$A$16,0),MATCH('Weekly Spend'!J$8,'Labor Spend'!$A$8:$AX$8,0)),0)} -> 0 | K71: {=IFERROR(INDEX('Labor Spend'!$A$8:$AX$16,MATCH('Weekly Spend'!#REF!,'Labor Spend'!$A$8:$A$16,0),MATCH('Weekly Spend'!K$8,'Labor Spend'!$A$8:$AX$8,0)),0)} -> 0 | L71: {=IFERROR(INDEX('Labor Spend'!$A$8:$AX$16,MATCH('Weekly Spend'!#REF!,'Labor Spend'!$A$8:$A$16,0),MATCH('Weekly Spend'!L$8,'Labor Spend'!$A$8:$AX$8,0)),0)} -> 0 | M71: {=IFERROR(INDEX('Labor Spend'!$A$8:$AX$16,MATCH('Weekly Spend'!#REF!,'Labor Spend'!$A$8:$A$16,0),MATCH('Weekly Spend'!M$8,'Labor Spend'!$A$8:$AX$8,0)),0)} -> 0 | N71: =SUMIF($O$8:$AV$8,">="&'CURRENT FORECAST START DATE'!$C$4,'Weekly Spend'!O71:AV71) -> 357424.44 | O71: {=IFERROR(INDEX('Labor Spend'!$A$8:$AX$16,MATCH('Weekly Spend'!#REF!,'Labor Spend'!$A$8:$A$16,0),MATCH('Weekly Spend'!O$8,'Labor Spend'!$A$8:$AX$8,0)),0)} -> 0 | P71: {=IFERROR(INDEX('Labor Spend'!$A$8:$AX$16,MATCH('Weekly Spend'!#REF!,'Labor Spend'!$A$8:$A$16,0),MATCH('Weekly Spend'!P$8,'Labor Spend'!$A$8:$AX$8,0)),0)} -> 0 | Q71: {=IFERROR(INDEX('Labor Spend'!$A$8:$AX$16,MATCH('Weekly Spend'!#REF!,'Labor Spend'!$A$8:$A$16,0),MATCH('Weekly Spend'!Q$8,'Labor Spend'!$A$8:$AX$8,0)),0)} -> 0 | R71: {=IFERROR(INDEX('Labor Spend'!$A$8:$AX$16,MATCH('Weekly Spend'!#REF!,'Labor Spend'!$A$8:$A$16,0),MATCH('Weekly Spend'!R$8,'Labor Spend'!$A$8:$AX$8,0)),0)} -> 0 | S71: 53500 | T71: =_xlfn.XLOOKUP(T8,'Labor Spend'!8:8,'Labor Spend'!29:29,0) -> 0 | U71: 63500 | V71: =_xlfn.XLOOKUP(V8,'Labor Spend'!8:8,'Labor Spend'!29:29,0) -> 0 | W71: =_xlfn.XLOOKUP(W8,'Labor Spend'!8:8,'Labor Spend'!29:29,0) -> 65500 | X71: =_xlfn.XLOOKUP(X8,'Labor Spend'!8:8,'Labor Spend'!29:29,0) -> 0 | Y71: =_xlfn.XLOOKUP(Y8,'Labor Spend'!8:8,'Labor Spend'!29:29,0) -> 67500 | Z71: =_xlfn.XLOOKUP(Z8,'Labor Spend'!8:8,'Labor Spend'!29:29,0) -> 0 | AA71: =_xlfn.XLOOKUP(AA8,'Labor Spend'!8:8,'Labor Spend'!29:29,0) -> 68477.5 | AB71: =_xlfn.XLOOKUP(AB8,'Labor Spend'!8:8,'Labor Spend'!29:29,0) -> 0 | AC71: =_xlfn.XLOOKUP(AC8,'Labor Spend'!8:8,'Labor Spend'!29:29,0) -> 72390 | ... CV71: =_xlfn.XLOOKUP(CV8,'Labor Spend'!8:8,'Labor Spend'!29:29,0) -> 100313.69
D72: Benefits | E72: Payroll | F72: Labor | N72: =SUMIF($O$8:$AV$8,">="&'CURRENT FORECAST START DATE'!$C$4,'Weekly Spend'!O72:AV72) -> 18000 | O72: 0 | P72: 0 | Q72: 0 | R72: 0 | S72: 0 | T72: 0 | U72: 1524.76 | V72: 0 | W72: 0 | X72: 0 | Y72: =1524.76+1000+6000 -> 8524.76 | Z72: 0 | AA72: 0 | AB72: 0 | AC72: 0 | AD72: =1524.76+6000 -> 7524.76 | AF72: 0 | AG72: 0 | AH72: 0 | AI72: 4500 | AJ72: 3000 | AK72: 0 | AL72: 3000 | AM72: 0 | AN72: 3000 | AO72: 0 | AP72: 3000 | AQ72: =AI72 -> 4500 | AR72: 3000 | AS72: 0 | AT72: 3000 | AU72: 0 | AV72: =AQ72 -> 4500 | AW72: 0 | AX72: 3000 | AY72: 0 | AZ72: =AX72 -> 3000 | BA72: 0 | BB72: =AZ72 -> 3000 | BC72: 0 | BD72: =BB72 -> 3000 | BE72: 0 | BF72: =BD72 -> 3000 | BG72: 0 | BH72: =BF72 -> 3000 | BI72: 0 | BJ72: =BH72 -> 3000 | BK72: 0 | BL72: =BJ72 -> 3000 | BM72: 0 | BN72: =BL72 -> 3000 | BO72: 0 | BP72: =BN72 -> 3000 | BQ72: 0 | BR72: =BP72 -> 3000 | BS72: 0 | BT72: =BR72 -> 3000 | BU72: 0 | BV72: =BT72 -> 3000 | BW72: 0 | BX72: =BV72 -> 3000 | BY72: 0 | BZ72: 0 | CA72: 0 | CB72: 0 | CC72: 0 | CD72: 0 | CE72: 0 | CF72: 0 | CG72: 0 | CH72: 0 | CI72: 0 | CJ72: 0 | CK72: 0 | CL72: 0 | CM72: 0 | CN72: 0 | CO72: 0 | CP72: 0 | CQ72: 0 | CR72: 0 | CS72: 0 | CT72: 0 | CU72: 0 | CV72: 0
A73: SC File (Link) | B73: =_xlfn.SINGLE(_xlfn.XLOOKUP(F73, $F$87:$F$95, $E$87:$E$95)) -> 2 | C73: K22 | D73: CableLabs | E73: Project | F73: OpEx | G73: {=INDEX('SC Cost File'!$A$2:$AB$31,MATCH($C73,'SC Cost File'!$A$2:$A$31,0),MATCH(G$7,'SC Cost File'!$A$2:$AB$2,0))/COUNTIF($G$7:$CV$7,G$7)} -> 0 | H73: {=INDEX('SC Cost File'!$A$2:$AB$31,MATCH($C73,'SC Cost File'!$A$2:$A$31,0),MATCH(H$7,'SC Cost File'!$A$2:$AB$2,0))/COUNTIF($G$7:$CV$7,H$7)} -> 0 | I73: {=INDEX('SC Cost File'!$A$2:$AB$31,MATCH($C73,'SC Cost File'!$A$2:$A$31,0),MATCH(I$7,'SC Cost File'!$A$2:$AB$2,0))/COUNTIF($G$7:$CV$7,I$7)} -> 0 | J73: {=INDEX('SC Cost File'!$A$2:$AB$31,MATCH($C73,'SC Cost File'!$A$2:$A$31,0),MATCH(J$7,'SC Cost File'!$A$2:$AB$2,0))/COUNTIF($G$7:$CV$7,J$7)} -> 0 | K73: {=INDEX('SC Cost File'!$A$2:$AB$31,MATCH($C73,'SC Cost File'!$A$2:$A$31,0),MATCH(K$7,'SC Cost File'!$A$2:$AB$2,0))/COUNTIF($G$7:$CV$7,K$7)} -> 0 | L73: {=INDEX('SC Cost File'!$A$2:$AB$31,MATCH($C73,'SC Cost File'!$A$2:$A$31,0),MATCH(L$7,'SC Cost File'!$A$2:$AB$2,0))/COUNTIF($G$7:$CV$7,L$7)} -> 0 | M73: {=INDEX('SC Cost File'!$A$2:$AB$31,MATCH($C73,'SC Cost File'!$A$2:$A$31,0),MATCH(M$7,'SC Cost File'!$A$2:$AB$2,0))/COUNTIF($G$7:$CV$7,M$7)} -> 4301 | N73: =SUMIF($O$8:$AV$8,">="&'CURRENT FORECAST START DATE'!$C$4,'Weekly Spend'!O73:AV73) -> 0 | O73: {=INDEX('SC Cost File'!$A$2:$AB$31,MATCH($C73,'SC Cost File'!$A$2:$A$31,0),MATCH(O$7,'SC Cost File'!$A$2:$AB$2,0))/COUNTIF($G$7:$CV$7,O$7)} -> 4301 | P73: {=INDEX('SC Cost File'!$A$2:$AB$31,MATCH($C73,'SC Cost File'!$A$2:$A$31,0),MATCH(P$7,'SC Cost File'!$A$2:$AB$2,0))/COUNTIF($G$7:$CV$7,P$7)} -> 4301 | Q73: {=INDEX('SC Cost File'!$A$2:$AB$31,MATCH($C73,'SC Cost File'!$A$2:$A$31,0),MATCH(Q$7,'SC Cost File'!$A$2:$AB$2,0))/COUNTIF($G$7:$CV$7,Q$7)} -> 4301 | R73: {=INDEX('SC Cost File'!$A$2:$AB$31,MATCH($C73,'SC Cost File'!$A$2:$A$31,0),MATCH(R$7,'SC Cost File'!$A$2:$AB$2,0))/COUNTIF($G$7:$CV$7,R$7)} -> 0 | S73: {=INDEX('SC Cost File'!$A$2:$AB$31,MATCH($C73,'SC Cost File'!$A$2:$A$31,0),MATCH(S$7,'SC Cost File'!$A$2:$AB$2,0))/COUNTIF($G$7:$CV$7,S$7)} -> 0 | T73: {=INDEX('SC Cost File'!$A$2:$AB$31,MATCH($C73,'SC Cost File'!$A$2:$A$31,0),MATCH(T$7,'SC Cost File'!$A$2:$AB$2,0))/COUNTIF($G$7:$CV$7,T$7)} -> 0 | U73: {=INDEX('SC Cost File'!$A$2:$AB$31,MATCH($C73,'SC Cost File'!$A$2:$A$31,0),MATCH(U$7,'SC Cost File'!$A$2:$AB$2,0))/COUNTIF($G$7:$CV$7,U$7)} -> 0 | V73: {=INDEX('SC Cost File'!$A$2:$AB$31,MATCH($C73,'SC Cost File'!$A$2:$A$31,0),MATCH(V$7,'SC Cost File'!$A$2:$AB$2,0))/COUNTIF($G$7:$CV$7,V$7)} -> 0 | W73: 0 | X73: 0 | Y73: 0 | Z73: 189000 | AA73: {=INDEX('SC Cost File'!$A$2:$AB$31,MATCH($C73,'SC Cost File'!$A$2:$A$31,0),MATCH(AA$7,'SC Cost File'!$A$2:$AB$2,0))/COUNTIF($G$7:$CV$7,AA$7)} -> 0 | AB73: {=INDEX('SC Cost File'!$A$2:$AB$31,MATCH($C73,'SC Cost File'!$A$2:$A$31,0),MATCH(AB$7,'SC Cost File'!$A$2:$AB$2,0))/COUNTIF($G$7:$CV$7,AB$7)} -> 0 | AC73: {=INDEX('SC Cost File'!$A$2:$AB$31,MATCH($C73,'SC Cost File'!$A$2:$A$31,0),MATCH(AC$7,'SC Cost File'!$A$2:$AB$2,0))/COUNTIF($G$7:$CV$7,AC$7)} -> 0 | AD73: {=INDEX('SC Cost File'!$A$2:$AB$31,MATCH($C73,'SC Cost File'!$A$2:$A$31,0),MATCH(AD$7,'SC Cost File'!$A$2:$AB$2,0))/COUNTIF($G$7:$CV$7,AD$7)} -> 0 | AE73: {=INDEX('SC Cost File'!$A$2:$AB$31,MATCH($C73,'SC Cost File'!$A$2:$A$31,0),MATCH(AE$7,'SC Cost File'!$A$2:$AB$2,0))/COUNTIF($G$7:$CV$7,AE$7)} -> 0 | AF73: {=INDEX('SC Cost File'!$A$2:$AB$31,MATCH($C73,'SC Cost File'!$A$2:$A$31,0),MATCH(AF$7,'SC Cost File'!$A$2:$AB$2,0))/COUNTIF($G$7:$CV$7,AF$7)} -> 0 | AG73: {=INDEX('SC Cost File'!$A$2:$AB$31,MATCH($C73,'SC Cost File'!$A$2:$A$31,0),MATCH(AG$7,'SC Cost File'!$A$2:$AB$2,0))/COUNTIF($G$7:$CV$7,AG$7)} -> 0 | AH73: {=INDEX('SC Cost File'!$A$2:$AB$31,MATCH($C73,'SC Cost File'!$A$2:$A$31,0),MATCH(AH$7,'SC Cost File'!$A$2:$AB$2,0))/COUNTIF($G$7:$CV$7,AH$7)} -> 0 | ... CV73: {=INDEX('SC Cost File'!$A$2:$AB$31,MATCH($C73,'SC Cost File'!$A$2:$A$31,0),MATCH(CV$7,'SC Cost File'!$A$2:$AB$2,0))/COUNTIF($G$7:$CV$7,CV$7)} -> 0
D74: Actuarial Services | E74: OBS | F74: OpEx | N74: =SUMIF($O$8:$AV$8,">="&'CURRENT FORECAST START DATE'!$C$4,'Weekly Spend'!O74:AV74) -> 0 | Y74: 0 | AA74: 2500
A75: Manual Invoice | B75: =_xlfn.SINGLE(_xlfn.XLOOKUP(F75, $F$87:$F$95, $E$87:$E$95)) -> 7 | C75: K45 | D75: Tide Rock | E75: Interest | F75: Tide Rock Interest Payments | H75: 4499.03 | N75: =SUMIF($O$8:$AV$8,">="&'CURRENT FORECAST START DATE'!$C$4,'Weekly Spend'!O75:AV75) -> 30000 | O75: 0 | P75: 0 | Q75: 0 | R75: 0 | S75: 0 | T75: 0 | U75: 0 | V75: =1928.2 -> 1928.2 | W75: 0 | X75: 0 | Y75: 0 | Z75: 6000 | AA75: 0 | AB75: 0 | AC75: 0 | AE75: 13000 | AF75: 0 | AG75: 0 | AH75: =AD75 -> 0 | AI75: =AE75 -> 13000 | AJ75: 0 | AK75: 0 | AL75: 0 | AM75: 14000 | AN75: 0 | AO75: 0 | AP75: =AL75 -> 0 | AQ75: 15000 | AR75: 0 | AS75: 0 | AT75: =AP75 -> 0 | AV75: =AQ75 -> 15000 | AW75: 0 | AX75: =AT75 -> 0 | AY75: 0 | AZ75: =AV75 -> 15000 | BA75: 0 | BB75: =AX75 -> 0 | BC75: 0 | BE75: =AZ75 -> 15000 | BF75: 0 | BG75: 0 | BH75: 0 | BI75: 13333 | BJ75: 0 | BK75: 0 | BL75: 0 | BM75: 13333 | BN75: 0 | BO75: 0 | BP75: 0 | BQ75: 0 | BR75: 0 | BS75: 0 | BT75: 0 | BU75: 0 | BV75: 0 | BW75: 0 | BX75: 0 | BY75: 0 | BZ75: 0 | CA75: 0 | CB75: 0 | CC75: 0 | CD75: 0 | CE75: 0 | CF75: 0 | CG75: 0 | CH75: 0 | CI75: 0 | CJ75: 0 | CK75: 0 | CL75: 0 | CM75: 0 | CN75: 0 | CO75: 0 | CP75: 0 | CQ75: 0 | CR75: 0 | CS75: 0 | CT75: 0 | CU75: 0 | CV75: 0
D76: Vietnam Project Team | E76: Contract | F76: OpEx | N76: =SUMIF($O$8:$AV$8,">="&'CURRENT FORECAST START DATE'!$C$4,'Weekly Spend'!O76:AV76) -> 0 | Y76: 1350 | Z76: 2500 | AB76: 4050 | AF76: 3000 | AG76: 4000 | AH76: 3500 | AI76: 3500 | AJ76: 5625
D77: Gryphon (AWS Update/ Dev Ops) | E77: Services | F77: NRE/Dev Ops | N77: =SUMIF($O$8:$AV$8,">="&'CURRENT FORECAST START DATE'!$C$4,'Weekly Spend'!O77:AV77) -> 0 | AE77: 7384 | AF77: 7384.62 | AK77: =7385+3692.31 -> 11077.31 | AN77: 7384.62 | BG77: 40000 | BK77: 35000 | BV77: 35000 | BX77: 35000 | BY77: 35000 | CA77: 35000 | CB77: 0 | CC77: 35000 | CE77: 35000 | CF77: 0 | CG77: 35000 | CI77: 35000 | CJ77: 0 | CL77: 35000 | CN77: 35000 | CO77: 0 | CQ77: 0 | CR77: 35000 | CS77: 0 | CT77: 35000 | CU77: 0
D78: Trackstreet | E78: Services | F78: OpEx | AQ78: 7400
B79: =_xlfn.SINGLE(_xlfn.XLOOKUP(F79, $F$87:$F$95, $E$87:$E$95)) -> 2 | D79: EMG | E79: Warehouse | F79: OpEx | N79: =SUMIF($O$8:$AV$8,">="&'CURRENT FORECAST START DATE'!$C$4,'Weekly Spend'!O79:AV79) -> 5162 | O79: 0 | P79: 0 | Q79: 0 | R79: 0 | S79: 0 | T79: 0 | U79: 0 | V79: 0 | W79: 0 | X79: 0 | Y79: 6000 | Z79: 3300 | AA79: 0 | AB79: 0 | AC79: 0 | AD79: 0 | AE79: 3744.75 | AF79: 2739.61 | AG79: 0 | AH79: 0 | AJ79: 8000 | AK79: 0 | AL79: 0 | AN79: 0 | AO79: 0 | AP79: 5162 | AR79: 0 | AS79: 0 | AT79: 0 | AU79: 0 | AV79: 0 | AW79: 0 | AX79: 0 | AY79: 0 | AZ79: 0 | BA79: 0 | BB79: 0 | BC79: 0 | BD79: 0 | BE79: 0 | BF79: 0 | BG79: 0 | BH79: 0 | BI79: 0 | BJ79: 0 | BK79: 0 | BL79: 0 | BM79: 0 | BN79: 0 | BO79: 0 | BP79: 0 | BQ79: 0 | BR79: 0 | BS79: 0 | BT79: 0 | BU79: 0 | BV79: 0 | BW79: 0 | BX79: 0 | BY79: 0 | BZ79: 0 | CA79: 0 | CB79: 0 | CC79: 0 | CD79: 0 | CE79: 0 | CF79: 0 | CG79: 0 | CH79: 0 | CI79: 0 | CJ79: 0 | CK79: 0 | CL79: 0 | CM79: 0 | CN79: 0 | CO79: 0 | CP79: 0 | CQ79: 0 | CR79: 0 | CS79: 0 | CT79: 0 | CU79: 0 | CV79: 0
B80: =_xlfn.SINGLE(_xlfn.XLOOKUP(F80, $F$87:$F$95, $E$87:$E$95)) -> 0
G81: =SUM(G10:G80) -> 158975.5 | H81: =SUM(H10:H80) -> 551706.53 | I81: =SUM(I10:I80) -> 201564.57 | J81: =SUM(J10:J80) -> 413064.01 | K81: =SUM(K10:K80) -> 8087.5 | L81: =SUM(L10:L80) -> 46087.5 | M81: =SUM(M10:M80) -> 152541.45 | N81: =SUM(N10:N80) -> 2066144.7 | ... CH81: =SUM(CH10:CH80) -> 107719.94
N83: Gryphon | AM83: =SUM(AM35:AM38)+AM77 -> 0 | AN83: =SUM(AN35:AN38)+AN77 -> 57692.31 | AO83: =SUM(AO35:AO38)+AO77 -> 57692.31 | AP83: =SUM(AP35:AP38)+AP77 -> 0 | AQ83: =SUM(AQ35:AQ38)+AQ77 -> 0 | AR83: =SUM(AR35:AR38)+AR77 -> 0 | AS83: =SUM(AS35:AS38)+AS77 -> 55000 | AT83: =SUM(AT35:AT38)+AT77 -> 0 | ... BA83: =SUM(BA35:BA38)+BA77 -> 0
G86: =G8 -> 45740 | H86: =H8 -> 45747 | I86: =I8 -> 45754 | J86: =J8 -> 45761 | K86: =K8 -> 45768 | L86: =L8 -> 45775 | M86: =M8 -> 45782 | N86: YTG | O86: =O8 -> 45789 | P86: =P8 -> 45796 | Q86: =Q8 -> 45803 | R86: =R8 -> 45810 | S86: =S8 -> 45817 | T86: =T8 -> 45824 | U86: =U8 -> 45831 | V86: =V8 -> 45838 | ... CV86: =CV8 -> 46384
E87: 1 | F87: R&D | G87: =SUMIF($F$10:$F$81,$F87,G$10:G$81) -> 0 | H87: =SUMIF($F$10:$F$81,$F87,H$10:H$81) -> 0 | I87: =SUMIF($F$10:$F$81,$F87,I$10:I$81) -> 0 | J87: =SUMIF($F$10:$F$81,$F87,J$10:J$81) -> 0 | K87: =SUMIF($F$10:$F$81,$F87,K$10:K$81) -> 0 | L87: =SUMIF($F$10:$F$81,$F87,L$10:L$81) -> 0 | M87: =SUMIF($F$10:$F$81,$F87,M$10:M$81) -> 0 | N87: =SUMIF($F$10:$F$81,$F87,N$10:N$81) -> 0 | ... CV87: =SUMIF($F$10:$F$81,$F87,CV$10:CV$81) -> 0
E88: 2 | F88: OpEx | G88: =SUMIF($F$10:$F$81,$F88,G$10:G$81) -> 1737.5 | H88: =SUMIF($F$10:$F$81,$F88,H$10:H$81) -> 1737.5 | I88: =SUMIF($F$10:$F$81,$F88,I$10:I$81) -> 25540.45 | J88: =SUMIF($F$10:$F$81,$F88,J$10:J$81) -> 587.5 | K88: =SUMIF($F$10:$F$81,$F88,K$10:K$81) -> 587.5 | L88: =SUMIF($F$10:$F$81,$F88,L$10:L$81) -> 587.5 | M88: =SUMIF($F$10:$F$81,$F88,M$10:M$81) -> 119041.45 | N88: =SUMIF($F$10:$F$81,$F88,N$10:N$81) -> 190653.3 | ... CV88: =SUMIF($F$10:$F$81,$F88,CV$10:CV$81) -> 26906.25
E89: 3 | F89: Labor | G89: =SUMIF($F$10:$F$81,$F89,G$10:G$81) -> 0 | H89: =SUMIF($F$10:$F$81,$F89,H$10:H$81) -> 0 | I89: =SUMIF($F$10:$F$81,$F89,I$10:I$81) -> 0 | J89: =SUMIF($F$10:$F$81,$F89,J$10:J$81) -> 0 | K89: =SUMIF($F$10:$F$81,$F89,K$10:K$81) -> 0 | L89: =SUMIF($F$10:$F$81,$F89,L$10:L$81) -> 0 | M89: =SUMIF($F$10:$F$81,$F89,M$10:M$81) -> 0 | N89: =SUMIF($F$10:$F$81,$F89,N$10:N$81) -> 375424.44 | ... CV89: =SUMIF($F$10:$F$81,$F89,CV$10:CV$81) -> 100313.69
E90: 4 | F90: Marketing | G90: =SUMIF($F$10:$F$81,$F90,G$10:G$81) -> 0 | H90: =SUMIF($F$10:$F$81,$F90,H$10:H$81) -> 0 | I90: =SUMIF($F$10:$F$81,$F90,I$10:I$81) -> 8169.12 | J90: =SUMIF($F$10:$F$81,$F90,J$10:J$81) -> 0 | K90: =SUMIF($F$10:$F$81,$F90,K$10:K$81) -> 0 | L90: =SUMIF($F$10:$F$81,$F90,L$10:L$81) -> 0 | M90: =SUMIF($F$10:$F$81,$F90,M$10:M$81) -> 0 | N90: =SUMIF($F$10:$F$81,$F90,N$10:N$81) -> 69450 | ... CV90: =SUMIF($F$10:$F$81,$F90,CV$10:CV$81) -> 2500
E91: 5 | F91: Cert | G91: =SUMIF($F$10:$F$81,$F91,G$10:G$81) -> 0 | H91: =SUMIF($F$10:$F$81,$F91,H$10:H$81) -> 0 | I91: =SUMIF($F$10:$F$81,$F91,I$10:I$81) -> 0 | J91: =SUMIF($F$10:$F$81,$F91,J$10:J$81) -> 0 | K91: =SUMIF($F$10:$F$81,$F91,K$10:K$81) -> 0 | L91: =SUMIF($F$10:$F$81,$F91,L$10:L$81) -> 0 | M91: =SUMIF($F$10:$F$81,$F91,M$10:M$81) -> 0 | N91: =SUMIF($F$10:$F$81,$F91,N$10:N$81) -> 0 | ... CV91: =SUMIF($F$10:$F$81,$F91,CV$10:CV$81) -> 0
E92: 6 | F92: Inventory | G92: =SUMIF($F$10:$F$81,$F92,G$10:G$81) -> 71119 | H92: =SUMIF($F$10:$F$81,$F92,H$10:H$81) -> 530470 | I92: =SUMIF($F$10:$F$81,$F92,I$10:I$81) -> 0 | J92: =SUMIF($F$10:$F$81,$F92,J$10:J$81) -> 404976.51 | K92: =SUMIF($F$10:$F$81,$F92,K$10:K$81) -> 0 | L92: =SUMIF($F$10:$F$81,$F92,L$10:L$81) -> 5000 | M92: =SUMIF($F$10:$F$81,$F92,M$10:M$81) -> 26000 | N92: =SUMIF($F$10:$F$81,$F92,N$10:N$81) -> 871728 | ... CV92: =SUMIF($F$10:$F$81,$F92,CV$10:CV$81) -> 0 | CW92: =SUM(V92:CV92) -> 5381236
E93: 7 | F93: Tide Rock Interest Payments | G93: =SUMIF($F$10:$F$81,$F93,G$10:G$81) -> 0 | H93: =SUMIF($F$10:$F$81,$F93,H$10:H$81) -> 4499.03 | I93: =SUMIF($F$10:$F$81,$F93,I$10:I$81) -> 0 | J93: =SUMIF($F$10:$F$81,$F93,J$10:J$81) -> 0 | K93: =SUMIF($F$10:$F$81,$F93,K$10:K$81) -> 0 | L93: =SUMIF($F$10:$F$81,$F93,L$10:L$81) -> 0 | M93: =SUMIF($F$10:$F$81,$F93,M$10:M$81) -> 0 | N93: =SUMIF($F$10:$F$81,$F93,N$10:N$81) -> 30000 | ... CV93: =SUMIF($F$10:$F$81,$F93,CV$10:CV$81) -> 0 | CW93: 2988225
E94: 8 | F94: NRE | G94: =SUMIF($F$10:$F$81,$F94,G$10:G$81) -> 86119 | H94: =SUMIF($F$10:$F$81,$F94,H$10:H$81) -> 15000 | I94: =SUMIF($F$10:$F$81,$F94,I$10:I$81) -> 167855 | J94: =SUMIF($F$10:$F$81,$F94,J$10:J$81) -> 7500 | K94: =SUMIF($F$10:$F$81,$F94,K$10:K$81) -> 7500 | L94: =SUMIF($F$10:$F$81,$F94,L$10:L$81) -> 40500 | M94: =SUMIF($F$10:$F$81,$F94,M$10:M$81) -> 7500 | N94: =SUMIF($F$10:$F$81,$F94,N$10:N$81) -> 528888.97 | ... CV94: =SUMIF($F$10:$F$81,$F94,CV$10:CV$81) -> 0 | CW94: =CW93-CW92 -> -2393011
N95: =SUMIF($O$8:$AV$8,">="&'CURRENT FORECAST START DATE'!$C$4,'Weekly Spend'!O95:AV95) -> 0
F96: Total Spend | G96: =SUM(G87:G94) -> 158975.5 | H96: =SUM(H87:H94) -> 551706.53 | I96: =SUM(I87:I94) -> 201564.57 | J96: =SUM(J87:J94) -> 413064.01 | K96: =SUM(K87:K94) -> 8087.5 | L96: =SUM(L87:L94) -> 46087.5 | M96: =SUM(M87:M94) -> 152541.45 | N96: =SUM(N87:N94) -> 2066144.7 | ... CV96: =SUM(CV87:CV94) -> 129719.94
F97: Total Excl Inventory | G97: =+G96-G92 -> 87856.5 | H97: =+H96-H92 -> 21236.53 | I97: =+I96-I92 -> 201564.57 | J97: =+J96-J92 -> 8087.5 | K97: =+K96-K92 -> 8087.5 | L97: =+L96-L92 -> 41087.5 | M97: =+M96-M92 -> 126541.45 | N97: =+N96-N92 -> 1194416.7 | ... CV97: =+CV96-CV92 -> 129719.94
F98: YTD ties | N98: 2456295
F99: Total Steve Inv | N99: 2988225
G100: =+G81-G96 -> 0 | H100: =+H81-H96 -> 0 | I100: =+I81-I96 -> 0 | J100: =+J81-J96 -> 0 | K100: =+K81-K96 -> 0 | L100: =+L81-L96 -> 0 | M100: =+M81-M96 -> 0 | N100: =+N81-N96 -> 0 | ... CL100: =+CL81-CL96 -> -107438.69
K102: 64K turn right away
L108: Funding Sources
G109: YTD Spend to 11/03 | H109: LT Spend 11/10 to 6/26 | I109: Total Spend | K109: Internal Cash YTD 9/30 | L109: =SUM([1]IS!$T$5:$Y$5) -> 1926650.1
F110: R&D | G110: =SUM(G87:AM87) -> 0 | H110: =SUM(AN87:BI87) -> 0 | I110: =H110+G110 -> 0 | K110: Internal Cash Sales (Bal of Year) | L110: ='[1]P&L Budget Compare'!$X$4 -> 701606.67
F111: OpEx | G111: =SUM(G88:AN88) -> 1213552.5 | H111: =SUM(AO88:BT88) -> 759507.3 | I111: =H111+G111 -> 1973059.8 | K111: Internal Cash 1 2026 to 3/30/26 | L111: =SUM('CURRENT WEEK CASHFLOW FORECAST'!M10:Z10) -> 1900000 | O111: 5000000
...

Sheet CURRENT WEEK CASHFLOW FORECAST
D1: 1 | E1: =D1+1 -> 2 | F1: =E1+1 -> 3 | G1: =F1+1 -> 4 | H1: 5 | I1: =H1+1 -> 6 | J1: =I1+1 -> 7 | K1: =J1+1 -> 8 | L1: =K1+1 -> 9 | M1: =L1+1 -> 10 | N1: =M1+1 -> 11 | O1: =N1+1 -> 12 | P1: =O1+1 -> 13 | Q1: Post 13 Week>> | R1: =+P1+1 -> 14 | S1: =+R1+1 -> 15 | T1: =+S1+1 -> 16 | U1: =+T1+1 -> 17 | V1: =+U1+1 -> 18 | W1: =+V1+1 -> 19 | X1: =+W1+1 -> 20 | Y1: =+X1+1 -> 21 | Z1: =+Y1+1 -> 22 | ... AN1: =+AM1+1 -> 36
D2: ="Week"&" "&D1 -> Week 1 | E2: ="Week"&" "&E1 -> Week 2 | F2: ="Week"&" "&F1 -> Week 3 | G2: ="Week"&" "&G1 -> Week 4 | H2: ="Week"&" "&H1 -> Week 5 | I2: ="Week"&" "&I1 -> Week 6 | J2: ="Week"&" "&J1 -> Week 7 | K2: ="Week"&" "&K1 -> Week 8 | ... P2: ="Week"&" "&P1 -> Week 13 | R2: ="Week"&" "&S1 -> Week 15 | S2: ="Week"&" "&T1 -> Week 16 | T2: ="Week"&" "&U1 -> Week 17 | U2: ="Week"&" "&V1 -> Week 18 | V2: ="Week"&" "&W1 -> Week 19 | W2: ="Week"&" "&X1 -> Week 20 | X2: ="Week"&" "&Y1 -> Week 21 | Y2: ="Week"&" "&Z1 -> Week 22 | ... AN2: ="Week"&" "&AO1 -> Week
C3: Monday of week | D3: ='CURRENT FORECAST START DATE'!C4 -> 45971 | E3: =D3+7 -> 45978 | F3: =E3+7 -> 45985 | G3: =F3+7 -> 45992 | H3: =G3+7 -> 45999 | I3: =H3+7 -> 46006 | J3: =I3+7 -> 46013 | K3: =J3+7 -> 46020 | L3: =K3+7 -> 46027 | ... P3: =O3+7 -> 46055 | R3: =P3+7 -> 46062 | S3: =R3+7 -> 46069 | T3: =S3+7 -> 46076 | U3: =T3+7 -> 46083 | V3: =U3+7 -> 46090 | W3: =V3+7 -> 46097 | X3: =W3+7 -> 46104 | Y3: =X3+7 -> 46111 | Z3: =Y3+7 -> 46118 | ... AN3: =AM3+7 -> 46216
B4: OPERATING CASH INFLOWS
B5: Operating Cash Receipts
B6: Customer Cash Receipts from A/R | C6: AR Aging | D6: 9000 | F6: 32000 | H6: 80000 | J6: 96000 | L6: 140000 | N6: 160000 | P6: 180000 | S6: 200000 | U6: 220000 | W6: 240000 | Y6: 260000 | AA6: 260000 | AC6: 260000 | AE6: 286957 | AG6: 286957 | AH6: =AF6 -> 0 | AI6: 286957 | AJ6: =AH6 -> 0 | AK6: =AI6 -> 286957 | AL6: =AJ6 -> 0 | AM6: =AK6 -> 286957 | AN6: =AL6 -> 0
B7: Customer Forecasted Receipts from Backlog | C7: AR (Backlog) | F7: 0 | G7: 0 | H7: 0 | I7: 0 | J7: 0 | K7: 0 | L7: 0 | M7: 0 | N7: 0 | O7: 0 | P7: 0 | R7: 0 | S7: 0 | T7: 0 | X7: 0 | Y7: 0 | Z7: 0 | AA7: 0 | AB7: 0 | AC7: 0 | AD7: 0 | AE7: 0 | AF7: 0 | AG7: 0 | AH7: 0 | AI7: 0 | AJ7: 0 | AK7: 0 | AL7: 0 | AM7: 0 | AN7: 0
B8: Customer Forecasted Receipts from Sales Forecast | C8: AR (Sales Forecast) | D8: =56952 -> 56952 | E8: 43968 | F8: 5763 | H8: 50000 | I8: 0 | J8: 0 | K8: 30000 | M8: 0 | O8: 0 | P8: 330000 | U8: 130000 | V8: 0 | W8: 0 | X8: 0 | Y8: 0 | Z8: 180000 | AA8: 0 | AB8: 0 | AC8: 0 | AD8: 230000 | AE8: 0 | AF8: 0 | AG8: 0 | AH8: 30000 | AK8: 1200000
B9: Other, non-customer related inflows | C9: Varies | D9: 0 | E9: 0 | F9: 0 | G9: 0 | H9: 0 | I9: 0 | J9: 0
B10: TOTAL INCOMING CASH | D10: =SUM(D6:D9) -> 65952 | E10: =SUM(E6:E9) -> 43968 | F10: =SUM(F6:F9) -> 37763 | G10: =SUM(G6:G9) -> 0 | H10: =SUM(H6:H9) -> 130000 | I10: =SUM(I6:I9) -> 0 | J10: =SUM(J6:J9) -> 96000 | K10: =SUM(K6:K9) -> 30000 | ... P10: =SUM(P6:P9) -> 510000 | R10: =SUM(R6:R9) -> 0 | S10: =SUM(S6:S9) -> 200000 | T10: =SUM(T6:T9) -> 0 | U10: =SUM(U6:U9) -> 350000 | V10: =SUM(V6:V9) -> 0 | W10: =SUM(W6:W9) -> 240000 | X10: =SUM(X6:X9) -> 0 | Y10: =SUM(Y6:Y9) -> 260000 | ... AN10: =SUM(AN6:AN9) -> 0
B12: OPERATING CASH DISBURSEMENTS
B13: Must Pays
B14: Labor | C14: Biweekly Payroll | D14: {=INDEX('Weekly Spend'!$F$86:$CV$94,MATCH($B14,'Weekly Spend'!$F$86:$F$94,0),MATCH(D$3,'Weekly Spend'!$F$86:$CV$86,0))} -> 0 | F14: {=INDEX('Weekly Spend'!$F$86:$CV$94,MATCH($B14,'Weekly Spend'!$F$86:$F$94,0),MATCH(F$3,'Weekly Spend'!$F$86:$CV$86,0))} -> 4500 | G14: {=INDEX('Weekly Spend'!$F$86:$CV$94,MATCH($B14,'Weekly Spend'!$F$86:$F$94,0),MATCH(G$3,'Weekly Spend'!$F$86:$CV$86,0))} -> 98566.692 | H14: {=INDEX('Weekly Spend'!$F$86:$CV$94,MATCH($B14,'Weekly Spend'!$F$86:$F$94,0),MATCH(H$3,'Weekly Spend'!$F$86:$CV$86,0))} -> 0 | I14: {=INDEX('Weekly Spend'!$F$86:$CV$94,MATCH($B14,'Weekly Spend'!$F$86:$F$94,0),MATCH(I$3,'Weekly Spend'!$F$86:$CV$86,0))} -> 93566.692 | J14: {=INDEX('Weekly Spend'!$F$86:$CV$94,MATCH($B14,'Weekly Spend'!$F$86:$F$94,0),MATCH(J$3,'Weekly Spend'!$F$86:$CV$86,0))} -> 0 | K14: {=INDEX('Weekly Spend'!$F$86:$CV$94,MATCH($B14,'Weekly Spend'!$F$86:$F$94,0),MATCH(K$3,'Weekly Spend'!$F$86:$CV$86,0))} -> 92316.692 | L14: {=INDEX('Weekly Spend'!$F$86:$CV$94,MATCH($B14,'Weekly Spend'!$F$86:$F$94,0),MATCH(L$3,'Weekly Spend'!$F$86:$CV$86,0))} -> 0 | M14: {=INDEX('Weekly Spend'!$F$86:$CV$94,MATCH($B14,'Weekly Spend'!$F$86:$F$94,0),MATCH(M$3,'Weekly Spend'!$F$86:$CV$86,0))} -> 90816.692 | ... P14: {=INDEX('Weekly Spend'!$F$86:$CV$94,MATCH($B14,'Weekly Spend'!$F$86:$F$94,0),MATCH(P$3,'Weekly Spend'!$F$86:$CV$86,0))} -> 0 | R14: {=INDEX('Weekly Spend'!$F$86:$CV$94,MATCH($B14,'Weekly Spend'!$F$86:$F$94,0),MATCH(R$3,'Weekly Spend'!$F$86:$CV$86,0))} -> 103716.69 | S14: {=INDEX('Weekly Spend'!$F$86:$CV$94,MATCH($B14,'Weekly Spend'!$F$86:$F$94,0),MATCH(S$3,'Weekly Spend'!$F$86:$CV$86,0))} -> 0 | T14: {=INDEX('Weekly Spend'!$F$86:$CV$94,MATCH($B14,'Weekly Spend'!$F$86:$F$94,0),MATCH(T$3,'Weekly Spend'!$F$86:$CV$86,0))} -> 100813.69 | U14: {=INDEX('Weekly Spend'!$F$86:$CV$94,MATCH($B14,'Weekly Spend'!$F$86:$F$94,0),MATCH(U$3,'Weekly Spend'!$F$86:$CV$86,0))} -> 0 | V14: {=INDEX('Weekly Spend'!$F$86:$CV$94,MATCH($B14,'Weekly Spend'!$F$86:$F$94,0),MATCH(V$3,'Weekly Spend'!$F$86:$CV$86,0))} -> 91813.692 | W14: {=INDEX('Weekly Spend'!$F$86:$CV$94,MATCH($B14,'Weekly Spend'!$F$86:$F$94,0),MATCH(W$3,'Weekly Spend'!$F$86:$CV$86,0))} -> 0 | X14: {=INDEX('Weekly Spend'!$F$86:$CV$94,MATCH($B14,'Weekly Spend'!$F$86:$F$94,0),MATCH(X$3,'Weekly Spend'!$F$86:$CV$86,0))} -> 100813.69 | Y14: {=INDEX('Weekly Spend'!$F$86:$CV$94,MATCH($B14,'Weekly Spend'!$F$86:$F$94,0),MATCH(Y$3,'Weekly Spend'!$F$86:$CV$86,0))} -> 0 | ... AN14: {=INDEX('Weekly Spend'!$F$86:$CV$94,MATCH($B14,'Weekly Spend'!$F$86:$F$94,0),MATCH(AN$3,'Weekly Spend'!$F$86:$CV$86,0))} -> 91716.692
B15: OpEx | C15: Invoices | D15: {=INDEX('Weekly Spend'!$F$86:$CV$94,MATCH($B15,'Weekly Spend'!$F$86:$F$94,0),MATCH(D$3,'Weekly Spend'!$F$86:$CV$86,0))} -> 5505.8 | E15: {=INDEX('Weekly Spend'!$F$86:$CV$94,MATCH($B15,'Weekly Spend'!$F$86:$F$94,0),MATCH(E$3,'Weekly Spend'!$F$86:$CV$86,0))} -> 5287 | F15: {=INDEX('Weekly Spend'!$F$86:$CV$94,MATCH($B15,'Weekly Spend'!$F$86:$F$94,0),MATCH(F$3,'Weekly Spend'!$F$86:$CV$86,0))} -> 20097.5 | G15: {=INDEX('Weekly Spend'!$F$86:$CV$94,MATCH($B15,'Weekly Spend'!$F$86:$F$94,0),MATCH(G$3,'Weekly Spend'!$F$86:$CV$86,0))} -> 67163 | H15: =INDEX('Weekly Spend'!$F$86:$CV$94,MATCH($B15,'Weekly Spend'!$F$86:$F$94,0),MATCH(H$3,'Weekly Spend'!$F$86:$CV$86,0)) -> 4500 | I15: {=INDEX('Weekly Spend'!$F$86:$CV$94,MATCH($B15,'Weekly Spend'!$F$86:$F$94,0),MATCH(I$3,'Weekly Spend'!$F$86:$CV$86,0))} -> 14500 | J15: {=INDEX('Weekly Spend'!$F$86:$CV$94,MATCH($B15,'Weekly Spend'!$F$86:$F$94,0),MATCH(J$3,'Weekly Spend'!$F$86:$CV$86,0))} -> 54500 | K15: {=INDEX('Weekly Spend'!$F$86:$CV$94,MATCH($B15,'Weekly Spend'!$F$86:$F$94,0),MATCH(K$3,'Weekly Spend'!$F$86:$CV$86,0))} -> 26500 | L15: {=INDEX('Weekly Spend'!$F$86:$CV$94,MATCH($B15,'Weekly Spend'!$F$86:$F$94,0),MATCH(L$3,'Weekly Spend'!$F$86:$CV$86,0))} -> 44906.25 | M15: {=INDEX('Weekly Spend'!$F$86:$CV$94,MATCH($B15,'Weekly Spend'!$F$86:$F$94,0),MATCH(M$3,'Weekly Spend'!$F$86:$CV$86,0))} -> 4906.25 | N15: {=INDEX('Weekly Spend'!$F$86:$CV$94,MATCH($B15,'Weekly Spend'!$F$86:$F$94,0),MATCH(N$3,'Weekly Spend'!$F$86:$CV$86,0))} -> 24906.25 | O15: {=INDEX('Weekly Spend'!$F$86:$CV$94,MATCH($B15,'Weekly Spend'!$F$86:$F$94,0),MATCH(O$3,'Weekly Spend'!$F$86:$CV$86,0))} -> 26906.25 | P15: {=INDEX('Weekly Spend'!$F$86:$CV$94,MATCH($B15,'Weekly Spend'!$F$86:$F$94,0),MATCH(P$3,'Weekly Spend'!$F$86:$CV$86,0))} -> 49625 | R15: {=INDEX('Weekly Spend'!$F$86:$CV$94,MATCH($B15,'Weekly Spend'!$F$86:$F$94,0),MATCH(R$3,'Weekly Spend'!$F$86:$CV$86,0))} -> 4625 | S15: {=INDEX('Weekly Spend'!$F$86:$CV$94,MATCH($B15,'Weekly Spend'!$F$86:$F$94,0),MATCH(S$3,'Weekly Spend'!$F$86:$CV$86,0))} -> 4625 | T15: {=INDEX('Weekly Spend'!$F$86:$CV$94,MATCH($B15,'Weekly Spend'!$F$86:$F$94,0),MATCH(T$3,'Weekly Spend'!$F$86:$CV$86,0))} -> 46625 | U15: {=INDEX('Weekly Spend'!$F$86:$CV$94,MATCH($B15,'Weekly Spend'!$F$86:$F$94,0),MATCH(U$3,'Weekly Spend'!$F$86:$CV$86,0))} -> 47940.8 | V15: {=INDEX('Weekly Spend'!$F$86:$CV$94,MATCH($B15,'Weekly Spend'!$F$86:$F$94,0),MATCH(V$3,'Weekly Spend'!$F$86:$CV$86,0))} -> 7940.8 | W15: {=INDEX('Weekly Spend'!$F$86:$CV$94,MATCH($B15,'Weekly Spend'!$F$86:$F$94,0),MATCH(W$3,'Weekly Spend'!$F$86:$CV$86,0))} -> 7940.8 | X15: {=INDEX('Weekly Spend'!$F$86:$CV$94,MATCH($B15,'Weekly Spend'!$F$86:$F$94,0),MATCH(X$3,'Weekly Spend'!$F$86:$CV$86,0))} -> 7940.8 | Y15: {=INDEX('Weekly Spend'!$F$86:$CV$94,MATCH($B15,'Weekly Spend'!$F$86:$F$94,0),MATCH(Y$3,'Weekly Spend'!$F$86:$CV$86,0))} -> 39940.8 | ... AN15: {=INDEX('Weekly Spend'!$F$86:$CV$94,MATCH($B15,'Weekly Spend'!$F$86:$F$94,0),MATCH(AN$3,'Weekly Spend'!$F$86:$CV$86,0))} -> 7245
B16: R&D | C16: Invoices | D16: {=INDEX('Weekly Spend'!$F$86:$CV$94,MATCH($B16,'Weekly Spend'!$F$86:$F$94,0),MATCH(D$3,'Weekly Spend'!$F$86:$CV$86,0))} -> 0 | E16: {=INDEX('Weekly Spend'!$F$86:$CV$94,MATCH($B16,'Weekly Spend'!$F$86:$F$94,0),MATCH(E$3,'Weekly Spend'!$F$86:$CV$86,0))} -> 0 | F16: {=INDEX('Weekly Spend'!$F$86:$CV$94,MATCH($B16,'Weekly Spend'!$F$86:$F$94,0),MATCH(F$3,'Weekly Spend'!$F$86:$CV$86,0))} -> 0 | G16: {=INDEX('Weekly Spend'!$F$86:$CV$94,MATCH($B16,'Weekly Spend'!$F$86:$F$94,0),MATCH(G$3,'Weekly Spend'!$F$86:$CV$86,0))} -> 0 | H16: {=INDEX('Weekly Spend'!$F$86:$CV$94,MATCH($B16,'Weekly Spend'!$F$86:$F$94,0),MATCH(H$3,'Weekly Spend'!$F$86:$CV$86,0))} -> 0 | I16: {=INDEX('Weekly Spend'!$F$86:$CV$94,MATCH($B16,'Weekly Spend'!$F$86:$F$94,0),MATCH(I$3,'Weekly Spend'!$F$86:$CV$86,0))} -> 0 | J16: {=INDEX('Weekly Spend'!$F$86:$CV$94,MATCH($B16,'Weekly Spend'!$F$86:$F$94,0),MATCH(J$3,'Weekly Spend'!$F$86:$CV$86,0))} -> 0 | K16: {=INDEX('Weekly Spend'!$F$86:$CV$94,MATCH($B16,'Weekly Spend'!$F$86:$F$94,0),MATCH(K$3,'Weekly Spend'!$F$86:$CV$86,0))} -> 0 | ... P16: {=INDEX('Weekly Spend'!$F$86:$CV$94,MATCH($B16,'Weekly Spend'!$F$86:$F$94,0),MATCH(P$3,'Weekly Spend'!$F$86:$CV$86,0))} -> 0 | R16: {=INDEX('Weekly Spend'!$F$86:$CV$94,MATCH($B16,'Weekly Spend'!$F$86:$F$94,0),MATCH(R$3,'Weekly Spend'!$F$86:$CV$86,0))} -> 0 | S16: {=INDEX('Weekly Spend'!$F$86:$CV$94,MATCH($B16,'Weekly Spend'!$F$86:$F$94,0),MATCH(S$3,'Weekly Spend'!$F$86:$CV$86,0))} -> 0 | T16: {=INDEX('Weekly Spend'!$F$86:$CV$94,MATCH($B16,'Weekly Spend'!$F$86:$F$94,0),MATCH(T$3,'Weekly Spend'!$F$86:$CV$86,0))} -> 0 | U16: {=INDEX('Weekly Spend'!$F$86:$CV$94,MATCH($B16,'Weekly Spend'!$F$86:$F$94,0),MATCH(U$3,'Weekly Spend'!$F$86:$CV$86,0))} -> 0 | V16: {=INDEX('Weekly Spend'!$F$86:$CV$94,MATCH($B16,'Weekly Spend'!$F$86:$F$94,0),MATCH(V$3,'Weekly Spend'!$F$86:$CV$86,0))} -> 0 | W16: {=INDEX('Weekly Spend'!$F$86:$CV$94,MATCH($B16,'Weekly Spend'!$F$86:$F$94,0),MATCH(W$3,'Weekly Spend'!$F$86:$CV$86,0))} -> 0 | X16: {=INDEX('Weekly Spend'!$F$86:$CV$94,MATCH($B16,'Weekly Spend'!$F$86:$F$94,0),MATCH(X$3,'Weekly Spend'!$F$86:$CV$86,0))} -> 0 | Y16: {=INDEX('Weekly Spend'!$F$86:$CV$94,MATCH($B16,'Weekly Spend'!$F$86:$F$94,0),MATCH(Y$3,'Weekly Spend'!$F$86:$CV$86,0))} -> 0 | ... AN16: {=INDEX('Weekly Spend'!$F$86:$CV$94,MATCH($B16,'Weekly Spend'!$F$86:$F$94,0),MATCH(AN$3,'Weekly Spend'!$F$86:$CV$86,0))} -> 0
B17: Marketing | C17: Invoices | D17: {=INDEX('Weekly Spend'!$F$86:$CV$94,MATCH($B17,'Weekly Spend'!$F$86:$F$94,0),MATCH(D$3,'Weekly Spend'!$F$86:$CV$86,0))} -> 0 | E17: {=INDEX('Weekly Spend'!$F$86:$CV$94,MATCH($B17,'Weekly Spend'!$F$86:$F$94,0),MATCH(E$3,'Weekly Spend'!$F$86:$CV$86,0))} -> 5250 | F17: {=INDEX('Weekly Spend'!$F$86:$CV$94,MATCH($B17,'Weekly Spend'!$F$86:$F$94,0),MATCH(F$3,'Weekly Spend'!$F$86:$CV$86,0))} -> 44000 | G17: {=INDEX('Weekly Spend'!$F$86:$CV$94,MATCH($B17,'Weekly Spend'!$F$86:$F$94,0),MATCH(G$3,'Weekly Spend'!$F$86:$CV$86,0))} -> 0 | H17: {=INDEX('Weekly Spend'!$F$86:$CV$94,MATCH($B17,'Weekly Spend'!$F$86:$F$94,0),MATCH(H$3,'Weekly Spend'!$F$86:$CV$86,0))} -> 0 | I17: {=INDEX('Weekly Spend'!$F$86:$CV$94,MATCH($B17,'Weekly Spend'!$F$86:$F$94,0),MATCH(I$3,'Weekly Spend'!$F$86:$CV$86,0))} -> 0 | J17: {=INDEX('Weekly Spend'!$F$86:$CV$94,MATCH($B17,'Weekly Spend'!$F$86:$F$94,0),MATCH(J$3,'Weekly Spend'!$F$86:$CV$86,0))} -> 10700 | K17: {=INDEX('Weekly Spend'!$F$86:$CV$94,MATCH($B17,'Weekly Spend'!$F$86:$F$94,0),MATCH(K$3,'Weekly Spend'!$F$86:$CV$86,0))} -> 9500 | ... P17: {=INDEX('Weekly Spend'!$F$86:$CV$94,MATCH($B17,'Weekly Spend'!$F$86:$F$94,0),MATCH(P$3,'Weekly Spend'!$F$86:$CV$86,0))} -> 2800 | R17: {=INDEX('Weekly Spend'!$F$86:$CV$94,MATCH($B17,'Weekly Spend'!$F$86:$F$94,0),MATCH(R$3,'Weekly Spend'!$F$86:$CV$86,0))} -> 2500 | S17: {=INDEX('Weekly Spend'!$F$86:$CV$94,MATCH($B17,'Weekly Spend'!$F$86:$F$94,0),MATCH(S$3,'Weekly Spend'!$F$86:$CV$86,0))} -> 2500 | T17: {=INDEX('Weekly Spend'!$F$86:$CV$94,MATCH($B17,'Weekly Spend'!$F$86:$F$94,0),MATCH(T$3,'Weekly Spend'!$F$86:$CV$86,0))} -> 24500 | U17: {=INDEX('Weekly Spend'!$F$86:$CV$94,MATCH($B17,'Weekly Spend'!$F$86:$F$94,0),MATCH(U$3,'Weekly Spend'!$F$86:$CV$86,0))} -> 2000 | V17: {=INDEX('Weekly Spend'!$F$86:$CV$94,MATCH($B17,'Weekly Spend'!$F$86:$F$94,0),MATCH(V$3,'Weekly Spend'!$F$86:$CV$86,0))} -> 2000 | W17: {=INDEX('Weekly Spend'!$F$86:$CV$94,MATCH($B17,'Weekly Spend'!$F$86:$F$94,0),MATCH(W$3,'Weekly Spend'!$F$86:$CV$86,0))} -> 2000 | X17: {=INDEX('Weekly Spend'!$F$86:$CV$94,MATCH($B17,'Weekly Spend'!$F$86:$F$94,0),MATCH(X$3,'Weekly Spend'!$F$86:$CV$86,0))} -> 10700 | Y17: {=INDEX('Weekly Spend'!$F$86:$CV$94,MATCH($B17,'Weekly Spend'!$F$86:$F$94,0),MATCH(Y$3,'Weekly Spend'!$F$86:$CV$86,0))} -> 5000 | ... AN17: {=INDEX('Weekly Spend'!$F$86:$CV$94,MATCH($B17,'Weekly Spend'!$F$86:$F$94,0),MATCH(AN$3,'Weekly Spend'!$F$86:$CV$86,0))} -> 2500
B18: Cert | C18: Ad hoc | D18: =INDEX('Weekly Spend'!$F$86:$CV$94,MATCH($B18,'Weekly Spend'!$F$86:$F$94,0),MATCH(D$3,'Weekly Spend'!$F$86:$CV$86,0)) -> 0 | E18: {=INDEX('Weekly Spend'!$F$86:$CV$94,MATCH($B18,'Weekly Spend'!$F$86:$F$94,0),MATCH(E$3,'Weekly Spend'!$F$86:$CV$86,0))} -> 0 | F18: {=INDEX('Weekly Spend'!$F$86:$CV$94,MATCH($B18,'Weekly Spend'!$F$86:$F$94,0),MATCH(F$3,'Weekly Spend'!$F$86:$CV$86,0))} -> 0 | G18: {=INDEX('Weekly Spend'!$F$86:$CV$94,MATCH($B18,'Weekly Spend'!$F$86:$F$94,0),MATCH(G$3,'Weekly Spend'!$F$86:$CV$86,0))} -> 0 | H18: {=INDEX('Weekly Spend'!$F$86:$CV$94,MATCH($B18,'Weekly Spend'!$F$86:$F$94,0),MATCH(H$3,'Weekly Spend'!$F$86:$CV$86,0))} -> 0 | I18: {=INDEX('Weekly Spend'!$F$86:$CV$94,MATCH($B18,'Weekly Spend'!$F$86:$F$94,0),MATCH(I$3,'Weekly Spend'!$F$86:$CV$86,0))} -> 0 | J18: {=INDEX('Weekly Spend'!$F$86:$CV$94,MATCH($B18,'Weekly Spend'!$F$86:$F$94,0),MATCH(J$3,'Weekly Spend'!$F$86:$CV$86,0))} -> 0 | K18: {=INDEX('Weekly Spend'!$F$86:$CV$94,MATCH($B18,'Weekly Spend'!$F$86:$F$94,0),MATCH(K$3,'Weekly Spend'!$F$86:$CV$86,0))} -> 0 | L18: {=INDEX('Weekly Spend'!$F$86:$CV$94,MATCH($B18,'Weekly Spend'!$F$86:$F$94,0),MATCH(L$3,'Weekly Spend'!$F$86:$CV$86,0))} -> 0 | ... P18: {=INDEX('Weekly Spend'!$F$86:$CV$94,MATCH($B18,'Weekly Spend'!$F$86:$F$94,0),MATCH(P$3,'Weekly Spend'!$F$86:$CV$86,0))} -> 0 | R18: {=INDEX('Weekly Spend'!$F$86:$CV$94,MATCH($B18,'Weekly Spend'!$F$86:$F$94,0),MATCH(R$3,'Weekly Spend'!$F$86:$CV$86,0))} -> 0 | S18: {=INDEX('Weekly Spend'!$F$86:$CV$94,MATCH($B18,'Weekly Spend'!$F$86:$F$94,0),MATCH(S$3,'Weekly Spend'!$F$86:$CV$86,0))} -> 0 | T18: {=INDEX('Weekly Spend'!$F$86:$CV$94,MATCH($B18,'Weekly Spend'!$F$86:$F$94,0),MATCH(T$3,'Weekly Spend'!$F$86:$CV$86,0))} -> 0 | U18: {=INDEX('Weekly Spend'!$F$86:$CV$94,MATCH($B18,'Weekly Spend'!$F$86:$F$94,0),MATCH(U$3,'Weekly Spend'!$F$86:$CV$86,0))} -> 0 | V18: {=INDEX('Weekly Spend'!$F$86:$CV$94,MATCH($B18,'Weekly Spend'!$F$86:$F$94,0),MATCH(V$3,'Weekly Spend'!$F$86:$CV$86,0))} -> 0 | W18: {=INDEX('Weekly Spend'!$F$86:$CV$94,MATCH($B18,'Weekly Spend'!$F$86:$F$94,0),MATCH(W$3,'Weekly Spend'!$F$86:$CV$86,0))} -> 0 | X18: {=INDEX('Weekly Spend'!$F$86:$CV$94,MATCH($B18,'Weekly Spend'!$F$86:$F$94,0),MATCH(X$3,'Weekly Spend'!$F$86:$CV$86,0))} -> 0 | Y18: {=INDEX('Weekly Spend'!$F$86:$CV$94,MATCH($B18,'Weekly Spend'!$F$86:$F$94,0),MATCH(Y$3,'Weekly Spend'!$F$86:$CV$86,0))} -> 0 | ... AN18: {=INDEX('Weekly Spend'!$F$86:$CV$94,MATCH($B18,'Weekly Spend'!$F$86:$F$94,0),MATCH(AN$3,'Weekly Spend'!$F$86:$CV$86,0))} -> 0
B19: Inventory | C19: Projected Payments | D19: {=INDEX('Weekly Spend'!$F$86:$CV$94,MATCH($B19,'Weekly Spend'!$F$86:$F$94,0),MATCH(D$3,'Weekly Spend'!$F$86:$CV$86,0))} -> 59428 | E19: {=INDEX('Weekly Spend'!$F$86:$CV$94,MATCH($B19,'Weekly Spend'!$F$86:$F$94,0),MATCH(E$3,'Weekly Spend'!$F$86:$CV$86,0))} -> 0 | F19: {=INDEX('Weekly Spend'!$F$86:$CV$94,MATCH($B19,'Weekly Spend'!$F$86:$F$94,0),MATCH(F$3,'Weekly Spend'!$F$86:$CV$86,0))} -> 19000 | G19: {=INDEX('Weekly Spend'!$F$86:$CV$94,MATCH($B19,'Weekly Spend'!$F$86:$F$94,0),MATCH(G$3,'Weekly Spend'!$F$86:$CV$86,0))} -> 212100 | H19: =INDEX('Weekly Spend'!$F$86:$CV$94,MATCH($B19,'Weekly Spend'!$F$86:$F$94,0),MATCH(H$3,'Weekly Spend'!$F$86:$CV$86,0)) -> 0 | I19: {=INDEX('Weekly Spend'!$F$86:$CV$94,MATCH($B19,'Weekly Spend'!$F$86:$F$94,0),MATCH(I$3,'Weekly Spend'!$F$86:$CV$86,0))} -> 132000 | J19: {=INDEX('Weekly Spend'!$F$86:$CV$94,MATCH($B19,'Weekly Spend'!$F$86:$F$94,0),MATCH(J$3,'Weekly Spend'!$F$86:$CV$86,0))} -> 19200 | K19: {=INDEX('Weekly Spend'!$F$86:$CV$94,MATCH($B19,'Weekly Spend'!$F$86:$F$94,0),MATCH(K$3,'Weekly Spend'!$F$86:$CV$86,0))} -> 430000 | L19: {=INDEX('Weekly Spend'!$F$86:$CV$94,MATCH($B19,'Weekly Spend'!$F$86:$F$94,0),MATCH(L$3,'Weekly Spend'!$F$86:$CV$86,0))} -> 221429 | M19: {=INDEX('Weekly Spend'!$F$86:$CV$94,MATCH($B19,'Weekly Spend'!$F$86:$F$94,0),MATCH(M$3,'Weekly Spend'!$F$86:$CV$86,0))} -> 601044 | N19: {=INDEX('Weekly Spend'!$F$86:$CV$94,MATCH($B19,'Weekly Spend'!$F$86:$F$94,0),MATCH(N$3,'Weekly Spend'!$F$86:$CV$86,0))} -> 14400 | O19: {=INDEX('Weekly Spend'!$F$86:$CV$94,MATCH($B19,'Weekly Spend'!$F$86:$F$94,0),MATCH(O$3,'Weekly Spend'!$F$86:$CV$86,0))} -> 50000 | P19: {=INDEX('Weekly Spend'!$F$86:$CV$94,MATCH($B19,'Weekly Spend'!$F$86:$F$94,0),MATCH(P$3,'Weekly Spend'!$F$86:$CV$86,0))} -> 0 | R19: {=INDEX('Weekly Spend'!$F$86:$CV$94,MATCH($B19,'Weekly Spend'!$F$86:$F$94,0),MATCH(R$3,'Weekly Spend'!$F$86:$CV$86,0))} -> 0 | S19: {=INDEX('Weekly Spend'!$F$86:$CV$94,MATCH($B19,'Weekly Spend'!$F$86:$F$94,0),MATCH(S$3,'Weekly Spend'!$F$86:$CV$86,0))} -> 0 | T19: {=INDEX('Weekly Spend'!$F$86:$CV$94,MATCH($B19,'Weekly Spend'!$F$86:$F$94,0),MATCH(T$3,'Weekly Spend'!$F$86:$CV$86,0))} -> 215900 | U19: {=INDEX('Weekly Spend'!$F$86:$CV$94,MATCH($B19,'Weekly Spend'!$F$86:$F$94,0),MATCH(U$3,'Weekly Spend'!$F$86:$CV$86,0))} -> 221429 | V19: {=INDEX('Weekly Spend'!$F$86:$CV$94,MATCH($B19,'Weekly Spend'!$F$86:$F$94,0),MATCH(V$3,'Weekly Spend'!$F$86:$CV$86,0))} -> 460200 | W19: {=INDEX('Weekly Spend'!$F$86:$CV$94,MATCH($B19,'Weekly Spend'!$F$86:$F$94,0),MATCH(W$3,'Weekly Spend'!$F$86:$CV$86,0))} -> 0 | X19: {=INDEX('Weekly Spend'!$F$86:$CV$94,MATCH($B19,'Weekly Spend'!$F$86:$F$94,0),MATCH(X$3,'Weekly Spend'!$F$86:$CV$86,0))} -> 0 | Y19: {=INDEX('Weekly Spend'!$F$86:$CV$94,MATCH($B19,'Weekly Spend'!$F$86:$F$94,0),MATCH(Y$3,'Weekly Spend'!$F$86:$CV$86,0))} -> 33600 | ... AN19: {=INDEX('Weekly Spend'!$F$86:$CV$94,MATCH($B19,'Weekly Spend'!$F$86:$F$94,0),MATCH(AN$3,'Weekly Spend'!$F$86:$CV$86,0))} -> 0
B20: NRE | C20: Invoices | D20: {=INDEX('Weekly Spend'!$F$86:$CV$94,MATCH($B20,'Weekly Spend'!$F$86:$F$94,0),MATCH(D$3,'Weekly Spend'!$F$86:$CV$86,0))} -> 57692.31 | E20: {=INDEX('Weekly Spend'!$F$86:$CV$94,MATCH($B20,'Weekly Spend'!$F$86:$F$94,0),MATCH(E$3,'Weekly Spend'!$F$86:$CV$86,0))} -> 0 | F20: =INDEX('Weekly Spend'!$F$86:$CV$94,MATCH($B20,'Weekly Spend'!$F$86:$F$94,0),MATCH(F$3,'Weekly Spend'!$F$86:$CV$86,0)) -> 155000 | G20: {=INDEX('Weekly Spend'!$F$86:$CV$94,MATCH($B20,'Weekly Spend'!$F$86:$F$94,0),MATCH(G$3,'Weekly Spend'!$F$86:$CV$86,0))} -> 28250 | H20: {=INDEX('Weekly Spend'!$F$86:$CV$94,MATCH($B20,'Weekly Spend'!$F$86:$F$94,0),MATCH(H$3,'Weekly Spend'!$F$86:$CV$86,0))} -> 184196.66 | I20: {=INDEX('Weekly Spend'!$F$86:$CV$94,MATCH($B20,'Weekly Spend'!$F$86:$F$94,0),MATCH(I$3,'Weekly Spend'!$F$86:$CV$86,0))} -> 31250 | J20: {=INDEX('Weekly Spend'!$F$86:$CV$94,MATCH($B20,'Weekly Spend'!$F$86:$F$94,0),MATCH(J$3,'Weekly Spend'!$F$86:$CV$86,0))} -> 72500 | K20: {=INDEX('Weekly Spend'!$F$86:$CV$94,MATCH($B20,'Weekly Spend'!$F$86:$F$94,0),MATCH(K$3,'Weekly Spend'!$F$86:$CV$86,0))} -> 0 | L20: {=INDEX('Weekly Spend'!$F$86:$CV$94,MATCH($B20,'Weekly Spend'!$F$86:$F$94,0),MATCH(L$3,'Weekly Spend'!$F$86:$CV$86,0))} -> 50000 | M20: {=INDEX('Weekly Spend'!$F$86:$CV$94,MATCH($B20,'Weekly Spend'!$F$86:$F$94,0),MATCH(M$3,'Weekly Spend'!$F$86:$CV$86,0))} -> 38000 | N20: {=INDEX('Weekly Spend'!$F$86:$CV$94,MATCH($B20,'Weekly Spend'!$F$86:$F$94,0),MATCH(N$3,'Weekly Spend'!$F$86:$CV$86,0))} -> 50000 | ... P20: {=INDEX('Weekly Spend'!$F$86:$CV$94,MATCH($B20,'Weekly Spend'!$F$86:$F$94,0),MATCH(P$3,'Weekly Spend'!$F$86:$CV$86,0))} -> 0 | R20: {=INDEX('Weekly Spend'!$F$86:$CV$94,MATCH($B20,'Weekly Spend'!$F$86:$F$94,0),MATCH(R$3,'Weekly Spend'!$F$86:$CV$86,0))} -> 0 | S20: {=INDEX('Weekly Spend'!$F$86:$CV$94,MATCH($B20,'Weekly Spend'!$F$86:$F$94,0),MATCH(S$3,'Weekly Spend'!$F$86:$CV$86,0))} -> 100000 | T20: {=INDEX('Weekly Spend'!$F$86:$CV$94,MATCH($B20,'Weekly Spend'!$F$86:$F$94,0),MATCH(T$3,'Weekly Spend'!$F$86:$CV$86,0))} -> 0 | U20: {=INDEX('Weekly Spend'!$F$86:$CV$94,MATCH($B20,'Weekly Spend'!$F$86:$F$94,0),MATCH(U$3,'Weekly Spend'!$F$86:$CV$86,0))} -> 195000 | V20: {=INDEX('Weekly Spend'!$F$86:$CV$94,MATCH($B20,'Weekly Spend'!$F$86:$F$94,0),MATCH(V$3,'Weekly Spend'!$F$86:$CV$86,0))} -> 0 | W20: {=INDEX('Weekly Spend'!$F$86:$CV$94,MATCH($B20,'Weekly Spend'!$F$86:$F$94,0),MATCH(W$3,'Weekly Spend'!$F$86:$CV$86,0))} -> 0 | X20: {=INDEX('Weekly Spend'!$F$86:$CV$94,MATCH($B20,'Weekly Spend'!$F$86:$F$94,0),MATCH(X$3,'Weekly Spend'!$F$86:$CV$86,0))} -> 45000 | Y20: {=INDEX('Weekly Spend'!$F$86:$CV$94,MATCH($B20,'Weekly Spend'!$F$86:$F$94,0),MATCH(Y$3,'Weekly Spend'!$F$86:$CV$86,0))} -> 35000 | ... AN20: {=INDEX('Weekly Spend'!$F$86:$CV$94,MATCH($B20,'Weekly Spend'!$F$86:$F$94,0),MATCH(AN$3,'Weekly Spend'!$F$86:$CV$86,0))} -> 0
B21: Other | C21: Varies | D21: 0 | E21: 0 | F21: 0 | G21: 0 | H21: 0 | I21: 0 | J21: 0 | K21: 0 | L21: 0 | M21: 0 | N21: 0 | O21: 0 | P21: 0 | R21: 0 | S21: 0 | T21: 0 | U21: 0 | V21: 0 | W21: 0 | X21: 0 | Y21: 0 | Z21: 0 | AA21: 0 | AB21: 0 | AC21: 0 | AD21: 0 | AE21: 0 | AF21: 0 | AG21: 0 | AH21: 0 | AI21: 0 | AJ21: 0 | AK21: 0 | AL21: 0 | AM21: 0 | AN21: 0
B22: Total Must Pay | D22: =SUM(D14:D21) -> 122626.11 | E22: =SUM(E14:E21) -> 10537 | F22: =SUM(F14:F21) -> 242597.5 | G22: =SUM(G14:G21) -> 406079.69 | H22: =SUM(H14:H21) -> 188696.66 | I22: =SUM(I14:I21) -> 271316.69 | J22: =SUM(J14:J21) -> 156900 | K22: =SUM(K14:K21) -> 558316.69 | ... P22: =SUM(P14:P21) -> 52425 | R22: =SUM(R14:R21) -> 110841.69 | S22: =SUM(S14:S21) -> 107125 | T22: =SUM(T14:T21) -> 387838.69 | U22: =SUM(U14:U21) -> 466369.8 | V22: =SUM(V14:V21) -> 561954.49 | W22: =SUM(W14:W21) -> 9940.8 | X22: =SUM(X14:X21) -> 164454.49 | Y22: =SUM(Y14:Y21) -> 113540.8 | ... AN22: =SUM(AN14:AN21) -> 101461.69
B23: Accounts Payable
B24: Payables by week | C24: AP Aging (by week)
B25: Recurring Non Inventory Payables not in Aging report | C25: AP Forecast (non-inventory)
B26: Estimated Inventory AP from Open Purchase Orders | C26: AP Forecast (Open PO)
B27: Estimated Inventory AP from MRP estimated purchases | C27: AP Forecast (MRP)
B28: Total Accounts Payable | D28: =SUM(D24:D27) -> 0 | E28: =SUM(E24:E27) -> 0 | F28: =SUM(F24:F27) -> 0 | G28: =SUM(G24:G27) -> 0 | H28: =SUM(H24:H27) -> 0 | I28: =SUM(I24:I27) -> 0 | J28: =SUM(J24:J27) -> 0 | K28: =SUM(K24:K27) -> 0 | ... P28: =SUM(P24:P27) -> 0 | R28: =SUM(R24:R27) -> 0 | S28: =SUM(S24:S27) -> 0 | T28: =SUM(T24:T27) -> 0 | U28: =SUM(U24:U27) -> 0 | V28: =SUM(V24:V27) -> 0 | W28: =SUM(W24:W27) -> 0 | X28: =SUM(X24:X27) -> 0 | Y28: =SUM(Y24:Y27) -> 0 | ... AN28: =SUM(AN24:AN27) -> 0
B29: TOTAL OPERATING CASH OUTFLOWS | D29: =D22+D28 -> 122626.11 | E29: =E22+E28 -> 10537 | F29: =F22+F28 -> 242597.5 | G29: =G22+G28 -> 406079.69 | H29: =H22+H28 -> 188696.66 | I29: =I22+I28 -> 271316.69 | J29: =J22+J28 -> 156900 | K29: =K22+K28 -> 558316.69 | ... P29: =P22+P28 -> 52425 | R29: =R22+R28 -> 110841.69 | S29: =S22+S28 -> 107125 | T29: =T22+T28 -> 387838.69 | U29: =U22+U28 -> 466369.8 | V29: =V22+V28 -> 561954.49 | W29: =W22+W28 -> 9940.8 | X29: =X22+X28 -> 164454.49 | Y29: =Y22+Y28 -> 113540.8 | ... AN29: =AN22+AN28 -> 101461.69
B31: OPERATING CASH FLOW (excl. financing activities) | D31: =D10-D29 -> -56674.11 | E31: =E10-E29 -> 33431 | F31: =F10-F29 -> -204834.5 | G31: =G10-G29 -> -406079.69 | H31: =H10-H29 -> -58696.66 | I31: =I10-I29 -> -271316.69 | J31: =J10-J29 -> -60900 | K31: =K10-K29 -> -528316.69 | ... P31: =P10-P29 -> 457575 | R31: =R10-R29 -> -110841.69 | S31: =S10-S29 -> 92875 | T31: =T10-T29 -> -387838.69 | U31: =U10-U29 -> -116369.8 | V31: =V10-V29 -> -561954.49 | W31: =W10-W29 -> 230059.2 | X31: =X10-X29 -> -164454.49 | Y31: =Y10-Y29 -> 146459.2 | ... AN31: =AN10-AN29 -> -101461.69
B33: FUNDING REQUEST
B34: Tide Rock Capital Funding (LT Notes Payable) | D34: 0 | E34: 0 | F34: 0 | G34: 0 | H34: 0 | I34: 0 | J34: 0 | K34: 0 | L34: 0 | M34: 0 | N34: 0 | O34: 0 | P34: 0 | R34: 0 | S34: 0 | T34: 0 | U34: 0 | V34: 0 | W34: 0 | X34: 0 | Y34: 0 | Z34: 0 | AA34: 0 | AB34: 0 | AC34: 0 | AD34: 0 | AF34: 0 | AG34: 0 | AH34: 0 | AI34: 0 | AJ34: 0 | AK34: 0 | AL34: 0 | AM34: 0 | AN34: 0
B35: Tide Rock Cashflow Funding (ST Notes Payable) | F35: 100000 | G35: =500000 -> 500000 | J35: 250000 | K35: 750000 | M35: 600000 | V35: 225000 | Z35: 150000 | AD35: 100000 | AK35: 0 | AL35: 0 | AN35: 0
B36: TOTAL FUNDING REQUEST | D36: =SUM(D34:D35) -> 0 | E36: =SUM(E34:E35) -> 0 | F36: =SUM(F34:F35) -> 100000 | G36: =SUM(G34:G35) -> 500000 | H36: =SUM(H34:H35) -> 0 | I36: =SUM(I34:I35) -> 0 | J36: =SUM(J34:J35) -> 250000 | K36: =SUM(K34:K35) -> 750000 | ... P36: =SUM(P34:P35) -> 0 | R36: =SUM(R34:R35) -> 0 | S36: =SUM(S34:S35) -> 0 | T36: =SUM(T34:T35) -> 0 | U36: =SUM(U34:U35) -> 0 | V36: =SUM(V34:V35) -> 225000 | W36: =SUM(W34:W35) -> 0 | X36: =SUM(X34:X35) -> 0 | Y36: =SUM(Y34:Y35) -> 0 | ... AN36: =SUM(AN34:AN35) -> 0
B38: NON OPERATING CASH DISBURSEMENTS
B39: Tide Rock Notes Repayment | C39: Repayment Plan | D39: 0 | E39: 0 | F39: 0 | G39: 0 | H39: 0 | I39: 0 | J39: 0 | K39: 0 | L39: 0 | M39: 0 | P39: 0 | S39: 0 | T39: 0 | U39: 0 | V39: 0 | AJ39: 0 | AL39: 0
B40: Tide Rock Interest Payments | C40: Monthly Invoice (TR) | D40: =INDEX('Weekly Spend'!$F$86:$CV$94,MATCH($B40,'Weekly Spend'!$F$86:$F$94,0),MATCH(D$3,'Weekly Spend'!$F$86:$CV$86,0)) -> 0 | E40: =INDEX('Weekly Spend'!$F$86:$CV$94,MATCH($B40,'Weekly Spend'!$F$86:$F$94,0),MATCH(E$3,'Weekly Spend'!$F$86:$CV$86,0)) -> 0 | F40: =INDEX('Weekly Spend'!$F$86:$CV$94,MATCH($B40,'Weekly Spend'!$F$86:$F$94,0),MATCH(F$3,'Weekly Spend'!$F$86:$CV$86,0)) -> 15000 | G40: =INDEX('Weekly Spend'!$F$86:$CV$94,MATCH($B40,'Weekly Spend'!$F$86:$F$94,0),MATCH(G$3,'Weekly Spend'!$F$86:$CV$86,0)) -> 0 | H40: =INDEX('Weekly Spend'!$F$86:$CV$94,MATCH($B40,'Weekly Spend'!$F$86:$F$94,0),MATCH(H$3,'Weekly Spend'!$F$86:$CV$86,0)) -> 0 | I40: =INDEX('Weekly Spend'!$F$86:$CV$94,MATCH($B40,'Weekly Spend'!$F$86:$F$94,0),MATCH(I$3,'Weekly Spend'!$F$86:$CV$86,0)) -> 0 | J40: =INDEX('Weekly Spend'!$F$86:$CV$94,MATCH($B40,'Weekly Spend'!$F$86:$F$94,0),MATCH(J$3,'Weekly Spend'!$F$86:$CV$86,0)) -> 0 | K40: =INDEX('Weekly Spend'!$F$86:$CV$94,MATCH($B40,'Weekly Spend'!$F$86:$F$94,0),MATCH(K$3,'Weekly Spend'!$F$86:$CV$86,0)) -> 15000 | ... P40: =INDEX('Weekly Spend'!$F$86:$CV$94,MATCH($B40,'Weekly Spend'!$F$86:$F$94,0),MATCH(P$3,'Weekly Spend'!$F$86:$CV$86,0)) -> 0 | R40: =INDEX('Weekly Spend'!$F$86:$CV$94,MATCH($B40,'Weekly Spend'!$F$86:$F$94,0),MATCH(R$3,'Weekly Spend'!$F$86:$CV$86,0)) -> 0 | S40: =INDEX('Weekly Spend'!$F$86:$CV$94,MATCH($B40,'Weekly Spend'!$F$86:$F$94,0),MATCH(S$3,'Weekly Spend'!$F$86:$CV$86,0)) -> 0 | T40: =INDEX('Weekly Spend'!$F$86:$CV$94,MATCH($B40,'Weekly Spend'!$F$86:$F$94,0),MATCH(T$3,'Weekly Spend'!$F$86:$CV$86,0)) -> 0 | U40: =INDEX('Weekly Spend'!$F$86:$CV$94,MATCH($B40,'Weekly Spend'!$F$86:$F$94,0),MATCH(U$3,'Weekly Spend'!$F$86:$CV$86,0)) -> 15000 | V40: =INDEX('Weekly Spend'!$F$86:$CV$94,MATCH($B40,'Weekly Spend'!$F$86:$F$94,0),MATCH(V$3,'Weekly Spend'!$F$86:$CV$86,0)) -> 0 | W40: =INDEX('Weekly Spend'!$F$86:$CV$94,MATCH($B40,'Weekly Spend'!$F$86:$F$94,0),MATCH(W$3,'Weekly Spend'!$F$86:$CV$86,0)) -> 0 | X40: =INDEX('Weekly Spend'!$F$86:$CV$94,MATCH($B40,'Weekly Spend'!$F$86:$F$94,0),MATCH(X$3,'Weekly Spend'!$F$86:$CV$86,0)) -> 0 | Y40: =INDEX('Weekly Spend'!$F$86:$CV$94,MATCH($B40,'Weekly Spend'!$F$86:$F$94,0),MATCH(Y$3,'Weekly Spend'!$F$86:$CV$86,0)) -> 13333 | ... AN40: =INDEX('Weekly Spend'!$F$86:$CV$94,MATCH($B40,'Weekly Spend'!$F$86:$F$94,0),MATCH(AN$3,'Weekly Spend'!$F$86:$CV$86,0)) -> 0
B41: Tide Rock Distributions (including MPs) | C41: Quarterly Distribution Schedule | D41: 0 | E41: 0 | F41: 0 | I41: 0 | K41: 0 | L41: 0 | M41: 0 | N41: 0 | O41: 0 | P41: 0 | R41: 0 | S41: 0 | T41: 0 | U41: 0 | V41: 0 | W41: 0 | X41: 0 | Y41: 0 | Z41: 0 | AA41: 0 | AB41: 0 | AC41: 0 | AD41: 0 | AE41: 0 | AF41: 0 | AG41: 0 | AH41: 0 | AI41: 0 | AJ41: 0 | AK41: 0 | AL41: 0 | AM41: 0 | AN41: 0
B43: NET CASH FLOW | D43: =D31+D36-SUM(D39:D41) -> -56674.11 | E43: =E31+E36-SUM(E39:E41) -> 33431 | F43: =F31+F36-SUM(F39:F41) -> -119834.5 | G43: =G31+G36-SUM(G39:G41) -> 93920.308 | H43: =H31+H36-SUM(H39:H41) -> -58696.66 | I43: =I31+I36-SUM(I39:I41) -> -271316.69 | J43: =J31+J36-SUM(J39:J41) -> 189100 | K43: =K31+K36-SUM(K39:K41) -> 206683.31 | ... P43: =P31+P36-SUM(P39:P41) -> 457575 | R43: =R31+R36-SUM(R39:R41) -> -110841.69 | S43: =S31+S36-SUM(S39:S41) -> 92875 | T43: =T31+T36-SUM(T39:T41) -> -387838.69 | U43: =U31+U36-SUM(U39:U41) -> -131369.8 | V43: =V31+V36-SUM(V39:V41) -> -336954.49 | W43: =W31+W36-SUM(W39:W41) -> 230059.2 | X43: =X31+X36-SUM(X39:X41) -> -164454.49 | Y43: =Y31+Y36-SUM(Y39:Y41) -> 133126.2 | ... AN43: =AN31+AN36-SUM(AN39:AN41) -> -101461.69
B45: Beginning Bank Balance | C45: Include all bank accounts | D45: 769810.3 | E45: =D48 -> 713136.19 | F45: =E48 -> 746567.19 | G45: =F48 -> 626732.69 | H45: =G48 -> 720653 | I45: =H48 -> 661956.34 | J45: =I48 -> 390639.65 | K45: =J48 -> 579739.65 | L45: =K48 -> 786422.95 | ... P45: =O48 -> 272791.57 | R45: =P48 -> 730366.57 | S45: =R48 -> 619524.88 | T45: =S48 -> 712399.88 | U45: =T48 -> 324561.18 | V45: =U48 -> 193191.38 | W45: =V48 -> -143763.11 | X45: =W48 -> 86296.092 | Y45: =X48 -> -78158.401 | Z45: =Y48 -> 54967.799 | ... AN45: =AM48 -> 1390812.3
B46: Outstanding checks | C46: bank recon to update
B48: ENDING BOOK BALANCE | D48: =D45+D43+D46 -> 713136.19 | E48: =E45+E43+E46 -> 746567.19 | F48: =F45+F43+F46 -> 626732.69 | G48: =G45+G43+G46 -> 720653 | H48: =H45+H43+H46 -> 661956.34 | I48: =I45+I43+I46 -> 390639.65 | J48: =J45+J43+J46 -> 579739.65 | K48: =K45+K43+K46 -> 786422.95 | ... P48: =P45+P43+P46 -> 730366.57 | R48: =R45+R43+R46 -> 619524.88 | S48: =S45+S43+S46 -> 712399.88 | T48: =T45+T43+T46 -> 324561.18 | U48: =U45+U43+U46 -> 193191.38 | V48: =V45+V43+V46 -> -143763.11 | W48: =W45+W43+W46 -> 86296.092 | X48: =X45+X43+X46 -> -78158.401 | Y48: =Y45+Y43+Y46 -> 54967.799 | ... AN48: =AN45+AN43+AN46 -> 1289350.7
B51: Low Cash | C51: =MIN(D48:AN48) -> -307450.13
B52: Loans | C52: =_xlfn.XLOOKUP(C51,48:48,3:3) -> 46146 | D52: 2325000 | E52: =D52+E36 -> 2325000 | F52: =E52+F36 -> 2425000 | G52: =F52+G36 -> 2925000 | H52: =G52+H36 -> 2925000 | I52: =H52+I36 -> 2925000 | J52: =I52+J36 -> 3175000 | K52: =J52+K36 -> 3925000 | L52: =K52+L36 -> 3925000 | ... P52: =O52+P36 -> 4525000 | R52: =P52+R36 -> 4525000 | S52: =R52+S36 -> 4525000 | T52: =S52+T36 -> 4525000 | U52: =T52+U36 -> 4525000 | V52: =U52+V36 -> 4750000 | W52: =V52+W36 -> 4750000 | X52: =W52+X36 -> 4750000 | Y52: =X52+Y36 -> 4750000 | Z52: =Y52+Z36 -> 4900000 | ... AN52: =AM52+AN36 -> 5000000
R54: f
E57: Loan Tracker (Forecast) 11.03.25 | G57: =F65+42000+200000+1000000 -> 6242000 | H57: =F63+42000+200000+1000000 -> 3567000
E58: Loan 6/13 BB | F58: 500000
E59: Loan 7/18 | F59: 500000
E60: Loan 7/23 | F60: 300000
E61: Loan 7/28 | F61: 600000
E62: Loan 8/18 | F62: 425000
E63: Total Loans | F63: =SUM(F58:F62) -> 2325000
E64: Future Needs | F64: =SUM(D36:AN36) -> 2675000
E65: Total Requirements | F65: =F64+F63 -> 5000000
E66: Repayment Due
J68: Loan Tracker (Forecast) 10.27.25
I69: Loan 6/13 BB | J69: 500000
I70: Loan 7/18 | J70: 500000
I71: Loan 7/23 | J71: 300000
I72: Loan 7/28 | J72: 600000
I73: Loan 8/18 | J73: 425000
I74: Loan 11/17 | J74: 700000
I75: Loan 12/15 | J75: =L35 -> 0
I76: Loan 12/22 | J76: 900000

Sheet Sheet1

Sheet Cash Receipts
A1: AR Cash Receipts
B2: Get Real Numbers
B3: Week 1 | C3: Week 2 | D3: Week 3 | E3: Week 4 | F3: Week 5 | G3: Week 6 | H3: Week 7 | I3: Week 8 | J3: Week 9 | K3: Week 10 | L3: Week 11 | M3: Week 12 | N3: Week 13
B4: 45831 | C4: 45838 | D4: 45845 | E4: 45852 | F4: 45859 | G4: 45866 | H4: 45873 | I4: 45880 | J4: 45887 | K4: 45894 | L4: 45901 | M4: 45908 | N4: 45915
A6: Microcenter | E6: 12320
A7: Amazon | C7: =35498+64740+200 -> 100438 | D7: 24765 | E7: =80000-E6 -> 67680 | F7: 80000 | G7: 80000 | H7: 0 | I7: =325000/4 -> 81250 | J7: 0 | K7: 30000 | L7: 0 | N7: =325000/4 -> 81250
A8: New Sales | H8: 125000 | I8: =125000-I7 -> 43750 | J8: 125000 | K8: =125000-K7 -> 95000 | L8: 125000 | M8: 125000 | N8: =125000-N7 -> 43750
A13: Total Cash Receipts | C13: =SUM(C6:C12) -> 100438 | D13: =SUM(D6:D12) -> 24765 | E13: =SUM(E6:E12) -> 80000 | F13: =SUM(F6:F12) -> 80000 | G13: =SUM(G6:G12) -> 80000 | H13: =SUM(H6:H12) -> 125000 | I13: =SUM(I6:I12) -> 125000 | J13: =SUM(J6:J12) -> 125000 | ... N13: =SUM(N6:N12) -> 125000

Sheet LAST WEEK CASHFLOW FORECAST
D1: 1 | E1: =D1+1 -> 2 | F1: =E1+1 -> 3 | G1: =F1+1 -> 4 | H1: =G1+1 -> 5 | I1: =H1+1 -> 6 | J1: =I1+1 -> 7 | K1: =J1+1 -> 8 | L1: =K1+1 -> 9 | ... P1: =O1+1 -> 13
B2: - Copy and paste last week submission in this tab | C2: Week # | D2: ="Week"&" "&D1 -> Week 1 | E2: ="Week"&" "&E1 -> Week 2 | F2: ="Week"&" "&F1 -> Week 3 | G2: ="Week"&" "&G1 -> Week 4 | H2: ="Week"&" "&H1 -> Week 5 | I2: ="Week"&" "&I1 -> Week 6 | J2: ="Week"&" "&J1 -> Week 7 | K2: ="Week"&" "&K1 -> Week 8 | ... P2: ="Week"&" "&P1 -> Week 13
B3: - Paste Special -> Values and Number Formats | C3: Monday of week | D3: 45383 | E3: 45390 | F3: 45397 | G3: 45404 | H3: 45411 | I3: 45418 | J3: 45425 | K3: 45432 | L3: 45439 | M3: 45446 | N3: 45453 | O3: 45460 | P3: 45467
B4: OPERATING CASH INFLOWS
B5: Operating Cash Receipts
B6: Customer Cash Receipts from A/R | C6: AR Aging
B7: Customer Forecasted Receipts from Backlog | C7: AR (Backlog)
B8: Customer Forecasted Receipts from Sales Forecast | C8: AR (Sales Forecast)
B9: Other, non-customer related inflows | C9: Varies
B10: TOTAL INCOMING CASH | D10: =SUM(D6:D9) -> 0 | E10: =SUM(E6:E9) -> 0 | F10: =SUM(F6:F9) -> 0 | G10: =SUM(G6:G9) -> 0 | H10: =SUM(H6:H9) -> 0 | I10: =SUM(I6:I9) -> 0 | J10: =SUM(J6:J9) -> 0 | K10: =SUM(K6:K9) -> 0 | ... P10: =SUM(P6:P9) -> 0
B12: OPERATING CASH DISBURSEMENTS
B13: Must Pays
B14: Wages and benefits (payroll) | C14: Weekly Payroll
B15: Rent | C15: Monthly Invoice
B16: Insurance | C16: Monthly Invoice
B17: Sales Tax Expense | C17: Monthly or Quarterly | Q17: Health Benefits
B18: Credit Card Expense | C18: Monthly Auto Draw | Q18: Rent
B19: Other | C19: Varies
B20: Total Must Pay | D20: =SUM(D14:D19) -> 0 | E20: =SUM(E14:E19) -> 0 | F20: =SUM(F14:F19) -> 0 | G20: =SUM(G14:G19) -> 0 | H20: =SUM(H14:H19) -> 0 | I20: =SUM(I14:I19) -> 0 | J20: =SUM(J14:J19) -> 0 | K20: =SUM(K14:K19) -> 0 | ... P20: =SUM(P14:P19) -> 0
B21: Accounts Payable
B22: Payables by week | C22: AP Aging (by week)
B23: Recurring Non Inventory Payables not in Aging report | C23: AP Forecast (non-inventory)
B24: Estimated Inventory AP from Open Purchase Orders | C24: AP Forecast (Open PO)
B25: Estimated Inventory AP from MRP estimated purchases | C25: AP Forecast (MRP)
B26: Total Accounts Payable | D26: =SUM(D22:D25) -> 0 | E26: =SUM(E22:E25) -> 0 | F26: =SUM(F22:F25) -> 0 | G26: =SUM(G22:G25) -> 0 | H26: =SUM(H22:H25) -> 0 | I26: =SUM(I22:I25) -> 0 | J26: =SUM(J22:J25) -> 0 | K26: =SUM(K22:K25) -> 0 | ... P26: =SUM(P22:P25) -> 0
B27: TOTAL OPERATING CASH OUTFLOWS | D27: =D20+D26 -> 0 | E27: =E20+E26 -> 0 | F27: =F20+F26 -> 0 | G27: =G20+G26 -> 0 | H27: =H20+H26 -> 0 | I27: =I20+I26 -> 0 | J27: =J20+J26 -> 0 | K27: =K20+K26 -> 0 | ... P27: =P20+P26 -> 0
B29: OPERATING CASH FLOW (excl. financing activities) | D29: =D10-D27 -> 0 | E29: =E10-E27 -> 0 | F29: =F10-F27 -> 0 | G29: =G10-G27 -> 0 | H29: =H10-H27 -> 0 | I29: =I10-I27 -> 0 | J29: =J10-J27 -> 0 | K29: =K10-K27 -> 0 | ... P29: =P10-P27 -> 0
B31: FUNDING REQUEST
B32: Tide Rock Capital Funding (LT Notes Payable) | D32: 0 | E32: 0 | F32: 0 | G32: 0 | H32: 0 | I32: 0 | J32: 0 | K32: 0 | L32: 0 | M32: 0 | N32: 0 | O32: 0 | P32: 0
B33: Tide Rock Cashflow Funding (ST Notes Payable) | D33: 0 | E33: 0 | F33: 0 | G33: 0 | H33: 0 | I33: 0 | J33: 0 | K33: 0 | L33: 0 | M33: 0 | N33: 0 | O33: 0 | P33: 0
B34: TOTAL FUNDING REQUEST | D34: =SUM(D32:D33) -> 0 | E34: 0 | F34: 0 | G34: 0 | H34: 0 | I34: 0 | J34: 0 | K34: 0 | L34: 0 | M34: 0 | N34: 0 | O34: 0 | P34: 0
B36: NON OPERATING CASH DISBURSEMENTS
B37: Tide Rock Notes Repayment | C37: Repayment Plan | D37: 0
B38: Tide Rock Interest Payments | C38: Monthly Invoice (TR) | D38: 0
B39: Tide Rock Distributions (including MPs) | C39: Quarterly Distribution Schedule | D39: 0 | E39: 0 | F39: 0 | G39: 0 | H39: 0 | I39: 0 | J39: 0 | K39: 0 | L39: 0 | M39: 0 | N39: 0 | O39: 0 | P39: 0
B41: NET CASH FLOW | D41: =D29+D34-SUM(D37:D39) -> 0 | E41: =E29+E34-SUM(E37:E39) -> 0 | F41: =F29+F34-SUM(F37:F39) -> 0 | G41: =G29+G34-SUM(G37:G39) -> 0 | H41: =H29+H34-SUM(H37:H39) -> 0 | I41: =I29+I34-SUM(I37:I39) -> 0 | J41: =J29+J34-SUM(J37:J39) -> 0 | K41: =K29+K34-SUM(K37:K39) -> 0 | ... P41: =P29+P34-SUM(P37:P39) -> 0
B43: Beginning Bank Balance | C43: Include all bank accounts | E43: =D46 -> 0 | F43: =E46 -> 0 | G43: =F46 -> 0 | H43: =G46 -> 0 | I43: =H46 -> 0 | J43: =I46 -> 0 | K43: =J46 -> 0 | L43: =K46 -> 0 | ... P43: =O46 -> 0
B44: Outstanding checks | C44: bank recon to update | D44: 0 | E44: 0 | F44: 0 | G44: 0 | H44: 0 | I44: 0 | J44: 0 | K44: 0 | L44: 0 | M44: 0 | N44: 0 | O44: 0 | P44: 0
B46: ENDING BOOK BALANCE | D46: =D43+D41+D44 -> 0 | E46: =E43+E41+E44 -> 0 | F46: =F43+F41+F44 -> 0 | G46: =G43+G41+G44 -> 0 | H46: =H43+H41+H44 -> 0 | I46: =I43+I41+I44 -> 0 | J46: =J43+J41+J44 -> 0 | K46: =K43+K41+K44 -> 0 | ... P46: =P43+P41+P44 -> 0

Sheet CASHFLOW VARIANCE ANALYSIS
C30: 1 | D30: =C30+1 -> 2 | E30: =D30+1 -> 3 | F30: =E30+1 -> 4 | G30: =F30+1 -> 5 | H30: =G30+1 -> 6 | I30: =H30+1 -> 7 | J30: =I30+1 -> 8 | K30: =J30+1 -> 9 | ... O30: =N30+1 -> 13
B31: Week # | C31: ="Week"&" "&C30 -> Week 1 | D31: ="Week"&" "&D30 -> Week 2 | E31: ="Week"&" "&E30 -> Week 3 | F31: ="Week"&" "&F30 -> Week 4 | G31: ="Week"&" "&G30 -> Week 5 | H31: ="Week"&" "&H30 -> Week 6 | I31: ="Week"&" "&I30 -> Week 7 | J31: ="Week"&" "&J30 -> Week 8 | ... O31: ="Week"&" "&O30 -> Week 13
B32: Monday of week | C32: ='CURRENT FORECAST START DATE'!C4 -> 45971 | D32: =C32+7 -> 45978 | E32: =D32+7 -> 45985 | F32: =E32+7 -> 45992 | G32: =F32+7 -> 45999 | H32: =G32+7 -> 46006 | I32: =H32+7 -> 46013 | J32: =I32+7 -> 46020 | K32: =J32+7 -> 46027 | ... O32: =N32+7 -> 46055 | Q32: Comments
B33: ENDING BOOK BALANCE [CURRENT FORECAST] | C33: ='CURRENT WEEK CASHFLOW FORECAST'!D48 -> 713136.19 | D33: ='CURRENT WEEK CASHFLOW FORECAST'!E48 -> 746567.19 | E33: ='CURRENT WEEK CASHFLOW FORECAST'!F48 -> 626732.69 | F33: ='CURRENT WEEK CASHFLOW FORECAST'!G48 -> 720653 | G33: ='CURRENT WEEK CASHFLOW FORECAST'!H48 -> 661956.34 | H33: ='CURRENT WEEK CASHFLOW FORECAST'!I48 -> 390639.65 | I33: ='CURRENT WEEK CASHFLOW FORECAST'!J48 -> 579739.65 | J33: ='CURRENT WEEK CASHFLOW FORECAST'!K48 -> 786422.95 | ... O33: ='CURRENT WEEK CASHFLOW FORECAST'!P48 -> 730366.57 | Q33: Pull from CASHFLOW FORECAST CURRENT WEEK
A34: x | B34: ENDING BOOK BALANCE [LAST WEEK FORECAST] | C34: ='LAST WEEK CASHFLOW FORECAST'!E46 -> 0 | D34: ='LAST WEEK CASHFLOW FORECAST'!F46 -> 0 | E34: ='LAST WEEK CASHFLOW FORECAST'!G46 -> 0 | F34: ='LAST WEEK CASHFLOW FORECAST'!H46 -> 0 | G34: ='LAST WEEK CASHFLOW FORECAST'!I46 -> 0 | H34: ='LAST WEEK CASHFLOW FORECAST'!J46 -> 0 | I34: ='LAST WEEK CASHFLOW FORECAST'!K46 -> 0 | J34: ='LAST WEEK CASHFLOW FORECAST'!L46 -> 0 | ... N34: ='LAST WEEK CASHFLOW FORECAST'!P46 -> 0 | Q34: Pull from CASHFLOW FORECAST LAST WEEK - make sure it starts at week 2
A36: x | B36: VARIANCE ($) | C36: =C33-C34 -> 713136.19 | D36: =D33-D34 -> 746567.19 | E36: =E33-E34 -> 626732.69 | F36: =F33-F34 -> 720653 | G36: =G33-G34 -> 661956.34 | H36: =H33-H34 -> 390639.65 | I36: =I33-I34 -> 579739.65 | J36: =J33-J34 -> 786422.95 | ... N36: =N33-N34 -> 272791.57 | Q36: Variance $ [Current - Forecast]
B37: VARIANCE (%) | C37: =C36/C34 -> #DIV/0! | D37: =D36/D34 -> #DIV/0! | E37: =E36/E34 -> #DIV/0! | F37: =F36/F34 -> #DIV/0! | G37: =G36/G34 -> #DIV/0! | H37: =H36/H34 -> #DIV/0! | I37: =I36/I34 -> #DIV/0! | J37: =J36/J34 -> #DIV/0! | ... N37: =N36/N34 -> #DIV/0! | Q37: Variance % [Current - Forecast]
A39: x | B39: VARIANCE EXPLANATIONS
B40: Current Cash Receipts from A/R | C40: ='CURRENT WEEK CASHFLOW FORECAST'!D6-'LAST WEEK CASHFLOW FORECAST'!E6 -> 9000 | D40: ='CURRENT WEEK CASHFLOW FORECAST'!E6-'LAST WEEK CASHFLOW FORECAST'!F6 -> 0 | E40: ='CURRENT WEEK CASHFLOW FORECAST'!F6-'LAST WEEK CASHFLOW FORECAST'!G6 -> 32000 | F40: ='CURRENT WEEK CASHFLOW FORECAST'!G6-'LAST WEEK CASHFLOW FORECAST'!H6 -> 0 | G40: ='CURRENT WEEK CASHFLOW FORECAST'!H6-'LAST WEEK CASHFLOW FORECAST'!I6 -> 80000 | H40: ='CURRENT WEEK CASHFLOW FORECAST'!I6-'LAST WEEK CASHFLOW FORECAST'!J6 -> 0 | I40: ='CURRENT WEEK CASHFLOW FORECAST'!J6-'LAST WEEK CASHFLOW FORECAST'!K6 -> 96000 | J40: ='CURRENT WEEK CASHFLOW FORECAST'!K6-'LAST WEEK CASHFLOW FORECAST'!L6 -> 0 | ... N40: ='CURRENT WEEK CASHFLOW FORECAST'!O6-'LAST WEEK CASHFLOW FORECAST'!P6 -> 0 | Q40: Variance in AR Aging report
B41: Forecasted Receipts | C41: =('CURRENT WEEK CASHFLOW FORECAST'!D7+'CURRENT WEEK CASHFLOW FORECAST'!D8)-('LAST WEEK CASHFLOW FORECAST'!E7+'LAST WEEK CASHFLOW FORECAST'!E8) -> 56952 | D41: =('CURRENT WEEK CASHFLOW FORECAST'!E7+'CURRENT WEEK CASHFLOW FORECAST'!E8)-('LAST WEEK CASHFLOW FORECAST'!F7+'LAST WEEK CASHFLOW FORECAST'!F8) -> 43968 | E41: =('CURRENT WEEK CASHFLOW FORECAST'!F7+'CURRENT WEEK CASHFLOW FORECAST'!F8)-('LAST WEEK CASHFLOW FORECAST'!G7+'LAST WEEK CASHFLOW FORECAST'!G8) -> 5763 | F41: =('CURRENT WEEK CASHFLOW FORECAST'!G7+'CURRENT WEEK CASHFLOW FORECAST'!G8)-('LAST WEEK CASHFLOW FORECAST'!H7+'LAST WEEK CASHFLOW FORECAST'!H8) -> 0 | G41: =('CURRENT WEEK CASHFLOW FORECAST'!H7+'CURRENT WEEK CASHFLOW FORECAST'!H8)-('LAST WEEK CASHFLOW FORECAST'!I7+'LAST WEEK CASHFLOW FORECAST'!I8) -> 50000 | H41: =('CURRENT WEEK CASHFLOW FORECAST'!I7+'CURRENT WEEK CASHFLOW FORECAST'!I8)-('LAST WEEK CASHFLOW FORECAST'!J7+'LAST WEEK CASHFLOW FORECAST'!J8) -> 0 | I41: =('CURRENT WEEK CASHFLOW FORECAST'!J7+'CURRENT WEEK CASHFLOW FORECAST'!J8)-('LAST WEEK CASHFLOW FORECAST'!K7+'LAST WEEK CASHFLOW FORECAST'!K8) -> 0 | J41: =('CURRENT WEEK CASHFLOW FORECAST'!K7+'CURRENT WEEK CASHFLOW FORECAST'!K8)-('LAST WEEK CASHFLOW FORECAST'!L7+'LAST WEEK CASHFLOW FORECAST'!L8) -> 30000 | ... N41: =('CURRENT WEEK CASHFLOW FORECAST'!O7+'CURRENT WEEK CASHFLOW FORECAST'!O8)-('LAST WEEK CASHFLOW FORECAST'!P7+'LAST WEEK CASHFLOW FORECAST'!P8) -> 0 | Q41: Variance in Revenue forecasts [Backlog + Forecast]
B42: Accured Payroll Expense (including Bonus) | C42: =-('CURRENT WEEK CASHFLOW FORECAST'!D14-'LAST WEEK CASHFLOW FORECAST'!E14) -> 0 | D42: =-('CURRENT WEEK CASHFLOW FORECAST'!E14-'LAST WEEK CASHFLOW FORECAST'!F14) -> 0 | E42: =-('CURRENT WEEK CASHFLOW FORECAST'!F14-'LAST WEEK CASHFLOW FORECAST'!G14) -> -4500 | F42: =-('CURRENT WEEK CASHFLOW FORECAST'!G14-'LAST WEEK CASHFLOW FORECAST'!H14) -> -98566.692 | G42: =-('CURRENT WEEK CASHFLOW FORECAST'!H14-'LAST WEEK CASHFLOW FORECAST'!I14) -> 0 | H42: =-('CURRENT WEEK CASHFLOW FORECAST'!I14-'LAST WEEK CASHFLOW FORECAST'!J14) -> -93566.692 | I42: =-('CURRENT WEEK CASHFLOW FORECAST'!J14-'LAST WEEK CASHFLOW FORECAST'!K14) -> 0 | J42: =-('CURRENT WEEK CASHFLOW FORECAST'!K14-'LAST WEEK CASHFLOW FORECAST'!L14) -> -92316.692 | ... N42: =-('CURRENT WEEK CASHFLOW FORECAST'!O14-'LAST WEEK CASHFLOW FORECAST'!P14) -> -99816.692 | Q42: Variance in Payroll Liabilities / Accruals
B43: Accrued Rent | C43: =-('CURRENT WEEK CASHFLOW FORECAST'!D15-'LAST WEEK CASHFLOW FORECAST'!E15) -> -5505.8 | D43: =-('CURRENT WEEK CASHFLOW FORECAST'!E15-'LAST WEEK CASHFLOW FORECAST'!F15) -> -5287 | E43: =-('CURRENT WEEK CASHFLOW FORECAST'!F15-'LAST WEEK CASHFLOW FORECAST'!G15) -> -20097.5 | F43: =-('CURRENT WEEK CASHFLOW FORECAST'!G15-'LAST WEEK CASHFLOW FORECAST'!H15) -> -67163 | G43: =-('CURRENT WEEK CASHFLOW FORECAST'!H15-'LAST WEEK CASHFLOW FORECAST'!I15) -> -4500 | H43: =-('CURRENT WEEK CASHFLOW FORECAST'!I15-'LAST WEEK CASHFLOW FORECAST'!J15) -> -14500 | I43: =-('CURRENT WEEK CASHFLOW FORECAST'!J15-'LAST WEEK CASHFLOW FORECAST'!K15) -> -54500 | J43: =-('CURRENT WEEK CASHFLOW FORECAST'!K15-'LAST WEEK CASHFLOW FORECAST'!L15) -> -26500 | ... N43: =-('CURRENT WEEK CASHFLOW FORECAST'!O15-'LAST WEEK CASHFLOW FORECAST'!P15) -> -26906.25 | Q43: Variance in Accrued Rent / Sales Tax
B44: Accounts Payable | C44: =-(SUM('CURRENT WEEK CASHFLOW FORECAST'!D24:D27)-SUM('LAST WEEK CASHFLOW FORECAST'!E22:E25)) -> 0 | D44: =-(SUM('CURRENT WEEK CASHFLOW FORECAST'!E24:E27)-SUM('LAST WEEK CASHFLOW FORECAST'!F22:F25)) -> 0 | E44: =-(SUM('CURRENT WEEK CASHFLOW FORECAST'!F24:F27)-SUM('LAST WEEK CASHFLOW FORECAST'!G22:G25)) -> 0 | F44: =-(SUM('CURRENT WEEK CASHFLOW FORECAST'!G24:G27)-SUM('LAST WEEK CASHFLOW FORECAST'!H22:H25)) -> 0 | G44: =-(SUM('CURRENT WEEK CASHFLOW FORECAST'!H24:H27)-SUM('LAST WEEK CASHFLOW FORECAST'!I22:I25)) -> 0 | H44: =-(SUM('CURRENT WEEK CASHFLOW FORECAST'!I24:I27)-SUM('LAST WEEK CASHFLOW FORECAST'!J22:J25)) -> 0 | I44: =-(SUM('CURRENT WEEK CASHFLOW FORECAST'!J24:J27)-SUM('LAST WEEK CASHFLOW FORECAST'!K22:K25)) -> 0 | J44: =-(SUM('CURRENT WEEK CASHFLOW FORECAST'!K24:K27)-SUM('LAST WEEK CASHFLOW FORECAST'!L22:L25)) -> 0 | ... N44: =-(SUM('CURRENT WEEK CASHFLOW FORECAST'!O24:O27)-SUM('LAST WEEK CASHFLOW FORECAST'!P22:P25)) -> 0 | Q44: Variance in AP [Aging + Open PO + MRP]
B45: Accrued Sales Tax | C45: =-('CURRENT WEEK CASHFLOW FORECAST'!D17-'LAST WEEK CASHFLOW FORECAST'!E17) -> 0 | D45: =-('CURRENT WEEK CASHFLOW FORECAST'!E17-'LAST WEEK CASHFLOW FORECAST'!F17) -> -5250 | E45: =-('CURRENT WEEK CASHFLOW FORECAST'!F17-'LAST WEEK CASHFLOW FORECAST'!G17) -> -44000 | F45: =-('CURRENT WEEK CASHFLOW FORECAST'!G17-'LAST WEEK CASHFLOW FORECAST'!H17) -> 0 | G45: =-('CURRENT WEEK CASHFLOW FORECAST'!H17-'LAST WEEK CASHFLOW FORECAST'!I17) -> 0 | H45: =-('CURRENT WEEK CASHFLOW FORECAST'!I17-'LAST WEEK CASHFLOW FORECAST'!J17) -> 0 | I45: =-('CURRENT WEEK CASHFLOW FORECAST'!J17-'LAST WEEK CASHFLOW FORECAST'!K17) -> -10700 | J45: =-('CURRENT WEEK CASHFLOW FORECAST'!K17-'LAST WEEK CASHFLOW FORECAST'!L17) -> -9500 | ... N45: =-('CURRENT WEEK CASHFLOW FORECAST'!O17-'LAST WEEK CASHFLOW FORECAST'!P17) -> -24000 | Q45: Variance in Accured Sales Tax Expense
B46: Accrued Credit Card Expense | C46: =-('CURRENT WEEK CASHFLOW FORECAST'!D18-'LAST WEEK CASHFLOW FORECAST'!E18) -> 0 | D46: =-('CURRENT WEEK CASHFLOW FORECAST'!E18-'LAST WEEK CASHFLOW FORECAST'!F18) -> 0 | E46: =-('CURRENT WEEK CASHFLOW FORECAST'!F18-'LAST WEEK CASHFLOW FORECAST'!G18) -> 0 | F46: =-('CURRENT WEEK CASHFLOW FORECAST'!G18-'LAST WEEK CASHFLOW FORECAST'!H18) -> 0 | G46: =-('CURRENT WEEK CASHFLOW FORECAST'!H18-'LAST WEEK CASHFLOW FORECAST'!I18) -> 0 | H46: =-('CURRENT WEEK CASHFLOW FORECAST'!I18-'LAST WEEK CASHFLOW FORECAST'!J18) -> 0 | I46: =-('CURRENT WEEK CASHFLOW FORECAST'!J18-'LAST WEEK CASHFLOW FORECAST'!K18) -> 0 | J46: =-('CURRENT WEEK CASHFLOW FORECAST'!K18-'LAST WEEK CASHFLOW FORECAST'!L18) -> 0 | ... N46: =-('CURRENT WEEK CASHFLOW FORECAST'!O18-'LAST WEEK CASHFLOW FORECAST'!P18) -> 0 | Q46: Variance in Accrued Credit Card Expense
B47: All Other | C47: =-('CURRENT WEEK CASHFLOW FORECAST'!D21-'LAST WEEK CASHFLOW FORECAST'!E19) -> 0 | D47: =-('CURRENT WEEK CASHFLOW FORECAST'!E21-'LAST WEEK CASHFLOW FORECAST'!F19) -> 0 | E47: =-('CURRENT WEEK CASHFLOW FORECAST'!F21-'LAST WEEK CASHFLOW FORECAST'!G19) -> 0 | F47: =-('CURRENT WEEK CASHFLOW FORECAST'!G21-'LAST WEEK CASHFLOW FORECAST'!H19) -> 0 | G47: =-('CURRENT WEEK CASHFLOW FORECAST'!H21-'LAST WEEK CASHFLOW FORECAST'!I19) -> 0 | H47: =-('CURRENT WEEK CASHFLOW FORECAST'!I21-'LAST WEEK CASHFLOW FORECAST'!J19) -> 0 | I47: =-('CURRENT WEEK CASHFLOW FORECAST'!J21-'LAST WEEK CASHFLOW FORECAST'!K19) -> 0 | J47: =-('CURRENT WEEK CASHFLOW FORECAST'!K21-'LAST WEEK CASHFLOW FORECAST'!L19) -> 0 | ... N47: =-('CURRENT WEEK CASHFLOW FORECAST'!O21-'LAST WEEK CASHFLOW FORECAST'!P19) -> 0 | Q47: All Others, add commentary
B48: Prior Week Cash Balance Impact | D48: ='CURRENT WEEK CASHFLOW FORECAST'!D48-'LAST WEEK CASHFLOW FORECAST'!E46 -> 713136.19 | E48: ='CURRENT WEEK CASHFLOW FORECAST'!E48-'LAST WEEK CASHFLOW FORECAST'!F46 -> 746567.19 | F48: ='CURRENT WEEK CASHFLOW FORECAST'!F48-'LAST WEEK CASHFLOW FORECAST'!G46 -> 626732.69 | G48: ='CURRENT WEEK CASHFLOW FORECAST'!G48-'LAST WEEK CASHFLOW FORECAST'!H46 -> 720653 | H48: ='CURRENT WEEK CASHFLOW FORECAST'!H48-'LAST WEEK CASHFLOW FORECAST'!I46 -> 661956.34 | I48: ='CURRENT WEEK CASHFLOW FORECAST'!I48-'LAST WEEK CASHFLOW FORECAST'!J46 -> 390639.65 | J48: ='CURRENT WEEK CASHFLOW FORECAST'!J48-'LAST WEEK CASHFLOW FORECAST'!K46 -> 579739.65 | K48: ='CURRENT WEEK CASHFLOW FORECAST'!K48-'LAST WEEK CASHFLOW FORECAST'!L46 -> 786422.95 | ... N48: ='CURRENT WEEK CASHFLOW FORECAST'!N48-'LAST WEEK CASHFLOW FORECAST'!O46 -> 538514.51 | Q48: Impact / carry-over from prior week
A49: x | B49: Check | C49: =C36-SUM(C40:C48) -> 652689.99 | D49: =D36-SUM(D40:D48) -> 0 | E49: =E36-SUM(E40:E48) -> -89000 | F49: =F36-SUM(F40:F48) -> 259650 | G49: =G36-SUM(G40:G48) -> -184196.66 | H49: =H36-SUM(H40:H48) -> -163250 | I49: =I36-SUM(I40:I48) -> 158300 | J49: =J36-SUM(J40:J48) -> 305000 | ... N49: =N36-SUM(N40:N48) -> -115000 | Q49: Should sum to 0
B51: CASH CONVERSION CYCLE ASSUMPTIONS | C51: Current | D51: Forecasted | E51: Forecasted | F51: Forecasted | G51: Forecasted | H51: Forecasted | I51: Forecasted | J51: Forecasted | K51: Forecasted | L51: Forecasted | M51: Forecasted | N51: Forecasted | Q51: Reason for Forecast
B52: (+) Days Sales Outstanding (DSO) | C52: 40 | D52: 55 | E52: 55 | F52: 55 | G52: 55 | H52: 55 | I52: 55 | J52: 55 | K52: 55 | L52: 55 | M52: 55 | N52: 55
B53: (+) Days Inventory Outstanding (DIO) | C53: 40 | D53: 10 | E53: 10 | F53: 10 | G53: 10 | H53: 10 | I53: 10 | J53: 10 | K53: 10 | L53: 10 | M53: 10 | N53: 10
B54: (-) Days Payable Outstanding (DPO) | C54: 40 | D54: -10 | E54: -10 | F54: -10 | G54: -10 | H54: -10 | I54: -10 | J54: -10 | K54: -10 | L54: -10 | M54: -10 | N54: -10
B55: Cash to Cash Days | C55: =C52+C53-C54 -> 40 | D55: =D52+D53-D54 -> 75 | E55: =E52+E53-E54 -> 75 | F55: =F52+F53-F54 -> 75 | G55: =G52+G53-G54 -> 75 | H55: =H52+H53-H54 -> 75 | I55: =I52+I53-I54 -> 75 | J55: =J52+J53-J54 -> 75 | ... N55: =N52+N53-N54 -> 75
B57: COMMENTARY ON VARIANCE
B58: Current Cash Receipts from A/R | C58: New Template
B59: Forecasted Receipts | C59: New Template
B60: Wages and Benefits / Accrued Bonus | C60: New Template
B61: Accrued Rent | C61: New Template
B62: Accounts Payable | C62: New Template
B63: Accrued Sales Tax | C63: New Template
B64: Accrued Credit Card Expense | C64: New Template
B65: Accounts Payable | C65: New Template
A66: x | B66: All Other | C66: New Template

Sheet NRE Inventory
D1: 45852 | E1: =D1+7 -> 45859 | F1: =E1+7 -> 45866 | G1: =F1+7 -> 45873 | H1: =G1+7 -> 45880 | I1: =H1+7 -> 45887 | J1: =I1+7 -> 45894 | K1: =J1+7 -> 45901 | L1: =K1+7 -> 45908 | ... AI1: =AH1+7 -> 46069
C2: Week 24~~~~~To Date | D2: Week 29 | E2: Week 30 | F2: Week 31 | G2: Week 32 | H2: Week 33 | I2: Week 34 | J2: Week 35 | K2: Week 36 | L2: Week 37 | M2: Week 38 | N2: Week 39 | O2: Week 40 | P2: Week 41 | Q2: Week 42 | R2: Week 43 | S2: Week 44 | T2: Week 45 | U2: Week 46 | V2: Week 47 | W2: Week 48 | X2: Week 49 | Y2: Week 50 | Z2: Week 51 | AA2: Week 52 | AB2: Week 1 | AC2: Week 2 | AD2: Week 3 | AE2: Week 4 | AF2: Week 5 | AG2: Week 6 | AH2: Week 7 | AI2: Week 8
A3: RLOC | B3: Debt for Dev and Opex and Inventory (Q15, Q21, B15, P15) | C3: 500000 | D3: 1000000 | F3: 1000000
B4: NEW SKU's, MULTI-CHANNEL
A5: Revenue | B5: Q15, Q21, B15, P15 Sales | M5: B15 ExWorks | O5: Q15 ExWorks | S5: B15-E ExWorks | AA5: Q21 ExWorks | AE5: Q15 E ExWorks | AH5: P15 ExWorks
A6: =SUM(C6:AI6) -> 2107929 | B6: Q15 Sales | S6: 624969 | AH6: 1482960
A7: =SUM(C7:AI7) -> 168843 | B7: B15 Sales | T7: =17495/2 -> 8747.5 | V7: =17495/2 -> 8747.5 | X7: =34991/2 -> 17495.5 | Z7: =34991/2 -> 17495.5 | AB7: =52486/2 -> 26243 | AD7: =52486/2 -> 26243 | AF7: =63871/2 -> 31935.5 | AH7: =63871/2 -> 31935.5
A8: =SUM(C8:AI8) -> 0 | B8: Q21 Sales
A9: =SUM(C9:AI9) -> 0 | B9: P15 Sales
A10: =SUM(C10:AI10) -> 1403601.5 | B10: Q20 Sales | J10: =34791/2 -> 17395.5 | L10: =34791/2 -> 17395.5 | N10: =55510/2 -> 27755 | P10: =55510/2 -> 27755 | R10: =214861/2 -> 107430.5 | T10: =214861/2 -> 107430.5 | V10: =354352/2 -> 177176 | X10: =354352/2 -> 177176 | Z10: =415620/2 -> 207810 | AB10: =415620/2 -> 207810 | AD10: =234821/2 -> 117410.5 | AF10: =234821/2 -> 117410.5 | AH10: =187293/2 -> 93646.5
A11: Minim.co Inventory Revenue | B11: OLD SKU's, SINGLE CHANNEL
B12: Legacy All SKUs | F12: =170571/2 -> 85285.5 | H12: =170571/2 -> 85285.5 | J12: =270317/2 -> 135158.5 | L12: =270317/2 -> 135158.5 | N12: =276693/2 -> 138346.5 | P12: =276693/2 -> 138346.5 | R12: =372794/2 -> 186397 | T12: =372794/2 -> 186397 | V12: =524927/2 -> 262463.5 | X12: =524927/2 -> 262463.5 | Z12: =418751/2 -> 209375.5 | AB12: =418751/2 -> 209375.5 | AD12: =415264/2 -> 207632 | AF12: =415264/2 -> 207632 | AH12: =466229/2 -> 233114.5
B15: Total | C15: =SUM(C6:C10)+SUM(C12:C13) -> 0 | D15: =SUM(D6:D10)+SUM(D12:D13) -> 0 | E15: =SUM(E6:E10)+SUM(E12:E13) -> 0 | F15: =SUM(F6:F10)+SUM(F12:F13) -> 85285.5 | G15: =SUM(G6:G10)+SUM(G12:G13) -> 0 | H15: =SUM(H6:H10)+SUM(H12:H13) -> 85285.5 | I15: =SUM(I6:I10)+SUM(I12:I13) -> 0 | J15: =SUM(J6:J10)+SUM(J12:J13) -> 152554 | ... AI15: =SUM(AI6:AI10)+SUM(AI12:AI13) -> 0
B16: 0.8 | C16: =C15*$B$16 -> 0 | D16: =D15*$B$16 -> 0 | E16: =E15*$B$16 -> 0 | F16: =F15*$B$16 -> 68228.4 | G16: =G15*$B$16 -> 0 | H16: =H15*$B$16 -> 68228.4 | I16: =I15*$B$16 -> 0 | J16: =J15*$B$16 -> 122043.2 | ... AI16: =AI15*$B$16 -> 0
B17: Evolving from legacy SKU's and single channel (Amazon) to multi-SKU/multi-channel in the USA (via EMG); allows further channel expansion via global disitrbutors | C17: 8
B19: STATEMENT on use of DOLLARS
C20: =C37+C22 -> 318474 | D20: =D37+D22 -> 313992 | E20: =E37+E22 -> 71053 | F20: =F37+F22 -> 483525 | G20: =G37+G22 -> 104700 | H20: =H37+H22 -> 37500 | I20: =I37+I22 -> 104000 | J20: =J37+J22 -> 69042 | ... AI20: =AI37+AI22 -> 0
A22: Product Development | B22: Q15, Q20,Q21, B15, P15 | C22: =SUM(C23:C34) -> 222474 | D22: =SUM(D23:D34) -> 124042 | E22: =SUM(E23:E34) -> 21053 | F22: =SUM(F23:F34) -> 189000 | G22: =SUM(G23:G34) -> 0 | H22: =SUM(H23:H34) -> 37500 | I22: =SUM(I23:I34) -> 104000 | J22: =SUM(J23:J34) -> 69042 | ... AI22: =SUM(AI23:AI34) -> 0
A23: =SUM(C23:AI23) -> 154588 | B23: Q15 | C23: 71119 | D23: $ - | E23: $ - | F23: $ - | G23: $ - | I23: $ - | J23: $ - | M23: $ - | N23: $ - | O23: 71119 | P23: 12350 | Q23: $ - | R23: $ - | S23: $ - | T23: $ - | U23: $ - | V23: $ - | W23: $ - | X23: $ - | Y23: $ - | Z23: $ - | AA23: $ - | AB23: $ - | AC23: $ - | AD23: $ - | AE23: $ - | AF23: $ - | AG23: $ - | AH23: $ - | AI23: $ -
A24: =SUM(C24:AI24) -> 42106 | B24: Q15-RoW | C24: $ - | D24: $ - | E24: 21053 | F24: $ - | H24: $ - | I24: $ - | J24: $ - | K24: $ - | L24: $ - | M24: $ - | N24: $ - | O24: 21053 | P24: $ - | Q24: $ - | R24: $ - | S24: $ - | T24: $ - | U24: $ - | V24: $ - | W24: $ - | X24: $ - | Y24: $ - | Z24: $ - | AA24: $ - | AB24: $ - | AC24: $ - | AD24: $ - | AE24: $ - | AF24: $ - | AG24: $ - | AH24: $ - | AI24: $ -
A25: =SUM(C25:AI25) -> 350939 | B25: B15 | C25: 151355 | D25: 5292 | E25: $ - | F25: 189000 | G25: $ - | H25: $ - | I25: $ - | J25: 5292 | K25: $ - | L25: $ - | N25: $ - | O25: $ - | P25: $ - | Q25: $ - | R25: $ - | S25: $ - | T25: $ - | U25: $ - | V25: $ - | W25: $ - | X25: $ - | Y25: $ - | Z25: $ - | AA25: $ - | AB25: $ - | AC25: $ - | AD25: $ - | AE25: $ - | AF25: $ - | AG25: $ - | AH25: $ - | AI25: $ -
A26: =SUM(C26:AI26) -> 46384 | B26: B15-RoW | C26: $ - | E26: $ - | F26: $ - | G26: $ - | H26: $ - | I26: $ - | K26: 23192 | L26: $ - | M26: $ - | N26: $ - | O26: =K26 -> 23192 | P26: $ - | Q26: $ - | R26: $ - | S26: $ - | T26: $ - | U26: $ - | V26: $ - | W26: $ - | X26: $ - | Y26: $ - | Z26: $ - | AA26: $ - | AB26: $ - | AC26: $ - | AD26: $ - | AE26: $ - | AF26: $ - | AG26: $ - | AH26: $ - | AI26: $ -
A27: =SUM(C27:AI27) -> 160000 | B27: Q21 | C27: $ - | D27: $ - | E27: $ - | F27: $ - | H27: $ - | I27: 80000 | J27: $ - | K27: $ - | L27: $ - | M27: $ - | N27: $ - | O27: $ - | P27: $ - | Q27: $ - | R27: $ - | S27: $ - | T27: $ - | U27: $ - | V27: $ - | W27: $ - | X27: $ - | Y27: $ - | Z27: $ - | AA27: $ - | AB27: 80000 | AC27: $ - | AD27: $ - | AE27: $ - | AF27: $ - | AG27: $ - | AH27: $ - | AI27: $ -
A28: =SUM(C28:AI28) -> 48000 | B28: Q21-RoW | C28: $ - | D28: $ - | E28: $ - | F28: $ - | H28: $ - | I28: 24000 | J28: $ - | K28: $ - | L28: $ - | M28: $ - | N28: $ - | O28: $ - | P28: $ - | Q28: $ - | R28: $ - | S28: $ - | T28: $ - | U28: $ - | V28: $ - | W28: $ - | X28: $ - | Y28: $ - | Z28: $ - | AA28: $ - | AB28: $ - | AC28: $ - | AD28: $ - | AE28: $ - | AF28: 24000 | AG28: $ - | AH28: $ - | AI28: $ -
A29: =SUM(C29:AI29) -> 249000 | B29: P15 | C29: $ - | D29: 118750 | E29: $ - | F29: $ - | G29: $ - | H29: 37500 | I29: $ - | J29: $ - | K29: $ - | L29: $ - | M29: $ - | N29: $ - | O29: $ - | P29: 18750 | Q29: $ - | R29: $ - | S29: $ - | T29: $ - | U29: 37000 | V29: $ - | W29: $ - | X29: $ - | Y29: $ - | Z29: $ - | AA29: $ - | AB29: $ - | AC29: $ - | AD29: 37000 | AE29: $ - | AF29: $ - | AG29: $ - | AH29: $ - | AI29: $ -
A30: =SUM(C30:AI30) -> 0 | B30: P15-RoW | C30: $ - | D30: $ - | E30: $ - | F30: $ - | G30: $ - | H30: $ - | I30: $ - | J30: $ - | K30: $ - | L30: $ - | M30: $ - | N30: $ - | O30: $ - | P30: $ - | Q30: $ - | R30: $ - | S30: $ - | T30: $ - | U30: $ - | V30: $ - | W30: $ - | X30: $ - | Y30: $ - | Z30: $ - | AA30: $ - | AB30: $ - | AC30: $ - | AD30: $ - | AE30: $ - | AF30: $ - | AG30: $ - | AH30: $ - | AI30: $ -
A31: =SUM(C31:AI31) -> 0 | B31: Q20 | C31: $ - | D31: $ - | E31: $ - | F31: $ - | G31: $ - | H31: $ - | I31: $ - | J31: $ - | K31: $ - | L31: $ - | M31: $ - | N31: $ - | O31: $ - | P31: $ - | Q31: $ - | R31: $ - | S31: $ - | T31: $ - | U31: $ - | V31: $ - | W31: $ - | X31: $ - | Y31: $ - | Z31: $ - | AA31: $ - | AB31: $ - | AC31: $ - | AD31: $ - | AE31: $ - | AF31: $ - | AG31: $ - | AH31: $ - | AI31: $ -
A32: =SUM(C32:AI32) -> 0 | B32: Q20-RoW | C32: $ - | D32: $ - | E32: $ - | F32: $ - | G32: $ - | H32: $ - | I32: $ - | J32: $ - | K32: $ - | L32: $ - | M32: $ - | N32: $ - | O32: $ - | P32: $ - | Q32: $ - | R32: $ - | S32: $ - | T32: $ - | U32: $ - | V32: $ - | W32: $ - | X32: $ - | Y32: $ - | Z32: $ - | AA32: $ - | AB32: $ - | AC32: $ - | AD32: $ - | AE32: $ - | AF32: $ - | AG32: $ - | AH32: $ - | AI32: $ -
A33: =SUM(C33:AI33) -> 0 | B33: MotoSync PRO | C33: $ - | E33: $ - | F33: $ - | G33: $ - | I33: $ - | J33: $ - | K33: $ - | L33: $ - | M33: $ - | N33: $ - | O33: $ - | P33: $ - | Q33: $ - | R33: $ - | S33: $ - | T33: $ - | U33: $ - | V33: $ - | W33: $ - | X33: $ - | Y33: $ - | Z33: $ - | AA33: $ - | AB33: $ - | AC33: $ - | AD33: $ - | AE33: $ - | AF33: $ - | AG33: $ - | AH33: $ - | AI33: $ -
A34: =SUM(C34:AI34) -> 63750 | B34: Motosync+ (p15) | C34: $ - | D34: $ - | E34: $ - | F34: $ - | G34: $ - | J34: =50000+13750 -> 63750 | K34: $ - | L34: $ - | M34: $ - | N34: $ - | O34: $ - | P34: $ - | Q34: $ - | R34: $ - | S34: $ - | T34: $ - | U34: $ - | V34: $ - | W34: $ - | X34: $ - | Y34: $ - | Z34: $ - | AA34: $ - | AB34: $ - | AC34: $ - | AD34: $ - | AE34: $ - | AF34: $ - | AG34: $ - | AH34: $ - | AI34: $ -
D36: =10%*D37 -> 18995 | E36: =10%*E37 -> 5000 | F36: =10%*F37 -> 29452.5 | G36: =10%*G37 -> 10470 | H36: =10%*H37 -> 0 | I36: =10%*I37 -> 0 | J36: =10%*J37 -> 0 | K36: =10%*K37 -> 0 | ... AI36: =10%*AI37 -> 0
A37: Product Inventory | B37: Q15, Q20,Q21, B15, P15 | C37: =SUM(C38:C47) -> 96000 | D37: =SUM(D38:D47) -> 189950 | E37: =SUM(E38:E47) -> 50000 | F37: =SUM(F38:F47) -> 294525 | G37: =SUM(G38:G47) -> 104700 | H37: =SUM(H38:H47) -> 0 | I37: =SUM(I38:I47) -> 0 | J37: =SUM(J38:J47) -> 0 | ... AI37: =SUM(AI38:AI47) -> 0 | AJ37: =SUM(C37:AI37) -> 2980725
A38: =SUM(C38:AI38) -> 387500 | B38: Q15 | C38: 96000 | D38: $ - | E38: 50000 | F38: $ - | G38: $ - | H38: $ - | I38: $ - | J38: $ - | K38: $ - | L38: $ - | M38: $ - | N38: $ - | O38: 241500 | P38: $ - | Q38: $ - | R38: $ - | S38: $ - | T38: $ - | U38: $ - | V38: $ - | W38: $ - | X38: $ - | Y38: $ - | Z38: $ - | AA38: $ - | AB38: $ - | AC38: $ - | AD38: $ - | AE38: $ - | AF38: $ - | AG38: $ - | AH38: $ - | AI38: $ -
A39: =SUM(C39:AI39) -> 349000 | B39: Q15-RoW | C39: $ - | D39: $ - | G39: 104700 | H39: $ - | I39: $ - | K39: $ - | L39: $ - | M39: $ - | N39: $ - | O39: 244300 | P39: $ - | Q39: $ - | R39: $ - | S39: $ - | T39: $ - | U39: $ - | V39: $ - | W39: $ - | X39: $ - | Y39: $ - | Z39: $ - | AA39: $ - | AB39: $ - | AC39: $ - | AD39: $ - | AE39: $ - | AF39: $ - | AG39: $ - | AH39: $ - | AI39: $ -
A40: =SUM(C40:AI40) -> 759800 | B40: B15 | C40: $ - | D40: 189950 | E40: $ - | F40: $ - | G40: $ - | H40: $ - | I40: $ - | J40: $ - | K40: $ - | L40: $ - | M40: $ - | N40: $ - | O40: $ - | P40: $ - | Q40: 569850 | R40: $ - | S40: $ - | T40: $ - | U40: $ - | V40: $ - | W40: $ - | X40: $ - | Y40: $ - | Z40: $ - | AA40: $ - | AB40: $ - | AC40: $ - | AD40: $ - | AE40: $ - | AF40: $ - | AG40: $ - | AH40: $ - | AI40: $ -
A41: =SUM(C41:AI41) -> 0 | B41: B15-RoW | C41: $ - | D41: $ - | E41: $ - | F41: $ - | G41: $ - | H41: $ - | I41: $ - | J41: $ - | K41: $ - | L41: $ - | M41: $ - | N41: $ - | O41: $ - | P41: $ - | Q41: $ - | R41: $ - | S41: $ - | T41: $ - | U41: $ - | V41: $ - | W41: $ - | X41: $ - | Y41: $ - | Z41: $ - | AA41: $ - | AB41: $ - | AC41: $ - | AD41: $ - | AE41: $ - | AF41: $ - | AG41: $ - | AH41: $ - | AI41: $ -
A42: =SUM(C42:AI42) -> 430000 | B42: Q21 | C42: $ - | D42: $ - | E42: $ - | F42: $ - | G42: $ - | H42: $ - | I42: $ - | J42: $ - | K42: $ - | L42: $ - | M42: $ - | N42: $ - | O42: 129000 | P42: $ - | Q42: $ - | R42: $ - | S42: $ - | T42: $ - | U42: $ - | V42: $ - | W42: $ - | X42: $ - | Y42: $ - | Z42: $ - | AA42: $ - | AB42: 301000 | AC42: $ - | AD42: $ - | AE42: $ - | AF42: $ - | AG42: $ - | AH42: $ - | AI42: $ -
A43: =SUM(C43:AI43) -> 519900 | B43: Q21-RoW | C43: $ - | D43: $ - | E43: $ - | F43: $ - | H43: $ - | I43: $ - | J43: $ - | K43: $ - | L43: $ - | M43: $ - | N43: $ - | O43: $ - | P43: $ - | Q43: $ - | R43: $ - | S43: $ - | T43: 155970 | U43: $ - | V43: $ - | W43: $ - | X43: $ - | Y43: $ - | Z43: $ - | AA43: $ - | AB43: $ - | AC43: $ - | AD43: $ - | AE43: $ - | AF43: 363930 | AG43: $ - | AH43: $ - | AI43: $ -
A44: =SUM(C44:AI44) -> 240000 | B44: P15 | C44: $ - | D44: $ - | E44: $ - | F44: $ - | G44: $ - | H44: $ - | I44: $ - | J44: $ - | K44: $ - | L44: $ - | M44: $ - | N44: $ - | O44: $ - | P44: $ - | Q44: $ - | R44: $ - | S44: $ - | T44: $ - | U44: 72000 | V44: $ - | W44: $ - | X44: $ - | Y44: $ - | Z44: $ - | AA44: $ - | AB44: $ - | AC44: $ - | AD44: $ - | AE44: 168000 | AF44: $ - | AG44: $ - | AH44: $ - | AI44: $ -
A45: =SUM(C45:AI45) -> 0 | B45: P15-RoW | C45: $ - | D45: $ - | E45: $ - | F45: $ - | G45: $ - | H45: $ - | I45: $ - | J45: $ - | K45: $ - | L45: $ - | M45: $ - | N45: $ - | O45: $ - | P45: $ - | Q45: $ - | R45: $ - | S45: $ - | T45: $ - | U45: $ - | V45: $ - | W45: $ - | X45: $ - | Y45: $ - | Z45: $ - | AA45: $ - | AB45: $ - | AC45: $ - | AD45: $ - | AE45: $ - | AF45: $ - | AG45: $ - | AH45: $ - | AI45: $ -
A46: =SUM(C46:AI46) -> 294525 | B46: Q20 | C46: $ - | D46: $ - | E46: $ - | F46: 294525 | G46: $ - | H46: $ - | I46: $ - | J46: $ - | K46: $ - | L46: $ - | M46: $ - | N46: $ - | O46: $ - | P46: $ - | Q46: $ - | R46: $ - | S46: $ - | T46: $ - | U46: $ - | V46: $ - | W46: $ - | X46: $ - | Y46: $ - | Z46: $ - | AA46: $ - | AB46: $ - | AC46: $ - | AD46: $ - | AE46: $ - | AF46: $ - | AG46: $ - | AH46: $ - | AI46: $ -
A47: =SUM(C47:AI47) -> 0 | B47: Q20-RoW | C47: $ - | D47: $ - | E47: $ - | F47: $ - | G47: $ - | H47: $ - | I47: $ - | J47: $ - | K47: $ - | L47: $ - | M47: $ - | N47: $ - | O47: $ - | P47: $ - | Q47: $ - | R47: $ - | S47: $ - | T47: $ - | U47: $ - | V47: $ - | W47: $ - | X47: $ - | Y47: $ - | Z47: $ - | AA47: $ - | AB47: $ - | AC47: $ - | AD47: $ - | AE47: $ - | AF47: $ - | AG47: $ - | AH47: $ - | AI47: $ -

Sheet Memory Chips & Issoy Sale
D4: NRE | E4: Inventory | H4: Sales
C5: Q15 | D5: =+'NRE Inventory'!A23+'NRE Inventory'!A24 -> 196694 | E5: =+'NRE Inventory'!A38+'NRE Inventory'!A39 -> 736500 | F5: =+D5+E5 -> 933194 | H5: =+E5/0.7 -> 1052142.9
C6: B15 | D6: =+'NRE Inventory'!A25+'NRE Inventory'!A26 -> 397323 | E6: =+'NRE Inventory'!A40 -> 759800 | F6: =+D6+E6 -> 1157123 | H6: =+E6/0.7 -> 1085428.6
C7: Q21 | D7: =+'NRE Inventory'!A27+'NRE Inventory'!A28 -> 208000 | E7: =+'NRE Inventory'!A42+'NRE Inventory'!A43 -> 949900 | F7: =+D7+E7 -> 1157900 | H7: =+E7/0.7 -> 1357000
C8: P15 | D8: =+'NRE Inventory'!A29 -> 249000 | E8: =+'NRE Inventory'!A44 -> 240000 | F8: =+D8+E8 -> 489000 | H8: =+E8/0.7 -> 342857.14
C9: Q20 | E9: =+'NRE Inventory'!A46 -> 294525 | F9: =+D9+E9 -> 294525 | H9: =+E9/0.7 -> 420750
B12: Memory Chips | C12: 409600 | D12: =C12/35000 -> 11.702857
C15: B12 | D15: Amazon SP | E15: 194
C16: B12 | D16: Issoy SP | E16: 101
E17: =E15-E16 -> 93
C19: Units Sold to Issoy | E19: 9536
E20: =E19*E17 -> 886848 | F20: Top line lost
C23: Retail Sales line | E23: 4329290
E24: 4155301
E25: =E23-E24 -> 173989

Sheet Sheet3
A3: Years (Date) | B3: Type | C3: Date | D3: Sum of Amount | F3: Years (Date) | G3: Type | H3: Date | I3: Sum of Amount
A4: 2025 | B4: D q15 | C4: 45856 | D4: 15052.5 | F4: 2025 | G4: D q15 | H4: 45856 | I4: 67252.5
C5: 45930 | D5: 86171.19 | H5: 45930 | I5: 86171.19
B6: D q15 Total | D6: 101223.69 | G6: D q15 Total | I6: 153423.69
B7: D q21 | C7: 45870 | D7: 73223.35 | G7: D q21 | H7: 45870 | I7: 73223.35
C8: 46021 | D8: 73223.35 | H8: 46021 | I8: 73223.35
B9: D q21 Total | D9: 146446.7 | G9: D q21 Total | I9: 146446.7
B10: Dq21 | C10: 45870 | D10: 17512.5 | G10: Dq21 | H10: 45870 | I10: 17512.5
C11: 45881 | D11: 12350 | H11: 45881 | I11: 12350
B12: Dq21 Total | D12: 29862.5 | G12: Dq21 Total | I12: 29862.5
B13: I | C13: 45858 | D13: 50000 | G13: I | H13: 45858 | I13: 50000
B14: I Total | D14: 50000 | G14: I Total | I14: 50000
B15: I Q15 | C15: 45856 | D15: 104700 | G15: I Q15 | H15: 45856 | I15: 52500
C16: 45870 | D16: 103500 | H16: 45870 | I16: 103500
C17: 45930 | D17: 493300 | H17: 45930 | I17: 493300
C18: 45960 | D18: 241500 | H18: 45960 | I18: 241500
B19: I Q15 Total | D19: 943000 | G19: I Q15 Total | I19: 890800
B20: I Q21 | C20: 45870 | D20: 129000 | G20: I Q21 | H20: 45870 | I20: 129000
C21: 45930 | D21: 129000 | H21: 45930 | I21: 129000
C22: 45960 | D22: 155970 | H22: 45960 | I22: 155970
C23: 46021 | D23: 602000 | H23: 46021 | I23: 602000
B24: I Q21 Total | D24: 1015970 | G24: I Q21 Total | I24: 1015970
A25: 2025 Total | D25: 2286502.9 | F25: 2025 Total | I25: 2286502.9
A26: 2026 | B26: D q21 | C26: 46052 | D26: 17512.5 | F26: 2026 | G26: D q21 | H26: 46052 | I26: 17512.5
B27: D q21 Total | D27: 17512.5 | G27: D q21 Total | I27: 17512.5
B28: I Q21 | C28: 46052 | D28: 363930 | G28: I Q21 | H28: 46052 | I28: 363930
B29: I Q21 Total | D29: 363930 | G29: I Q21 Total | I29: 363930
A30: 2026 Total | D30: 381442.5 | F30: 2026 Total | I30: 381442.5
A31: Grand Total | D31: 2667945.4 | F31: Grand Total | I31: 2667945.4

Sheet MTN Payment Schedule Summary
B1: Payment Schedule
B2: Date | C2: Amount | D2: Project | E2: Premier&Moto Model | F2: Note | G2: Type
B3: 45856 | C3: 13827.5 | D3: MNQ15 EU | E3: MNQ1525-30W-E | F3: 50% of the development cost | G3: D q15
B4: 45856 | C4: 52200 | D4: MNQ15 EU | E4: MNQ1525-30W-E | F4: 30% Deposit of 5K PO | G4: I Q15
B5: 45856 | C5: 1225 | D5: MNQ15 ANZ | E5: MNQ1525-30W-A | F5: 50% of the development cost | G5: D q15
B6: 45856 | C6: 52500 | D6: MNQ15 ANZ | E6: MNQ1525-30W-A | F6: 30% Deposit of 5K PO | G6: I Q15
B7: 45858 | C7: 50000 | D7: MNQ15&MNQ21 DDR | E7: MNQ15&MNQ21 | F7: Deposit for 100K 1GB DDR4 | G7: I
B8: 45870 | C8: 73223.35 | D8: MNQ21 US | E8: MNQ1525-30W-U | F8: 50% of the development cost | G8: D q21
B9: 45870 | C9: 16287.5 | D9: MNQ21 EU | E9: MNQ2126-30W-E | F9: 50% of the development cost | G9: Dq21
B10: 45870 | C10: 1225 | D10: MNQ21 ANZ | E10: MNQ2126-30W-A | F10: 50% of the development cost | G10: Dq21
B11: 45881 | C11: 12350 | D11: MNQ1525 | E11: MNQ1525-30W-U | F11: 200Units Engneer sample and shipping cost | G11: Dq21
B12: 45930 | C12: 71118.69 | D12: MNQ1525 | E12: MNQ1525-30W-U | F12: Rest payment of the development cost | G12: D q15
B13: 45930 | C13: 249000 | D13: MNQ1525 | E13: MNQ1525-30W-U | F13: Rest payment of the 10K PO before shippment | G13: I Q15
B14: 45930 | C14: 13827.5 | D14: MNQ15 EU | E14: MNQ1525-30W-E | F14: Rest payment of the development cost | G14: D q15
... B18: 45930 | C18: 129000 | D18: MNQ21 US | E18: MNQ1525-30W-U | F18: 30% Deposit of 5K PO | G18: I Q21
B19: 45960 | C19: 77850 | D19: MNQ21 EU | E19: MNQ2126-30W-E | F19: 30% Deposit of 3K PO | G19: I Q21 | H19: =C19+C20 -> 155970
B20: 45960 | C20: 78120 | D20: MNQ21 ANZ | E20: MNQ2126-30W-A | F20: 30% Deposit of 3K PO | G20: I Q21
B21: 46021 | C21: 73223.35 | D21: MNQ21 US | E21: MNQ1525-30W-U | F21: Rest payment of the development cost | G21: D q21
B22: 46021 | C22: 301000 | D22: MNQ21 US | E22: MNQ1525-30W-U | F22: Rest payment of 5K PO | G22: I Q21
B23: 46052 | C23: 16287.5 | D23: MNQ21 EU | E23: MNQ2126-30W-E | F23: Rest payment of the development cost | G23: D q21
B24: 46052 | C24: 181650 | D24: MNQ21 EU | E24: MNQ2126-30W-E | F24: Rest payment of 3K PO | G24: I Q21 | I24: =C24+C25+C26 -> 365155
B25: 46052 | C25: 1225 | D25: MNQ21 ANZ | E25: MNQ2126-30W-A | F25: Rest payment of the development cost | G25: D q21
B26: 46052 | C26: 182280 | D26: MNQ21 ANZ | E26: MNQ2126-30W-A | F26: Rest payment of 3K PO | G26: I Q21
B27: 45870 | C27: 41400 | D27: MNQ15 US 2pcs Packing | E27: MNQ1525-D30W-U | F27: MNQ1525-D30W-U 2K PO 30% Deposit | G27: I Q15
B28: 45870 | C28: 62100 | D28: MNQ15US 3pcs Packing | E28: MNQ1525-M30W-U | F28: MNQ1525-M30W-U 2K PO 30% Deposit | G28: I Q15
B29: 45960 | C29: 96600 | D29: MNQ15 US 2pcs Packing | E29: MNQ1525-D30W-U | F29: MNQ1525-D30W-U 2K PO Rest Payment | G29: I Q15
B30: 45960 | C30: 144900 | D30: MNQ15US 3pcs Packing | E30: MNQ1525-M30W-U | F30: MNQ1525-M30W-U 2K PO Rest Payment | G30: I Q15
B31: 45870 | C31: 51600 | D31: MNQ21 US 2pcs Packing | E31: MNQ2126-D30W-U | F31: MNQ2126-D30W-U 1K PO 30% Deposit | G31: I Q21
B32: 45870 | C32: 77400 | D32: MNQ21 US 3pcs Packing | E32: MNQ2126-M30W-U | F32: MNQ2126-M30W-U 1K PO 30% Deposit | G32: I Q21
B33: 46021 | C33: 120400 | D33: MNQ21 US 2pcs Packing | E33: MNQ2126-D30W-U | F33: MNQ2126-D30W-U 1K PO Rest Payment | G33: I Q21 | I33: =C34+C33+C22 -> 602000
B34: 46021 | C34: 180600 | D34: MNQ21 US 3pcs Packing | E34: MNQ2126-M30W-U | F34: MNQ2126-M30W-U 1K PO Rest Payment | G34: I Q21
C35: =SUM(C3:C34) -> 2667945.4
C36: ='Weekly Spend'!#REF!+'Weekly Spend'!N30+'Weekly Spend'!N28 -> #REF!
C37: =C35-C36 -> #REF!

Sheet New Gryphon SOW CLS Optimized
A1: Projects
J2: Resource Cost Table (Monthly)
A3: SOW #5 | B3: Resources | C3: May | D3: June | E3: July | F3: Aug | G3: Sept | H3: Comments | J3: Firmware | K3: 6500
A4: Linux, SPF12.5, Open WRT Security Updates | B4: Firmware | C4: 0 | D4: 0 | E4: 0 | F4: 0 | G4: 0 | H4: No Security or Open WRT update until after MQ14 is done | J4: App | K4: 6500
B5: App | C5: 0 | D5: 0 | E5: 0 | F5: 0 | G5: 0 | J5: QA | K5: 4000
B6: QA | C6: 0 | D6: 0 | E6: 0 | F6: 0 | G6: 0 | J6: Project Mgr | K6: 16000
B7: Project Mgr | C7: 0 | D7: 0 | E7: 0 | F7: 0 | G7: 0 | J7: AWS | K7: 8000
J8: Tier 2 Support | K8: 5000
A9: Total Cost | C9: =C4*$K$3+C5*$K$4+C6*$K$5+C7*$K$6 -> 0 | D9: =D4*$K$3+D5*$K$4+D6*$K$5+D7*$K$6 -> 0 | E9: =E4*$K$3+E5*$K$4+E6*$K$5+E7*$K$6 -> 0 | F9: =F4*$K$3+F5*$K$4+F6*$K$5+F7*$K$6 -> 0 | G9: =G4*$K$3+G5*$K$4+G6*$K$5+G7*$K$6 -> 0
A12: SOW #6 | B12: Resources | C12: May | D12: June | E12: July | F12: Aug | G12: Sept
A13: MQ20 and 8972 release and Maintenance 1. Slow deployment of 8702 from Minim to Premier server. 2. Bug triage, rootcause, fix if resonable issues | B13: Firmware | C13: 1 | D13: 1 | E13: 1 | F13: 1 | G13: 1 | H13: 1. Launching MQ20 in July
B14: App | C14: 0.5 | D14: 0.5 | E14: 0.5 | F14: 0.5 | G14: 0.5 | H14: 2 May-June: Factory support and
B15: QA | C15: 1 | D15: 1 | E15: 1 | F15: 1 | G15: 1 | H15: 8702 slow deployment
B16: Tier 2 Support | C16: 0 | D16: 0.25 | E16: 0.5 | F16: 0.5 | G16: 0.5 | H16: 3. EU language update and RF update
B17: Project Mgr | C17: 0.25 | H17: 4. No new features and no major issues
A18: Total Cost | C18: =C13*$K$3+C14*$K$4+C15*$K$5+C16*$K$8+C17*K6 -> 17750 | D18: =D13*$K$3+D14*$K$4+D15*$K$5+D16*$K$8 -> 15000 | E18: =E13*$K$3+E14*$K$4+E15*$K$5+E16*$K$8 -> 16250 | F18: =F13*$K$3+F14*$K$4+F15*$K$5+F16*$K$8 -> 16250 | G18: =G13*$K$3+G14*$K$4+G15*$K$5+G16*$K$8 -> 16250 | I18: =SUM(C18:G18) -> 81500
A21: SOW #7 | B21: Resources | C21: May | D21: June | E21: July | F21: Aug | G21: Sept
A22: MQ15 1. This will be on SPF12.5, with updated OpenWRT and Linux kernel. 2. Same Firmware will be tested with MQ20 | B22: Firmware | C22: 1 | D22: 3 | E22: 3 | F22: 2 | G22: 2 | H22: 1. Ramp in May
B23: App | C23: 0 | D23: 0.5 | E23: 0.5 | F23: 0.5 | G23: 0.5 | H23: 2. No or minimal CSL involvement
B24: QA | C24: 0 | D24: 1 | E24: 2 | F24: 4 | G24: 4 | H24: 3. Any change in factory schedule,
B25: Project Mgr | C25: 0.25 | D25: 0.5 | E25: 0.5 | F25: 0.5 | G25: 0.5 | H25: req change, accptance criteria will
H26: impact this number.
A27: Total Cost | C27: =C22*$K$3+C23*$K$4+C24*$K$5+C25*$K$6 -> 10500 | D27: =D22*$K$3+D23*$K$4+D24*$K$5+D25*$K$6 -> 34750 | E27: =E22*$K$3+E23*$K$4+E24*$K$5+E25*$K$6 -> 38750 | F27: =F22*$K$3+F23*$K$4+F24*$K$5+F25*$K$6 -> 40250 | G27: =G22*$K$3+G23*$K$4+G24*$K$5+G25*$K$6 -> 40250 | H27: No New features | I27: =SUM(C27:G27) -> 164500
A30: SOW #8 | B30: Resources | C30: May | D30: June | E30: July | F30: Aug | G30: Sept
A31: 1. AWS Server Support for all projects including MQ20, 8702, and MQ15, 2. EU support 2.New AWS VPN server with EU support | B31: AWS | C31: 2 | D31: 2 | E31: 2 | F31: 2 | G31: 2
B32: App
B33: QA
B34: Project Mgr | H34: covered by #7
A36: Total Cost | C36: =C31*$K$7 -> 16000 | D36: =D31*$K$7 -> 16000 | E36: =E31*$K$7 -> 16000 | F36: =F31*$K$7 -> 16000 | G36: =G31*$K$7 -> 16000 | I36: =SUM(C36:G36) -> 80000
A39: SOW #9 (optional) | B39: Resources | C39: May | D39: June | E39: July | F39: Aug | G39: Sept
A40: Homebound Feature Upgrade 1. New AWS VPN server with EU covered by #8 2. Re-Branding HomeBound App 3. FUT 1-month in July | B40: Firmware | F40: 1 | G40: 0.5 | H40: 1. No CLS
B41: App | F41: 0.5 | G41: 0.5 | H41: 2. 1 month integration, 1 month FUT
B42: QA | F42: 1 | G42: 1 | H42: 3. App rebranding limited to logo
B43: Project Mgr | F43: 0.15 | G43: 0.15 | H43: and color. No MULTI Lang support
B44: AWS | F44: 0 | G44: 0 | H44: Covered by #8
A45: Total Cost | C45: =C40*$K$7 -> 0 | D45: =D40*$K$7 -> 0 | E45: =E40*$K$7 -> 0 | F45: =F40*$K$3+F41*$K$4+F42*$K$5+F43*$K$6 -> 16150 | G45: =G40*$K$3+G41*$K$4+G42*$K$5+G43*$K$6 -> 12900 | I45: =SUM(C45:G45) -> 29050
A48: Total Cost (All) | C48: =C45+C36+C27+C18+C9 -> 44250 | D48: =D45+D36+D27+D18+D9 -> 65750 | E48: =E45+E36+E27+E18+E9 -> 71000 | F48: =F45+F36+F27+F18+F9 -> 88650 | G48: =G45+G36+G27+G18+G9 -> 85400 | I48: =SUM(C48:G48) -> 355050
F49: =F48-F45 -> 72500 | G49: =G48-G45 -> 72500
C51: 56000 | D51: =470000-326000 -> 144000 | E51: =E48/4 -> 17750 | F51: =F48/4 -> 22162.5 | G51: =G48/4 -> 21350

Sheet Cash in v1
D1: 1 | E1: =D1+1 -> 2 | F1: =E1+1 -> 3 | G1: =F1+1 -> 4 | H1: =G1+1 -> 5 | I1: =H1+1 -> 6 | J1: =I1+1 -> 7 | K1: =J1+1 -> 8 | L1: =K1+1 -> 9 | ... P1: =O1+1 -> 13 | Q1: Post 13 Week
B2: Week Ending | C2: Week # | D2: ="Week"&" "&D1 -> Week 1 | E2: ="Week"&" "&E1 -> Week 2 | F2: ="Week"&" "&F1 -> Week 3 | G2: ="Week"&" "&G1 -> Week 4 | H2: ="Week"&" "&H1 -> Week 5 | I2: ="Week"&" "&I1 -> Week 6 | J2: ="Week"&" "&J1 -> Week 7 | K2: ="Week"&" "&K1 -> Week 8 | ... P2: ="Week"&" "&P1 -> Week 13 | R2: ="Week"&" "&R1 -> Week | S2: ="Week"&" "&S1 -> Week | T2: ="Week"&" "&T1 -> Week | U2: ="Week"&" "&U1 -> Week | V2: ="Week"&" "&V1 -> Week | W2: ="Week"&" "&W1 -> Week | X2: ="Week"&" "&X1 -> Week | Y2: ="Week"&" "&Y1 -> Week | ... AN2: ="Week"&" "&AN1 -> Week
C3: Monday of week | D3: ='CURRENT FORECAST START DATE'!C4 -> 45971 | E3: =D3+7 -> 45978 | F3: =E3+7 -> 45985 | G3: =F3+7 -> 45992 | H3: =G3+7 -> 45999 | I3: =H3+7 -> 46006 | J3: =I3+7 -> 46013 | K3: =J3+7 -> 46020 | L3: =K3+7 -> 46027 | ... P3: =O3+7 -> 46055 | R3: =P3+7 -> 46062 | S3: =R3+7 -> 46069 | T3: =S3+7 -> 46076 | U3: =T3+7 -> 46083 | V3: =U3+7 -> 46090 | W3: =V3+7 -> 46097 | X3: =W3+7 -> 46104 | Y3: =X3+7 -> 46111 | Z3: =Y3+7 -> 46118 | ... AN3: =AM3+7 -> 46216
B4: OPERATING CASH INFLOWS
B5: Operating Cash Receipts
B6: Customer Cash Receipts from A/R | C6: AR Aging | D6: ='Cash in detail'!K30 -> 56250 | E6: ='Cash in detail'!L30 -> 56250 | F6: ='Cash in detail'!M30 -> 80000 | G6: ='Cash in detail'!N30 -> 80000 | H6: ='Cash in detail'!O30 -> 80000 | I6: ='Cash in detail'!P30 -> 80000 | J6: ='Cash in detail'!Q30 -> 125000 | K6: ='Cash in detail'!R30 -> 125000 | ... P6: ='Cash in detail'!W30 -> 212500 | R6: ='Cash in detail'!X30 -> 212500 | S6: ='Cash in detail'!Y30 -> 225000 | T6: ='Cash in detail'!Z30 -> 225000 | U6: ='Cash in detail'!AA30 -> 225000 | V6: ='Cash in detail'!AB30 -> 225000 | W6: ='Cash in detail'!AC30 -> 250000 | X6: ='Cash in detail'!AD30 -> 250000 | Y6: ='Cash in detail'!AE30 -> 250000 | ... AB6: ='Cash in detail'!AH30 -> 125000 | AC6: =_xlfn.XLOOKUP(AC3, 'Cash in detail'!$G$5:$CU$5, 'Cash in detail'!$G$8:$CU$8) -> 857127.77 | AD6: =_xlfn.XLOOKUP(AD3, 'Cash in detail'!$G$5:$CU$5, 'Cash in detail'!$G$8:$CU$8) -> 1437228.3 | AE6: =_xlfn.XLOOKUP(AE3, 'Cash in detail'!$G$5:$CU$5, 'Cash in detail'!$G$8:$CU$8) -> 1437228.3 | AF6: =_xlfn.XLOOKUP(AF3, 'Cash in detail'!$G$5:$CU$5, 'Cash in detail'!$G$8:$CU$8) -> 1437228.3 | AG6: =_xlfn.XLOOKUP(AG3, 'Cash in detail'!$G$5:$CU$5, 'Cash in detail'!$G$8:$CU$8) -> 1437228.3 | AH6: =_xlfn.XLOOKUP(AH3, 'Cash in detail'!$G$5:$CU$5, 'Cash in detail'!$G$8:$CU$8) -> 1414237.6 | AI6: =_xlfn.XLOOKUP(AI3, 'Cash in detail'!$G$5:$CU$5, 'Cash in detail'!$G$8:$CU$8) -> 1414237.6 | AJ6: =_xlfn.XLOOKUP(AJ3, 'Cash in detail'!$G$5:$CU$5, 'Cash in detail'!$G$8:$CU$8) -> 1414237.6 | ... AN6: =_xlfn.XLOOKUP(AN3, 'Cash in detail'!$G$5:$CU$5, 'Cash in detail'!$G$8:$CU$8) -> 1920654.7
B7: Customer Forecasted Receipts from Backlog | C7: AR (Backlog) | K7: 0 | L7: 0 | M7: 0 | N7: 0 | O7: 0 | P7: 0 | R7: 1 | S7: 2 | T7: 3 | U7: 4 | V7: 5 | W7: 6 | X7: 7 | Y7: 8 | Z7: 9 | AA7: 10 | AB7: 11 | AC7: 12 | AD7: 13 | AE7: 14 | AF7: 15 | AG7: 16 | AH7: 17 | AI7: 18 | AJ7: 19 | AK7: 20 | AL7: 21 | AM7: 22 | AN7: 23
B8: Customer Forecasted Receipts from Sales Forecast | C8: AR (Sales Forecast)
B9: Other, non-customer related inflows | C9: Varies | D9: 0 | E9: 0 | F9: 0 | G9: 0 | H9: 0 | I9: 0 | J9: 0
B10: TOTAL INCOMING CASH | D10: =SUM(D6:D9) -> 56250 | E10: =SUM(E6:E9) -> 56250 | F10: =SUM(F6:F9) -> 80000 | G10: =SUM(G6:G9) -> 80000 | H10: =SUM(H6:H9) -> 80000 | I10: =SUM(I6:I9) -> 80000 | J10: =SUM(J6:J9) -> 125000 | K10: =SUM(K6:K9) -> 125000 | ... P10: =SUM(P6:P9) -> 212500 | R10: =SUM(R6:R9) -> 212501 | S10: =SUM(S6:S9) -> 225002 | T10: =SUM(T6:T9) -> 225003 | U10: =SUM(U6:U9) -> 225004 | V10: =SUM(V6:V9) -> 225005 | W10: =SUM(W6:W9) -> 250006 | X10: =SUM(X6:X9) -> 250007 | Y10: =SUM(Y6:Y9) -> 250008 | ... AN10: =SUM(AN6:AN9) -> 1920677.7
B12: OPERATING CASH DISBURSEMENTS
B13: Must Pays
B14: Labor | C14: Biweekly Payroll | D14: {=INDEX('Weekly Spend'!$F$86:$CV$94,MATCH($B14,'Weekly Spend'!$F$86:$F$94,0),MATCH(D$3,'Weekly Spend'!$F$86:$CV$86,0))} -> 0 | E14: {=INDEX('Weekly Spend'!$F$86:$CV$94,MATCH($B14,'Weekly Spend'!$F$86:$F$94,0),MATCH(E$3,'Weekly Spend'!$F$86:$CV$86,0))} -> 86474.362 | F14: {=INDEX('Weekly Spend'!$F$86:$CV$94,MATCH($B14,'Weekly Spend'!$F$86:$F$94,0),MATCH(F$3,'Weekly Spend'!$F$86:$CV$86,0))} -> 4500 | G14: {=INDEX('Weekly Spend'!$F$86:$CV$94,MATCH($B14,'Weekly Spend'!$F$86:$F$94,0),MATCH(G$3,'Weekly Spend'!$F$86:$CV$86,0))} -> 98566.692 | H14: {=INDEX('Weekly Spend'!$F$86:$CV$94,MATCH($B14,'Weekly Spend'!$F$86:$F$94,0),MATCH(H$3,'Weekly Spend'!$F$86:$CV$86,0))} -> 0 | I14: {=INDEX('Weekly Spend'!$F$86:$CV$94,MATCH($B14,'Weekly Spend'!$F$86:$F$94,0),MATCH(I$3,'Weekly Spend'!$F$86:$CV$86,0))} -> 93566.692 | J14: {=INDEX('Weekly Spend'!$F$86:$CV$94,MATCH($B14,'Weekly Spend'!$F$86:$F$94,0),MATCH(J$3,'Weekly Spend'!$F$86:$CV$86,0))} -> 0 | K14: {=INDEX('Weekly Spend'!$F$86:$CV$94,MATCH($B14,'Weekly Spend'!$F$86:$F$94,0),MATCH(K$3,'Weekly Spend'!$F$86:$CV$86,0))} -> 92316.692 | ... P14: {=INDEX('Weekly Spend'!$F$86:$CV$94,MATCH($B14,'Weekly Spend'!$F$86:$F$94,0),MATCH(P$3,'Weekly Spend'!$F$86:$CV$86,0))} -> 0 | R14: {=INDEX('Weekly Spend'!$F$86:$CV$94,MATCH($B14,'Weekly Spend'!$F$86:$F$94,0),MATCH(R$3,'Weekly Spend'!$F$86:$CV$86,0))} -> 103716.69 | S14: {=INDEX('Weekly Spend'!$F$86:$CV$94,MATCH($B14,'Weekly Spend'!$F$86:$F$94,0),MATCH(S$3,'Weekly Spend'!$F$86:$CV$86,0))} -> 0 | T14: {=INDEX('Weekly Spend'!$F$86:$CV$94,MATCH($B14,'Weekly Spend'!$F$86:$F$94,0),MATCH(T$3,'Weekly Spend'!$F$86:$CV$86,0))} -> 100813.69 | U14: {=INDEX('Weekly Spend'!$F$86:$CV$94,MATCH($B14,'Weekly Spend'!$F$86:$F$94,0),MATCH(U$3,'Weekly Spend'!$F$86:$CV$86,0))} -> 0 | V14: {=INDEX('Weekly Spend'!$F$86:$CV$94,MATCH($B14,'Weekly Spend'!$F$86:$F$94,0),MATCH(V$3,'Weekly Spend'!$F$86:$CV$86,0))} -> 91813.692 | W14: {=INDEX('Weekly Spend'!$F$86:$CV$94,MATCH($B14,'Weekly Spend'!$F$86:$F$94,0),MATCH(W$3,'Weekly Spend'!$F$86:$CV$86,0))} -> 0 | X14: {=INDEX('Weekly Spend'!$F$86:$CV$94,MATCH($B14,'Weekly Spend'!$F$86:$F$94,0),MATCH(X$3,'Weekly Spend'!$F$86:$CV$86,0))} -> 100813.69 | Y14: {=INDEX('Weekly Spend'!$F$86:$CV$94,MATCH($B14,'Weekly Spend'!$F$86:$F$94,0),MATCH(Y$3,'Weekly Spend'!$F$86:$CV$86,0))} -> 0 | ... AN14: {=INDEX('Weekly Spend'!$F$86:$CV$94,MATCH($B14,'Weekly Spend'!$F$86:$F$94,0),MATCH(AN$3,'Weekly Spend'!$F$86:$CV$86,0))} -> 91716.692
B15: OpEx | C15: Invoices | D15: {=INDEX('Weekly Spend'!$F$86:$CV$94,MATCH($B15,'Weekly Spend'!$F$86:$F$94,0),MATCH(D$3,'Weekly Spend'!$F$86:$CV$86,0))} -> 5505.8 | E15: {=INDEX('Weekly Spend'!$F$86:$CV$94,MATCH($B15,'Weekly Spend'!$F$86:$F$94,0),MATCH(E$3,'Weekly Spend'!$F$86:$CV$86,0))} -> 5287 | F15: {=INDEX('Weekly Spend'!$F$86:$CV$94,MATCH($B15,'Weekly Spend'!$F$86:$F$94,0),MATCH(F$3,'Weekly Spend'!$F$86:$CV$86,0))} -> 20097.5 | G15: {=INDEX('Weekly Spend'!$F$86:$CV$94,MATCH($B15,'Weekly Spend'!$F$86:$F$94,0),MATCH(G$3,'Weekly Spend'!$F$86:$CV$86,0))} -> 67163 | H15: {=INDEX('Weekly Spend'!$F$86:$CV$94,MATCH($B15,'Weekly Spend'!$F$86:$F$94,0),MATCH(H$3,'Weekly Spend'!$F$86:$CV$86,0))} -> 4500 | I15: {=INDEX('Weekly Spend'!$F$86:$CV$94,MATCH($B15,'Weekly Spend'!$F$86:$F$94,0),MATCH(I$3,'Weekly Spend'!$F$86:$CV$86,0))} -> 14500 | J15: {=INDEX('Weekly Spend'!$F$86:$CV$94,MATCH($B15,'Weekly Spend'!$F$86:$F$94,0),MATCH(J$3,'Weekly Spend'!$F$86:$CV$86,0))} -> 54500 | K15: {=INDEX('Weekly Spend'!$F$86:$CV$94,MATCH($B15,'Weekly Spend'!$F$86:$F$94,0),MATCH(K$3,'Weekly Spend'!$F$86:$CV$86,0))} -> 26500 | ... P15: {=INDEX('Weekly Spend'!$F$86:$CV$94,MATCH($B15,'Weekly Spend'!$F$86:$F$94,0),MATCH(P$3,'Weekly Spend'!$F$86:$CV$86,0))} -> 49625 | R15: {=INDEX('Weekly Spend'!$F$86:$CV$94,MATCH($B15,'Weekly Spend'!$F$86:$F$94,0),MATCH(R$3,'Weekly Spend'!$F$86:$CV$86,0))} -> 4625 | S15: {=INDEX('Weekly Spend'!$F$86:$CV$94,MATCH($B15,'Weekly Spend'!$F$86:$F$94,0),MATCH(S$3,'Weekly Spend'!$F$86:$CV$86,0))} -> 4625 | T15: {=INDEX('Weekly Spend'!$F$86:$CV$94,MATCH($B15,'Weekly Spend'!$F$86:$F$94,0),MATCH(T$3,'Weekly Spend'!$F$86:$CV$86,0))} -> 46625 | U15: {=INDEX('Weekly Spend'!$F$86:$CV$94,MATCH($B15,'Weekly Spend'!$F$86:$F$94,0),MATCH(U$3,'Weekly Spend'!$F$86:$CV$86,0))} -> 47940.8 | V15: {=INDEX('Weekly Spend'!$F$86:$CV$94,MATCH($B15,'Weekly Spend'!$F$86:$F$94,0),MATCH(V$3,'Weekly Spend'!$F$86:$CV$86,0))} -> 7940.8 | W15: {=INDEX('Weekly Spend'!$F$86:$CV$94,MATCH($B15,'Weekly Spend'!$F$86:$F$94,0),MATCH(W$3,'Weekly Spend'!$F$86:$CV$86,0))} -> 7940.8 | X15: {=INDEX('Weekly Spend'!$F$86:$CV$94,MATCH($B15,'Weekly Spend'!$F$86:$F$94,0),MATCH(X$3,'Weekly Spend'!$F$86:$CV$86,0))} -> 7940.8 | Y15: {=INDEX('Weekly Spend'!$F$86:$CV$94,MATCH($B15,'Weekly Spend'!$F$86:$F$94,0),MATCH(Y$3,'Weekly Spend'!$F$86:$CV$86,0))} -> 39940.8 | ... AN15: {=INDEX('Weekly Spend'!$F$86:$CV$94,MATCH($B15,'Weekly Spend'!$F$86:$F$94,0),MATCH(AN$3,'Weekly Spend'!$F$86:$CV$86,0))} -> 7245
B16: R&D | C16: Invoices | D16: {=INDEX('Weekly Spend'!$F$86:$CV$94,MATCH($B16,'Weekly Spend'!$F$86:$F$94,0),MATCH(D$3,'Weekly Spend'!$F$86:$CV$86,0))} -> 0 | E16: {=INDEX('Weekly Spend'!$F$86:$CV$94,MATCH($B16,'Weekly Spend'!$F$86:$F$94,0),MATCH(E$3,'Weekly Spend'!$F$86:$CV$86,0))} -> 0 | F16: {=INDEX('Weekly Spend'!$F$86:$CV$94,MATCH($B16,'Weekly Spend'!$F$86:$F$94,0),MATCH(F$3,'Weekly Spend'!$F$86:$CV$86,0))} -> 0 | G16: {=INDEX('Weekly Spend'!$F$86:$CV$94,MATCH($B16,'Weekly Spend'!$F$86:$F$94,0),MATCH(G$3,'Weekly Spend'!$F$86:$CV$86,0))} -> 0 | H16: {=INDEX('Weekly Spend'!$F$86:$CV$94,MATCH($B16,'Weekly Spend'!$F$86:$F$94,0),MATCH(H$3,'Weekly Spend'!$F$86:$CV$86,0))} -> 0 | I16: {=INDEX('Weekly Spend'!$F$86:$CV$94,MATCH($B16,'Weekly Spend'!$F$86:$F$94,0),MATCH(I$3,'Weekly Spend'!$F$86:$CV$86,0))} -> 0 | J16: {=INDEX('Weekly Spend'!$F$86:$CV$94,MATCH($B16,'Weekly Spend'!$F$86:$F$94,0),MATCH(J$3,'Weekly Spend'!$F$86:$CV$86,0))} -> 0 | K16: {=INDEX('Weekly Spend'!$F$86:$CV$94,MATCH($B16,'Weekly Spend'!$F$86:$F$94,0),MATCH(K$3,'Weekly Spend'!$F$86:$CV$86,0))} -> 0 | ... P16: {=INDEX('Weekly Spend'!$F$86:$CV$94,MATCH($B16,'Weekly Spend'!$F$86:$F$94,0),MATCH(P$3,'Weekly Spend'!$F$86:$CV$86,0))} -> 0 | R16: {=INDEX('Weekly Spend'!$F$86:$CV$94,MATCH($B16,'Weekly Spend'!$F$86:$F$94,0),MATCH(R$3,'Weekly Spend'!$F$86:$CV$86,0))} -> 0 | S16: {=INDEX('Weekly Spend'!$F$86:$CV$94,MATCH($B16,'Weekly Spend'!$F$86:$F$94,0),MATCH(S$3,'Weekly Spend'!$F$86:$CV$86,0))} -> 0 | T16: {=INDEX('Weekly Spend'!$F$86:$CV$94,MATCH($B16,'Weekly Spend'!$F$86:$F$94,0),MATCH(T$3,'Weekly Spend'!$F$86:$CV$86,0))} -> 0 | U16: {=INDEX('Weekly Spend'!$F$86:$CV$94,MATCH($B16,'Weekly Spend'!$F$86:$F$94,0),MATCH(U$3,'Weekly Spend'!$F$86:$CV$86,0))} -> 0 | V16: {=INDEX('Weekly Spend'!$F$86:$CV$94,MATCH($B16,'Weekly Spend'!$F$86:$F$94,0),MATCH(V$3,'Weekly Spend'!$F$86:$CV$86,0))} -> 0 | W16: {=INDEX('Weekly Spend'!$F$86:$CV$94,MATCH($B16,'Weekly Spend'!$F$86:$F$94,0),MATCH(W$3,'Weekly Spend'!$F$86:$CV$86,0))} -> 0 | X16: {=INDEX('Weekly Spend'!$F$86:$CV$94,MATCH($B16,'Weekly Spend'!$F$86:$F$94,0),MATCH(X$3,'Weekly Spend'!$F$86:$CV$86,0))} -> 0 | Y16: {=INDEX('Weekly Spend'!$F$86:$CV$94,MATCH($B16,'Weekly Spend'!$F$86:$F$94,0),MATCH(Y$3,'Weekly Spend'!$F$86:$CV$86,0))} -> 0 | ... AN16: {=INDEX('Weekly Spend'!$F$86:$CV$94,MATCH($B16,'Weekly Spend'!$F$86:$F$94,0),MATCH(AN$3,'Weekly Spend'!$F$86:$CV$86,0))} -> 0
